Workbook
Name CFA: '31Mar24'!#REF!
Name CFB: '31Mar24'!#REF!
Name CFC: '31Mar24'!#REF!
Name CFD: '31Mar24'!#REF!
Name CFE: '31Mar24'!#REF!
Name CFF: '31Mar24'!#REF!
Name CFG: '31Mar24'!#REF!
Name CFH: '31Mar24'!#REF!
Name CFI: '31Mar24'!#REF!
Name Chol: 'ZCB rates'!#REF!
Name dates: 'ZCB rates'!$B$4:$B$319
Name days_in_year: Assumptions!$D$14
Name DeltaT: 'ZCB rates'!#REF!
Name EPS: 'ZCB rates'!#REF!
Name Hist_conf: #REF!
Name Lambda: Assumptions!$D$19
Name Lambda_hyb: #REF!
Name month_in_a_year: Assumptions!$D$16
Name months_in_a_year: Assumptions!$D$16
Name N_obs_EWMA: #REF!
Name N_obs_hist: #REF!
Name nodes: #REF!
Name Par_conf: #REF!
Name RET_header: 'ZCB rates'!$M$3:$Q$3
Name ZCP_header: 'ZCB rates'!$H$3:$L$3
Name ZCR_header: 'ZCB rates'!$R$3:$V$3

Sheet Cover
C8: Evaluating market risk for fixed income securities
C11: Group 15 - Risk Management and Value in Banking and Insurance
C12: MSc in Finance - 2025/2026
C15: Lorenzo Passioni, Christian Moresco, Raffaele Perillo, Chiara Sacconaghi, Ludovico Raspanti

Sheet Summary
B2: Summary table
B4: Select the desired inputs to below obtain the VaR in cell C9
B5: Date | C5: CI | D5: Method
B6: 45382 | C6: 0.95 | D6: Hybrid approach
B8: Var Value | C8: {=IFERROR(INDEX($C$14:$F$17,MATCH(B6,$B$14:$B$17,0),MATCH(1,(LOOKUP(COLUMN($C$11:$F$11),COLUMN($C$11:$F$11)/($C$11:$F$11<>""),$C$11:$F$11)=D6)*($C$13:$F$13=C6),0)),"Please select the inputs above")} -> 51.377143
C11: Parametric approach (EWMA) | E11: Hybrid approach
C12: Confidence interval
B13: Evaluation date | C13: 0.95 | D13: 0.99 | E13: 0.95 | F13: 0.99
B14: 45382 | C14: =+'31Mar24'!C106 -> 54.324429 | D14: =+'31Mar24'!D106 -> 76.832077 | E14: =+'31Mar24'!C120 -> 51.377143 | F14: =+'31Mar24'!D120 -> 60.071147
B15: 45473 | C15: =+'30Jun24'!C106 -> 35.75704 | D15: =+'30Jun24'!D106 -> 50.571863 | E15: =+'30Jun24'!C120 -> 28.40084 | F15: =+'30Jun24'!D120 -> 53.008952
B16: 45565 | C16: =+'30Sep24'!C106 -> 34.971916 | D16: =+'30Sep24'!D106 -> 49.461449 | E16: =+'30Sep24'!C120 -> 29.42962 | F16: =+'30Sep24'!D120 -> 48.799783
B17: 45657 | C17: =+'31Dec24'!C106 -> 31.689083 | D17: =+'31Dec24'!D106 -> 44.818475 | E17: =+'31Dec24'!C121 -> 27.190894 | F17: =+'31Dec24'!D121 -> 47.085678

Sheet Sheet1
B4: To be selected | D4: To be selected | F4: To be selected
B5: 45382 | D5: 0.95 | F5: Parametric approach (EWMA)
B6: 45473 | D6: 0.99 | F6: Hybrid approach
B7: 45565
B8: 45657

Sheet Inputs -->
D9: Inputs

Sheet Assumptions
B2: Assumptions
B6: Cash flows of the two securities
B7: Security 7 | D7: Dates | E7: 45657 | F7: 45838 | G7: 46022 | H7: 46203 | I7: 46387
D8: Cash flows | E8: 200 | F8: 200 | G8: 200 | H8: 200 | I8: 10200
B10: Security 10 | D10: Dates | E10: 45747 | F10: 45838 | G10: 46022 | H10: 46203
D11: Cash flows | E11: 150 | F11: 150 | G11: 150 | H11: 5150
B14: Days in a year | D14: 365
B16: Months in a year | D16: 12
B19: Lambda | D19: 0.94

Sheet ZCB rates
C2: Zero coupon rates (continuously compounded) | H2: ZCB Prices | M2: Log returns (weekly) | R2: ZCB rates (annually compounded rates)
B3: Date | C3: 3 | D3: 6 | E3: 12 | F3: 24 | G3: 60 | H3: 3 | I3: 6 | J3: 12 | K3: 24 | L3: 60 | M3: 3 | N3: 6 | O3: 12 | P3: 24 | Q3: 60 | R3: 3 | S3: 6 | T3: 12 | U3: 24 | V3: 60
B4: 43829 | C4: -0.005071695 | D4: -0.004933335 | E4: -0.004634075 | F4: -0.003960425 | G4: -0.001580295 | H4: =EXP(-0.25*C4) -> 1.0012687 | I4: =EXP(-0.5*D4) -> 1.0024697 | J4: =EXP(-1*E4) -> 1.0046448 | K4: =EXP(-2*F4) -> 1.0079523 | L4: =EXP(-5*G4) -> 1.0079328 | R4: =+EXP(C4)-1 -> -0.0050588557 | S4: =+EXP(D4)-1 -> -0.0049211861 | T4: =+EXP(E4)-1 -> -0.0046233542 | U4: =+EXP(F4)-1 -> -0.0039525929 | V4: =+EXP(G4)-1 -> -0.001579047
B5: 43836 | C5: -0.005241518 | D5: -0.005084434 | E5: -0.004755086 | F5: -0.004045126 | G5: -0.001664948 | H5: =EXP(-0.25*C5) -> 1.0013112 | I5: =EXP(-0.5*D5) -> 1.0025455 | J5: =EXP(-1*E5) -> 1.0047664 | K5: =EXP(-2*F5) -> 1.0081231 | L5: =EXP(-5*G5) -> 1.0083595 | M5: =+LN(H5/H4) -> 4.245575e-05 | N5: =+LN(I5/I4) -> 7.55495e-05 | O5: =+LN(J5/J4) -> 0.000121011 | P5: =+LN(K5/K4) -> 0.000169402 | Q5: =+LN(L5/L4) -> 0.000423265 | R5: =+EXP(C5)-1 -> -0.0052278052 | S5: =+EXP(D5)-1 -> -0.0050715301 | T5: =+EXP(E5)-1 -> -0.0047437985 | U5: =+EXP(F5)-1 -> -0.0040369555 | V5: =+EXP(G5)-1 -> -0.0016635627
B6: 43843 | C6: -0.005002826 | D6: -0.00482028 | E6: -0.004451986 | F6: -0.003702724 | G6: -0.001373752 | H6: =EXP(-0.25*C6) -> 1.0012515 | I6: =EXP(-0.5*D6) -> 1.002413 | J6: =EXP(-1*E6) -> 1.0044619 | K6: =EXP(-2*F6) -> 1.0074329 | L6: =EXP(-5*G6) -> 1.0068924 | M6: =+LN(H6/H5) -> -5.9673e-05 | N6: =+LN(I6/I5) -> -0.000132077 | O6: =+LN(J6/J5) -> -0.0003031 | P6: =+LN(K6/K5) -> -0.000684804 | Q6: =+LN(L6/L5) -> -0.00145598 | R6: =+EXP(C6)-1 -> -0.0049903327 | S6: =+EXP(D6)-1 -> -0.0048086811 | T6: =+EXP(E6)-1 -> -0.0044420906 | U6: =+EXP(F6)-1 -> -0.0036958774 | V6: =+EXP(G6)-1 -> -0.0013728088
B7: 43850 | C7: -0.004713972 | D7: -0.004548048 | E7: -0.004225668 | F7: -0.003602806 | G7: -0.001719622 | H7: =EXP(-0.25*C7) -> 1.0011792 | I7: =EXP(-0.5*D7) -> 1.0022766 | J7: =EXP(-1*E7) -> 1.0042346 | K7: =EXP(-2*F7) -> 1.0072316 | L7: =EXP(-5*G7) -> 1.0086352 | M7: =+LN(H7/H6) -> -7.22135e-05 | N7: =+LN(I7/I6) -> -0.000136116 | O7: =+LN(J7/J6) -> -0.000226318 | P7: =+LN(K7/K6) -> -0.000199836 | Q7: =+LN(L7/L6) -> 0.00172935 | R7: =+EXP(C7)-1 -> -0.0047028787 | S7: =+EXP(D7)-1 -> -0.0045377213 | T7: =+EXP(E7)-1 -> -0.0042167524 | U7: =+EXP(F7)-1 -> -0.0035963237 | V7: =+EXP(G7)-1 -> -0.0017181443
B8: 43857 | C8: -0.00490369 | D8: -0.00484303 | E8: -0.004707846 | F8: -0.004378868 | G8: -0.002943476 | H8: =EXP(-0.25*C8) -> 1.0012267 | I8: =EXP(-0.5*D8) -> 1.0024244 | J8: =EXP(-1*E8) -> 1.0047189 | K8: =EXP(-2*F8) -> 1.0087962 | L8: =EXP(-5*G8) -> 1.0148262 | M8: =+LN(H8/H7) -> 4.74295e-05 | N8: =+LN(I8/I7) -> 0.000147491 | O8: =+LN(J8/J7) -> 0.000482178 | P8: =+LN(K8/K7) -> 0.001552124 | Q8: =+LN(L8/L7) -> 0.00611927 | R8: =+EXP(C8)-1 -> -0.0048916865 | S8: =+EXP(D8)-1 -> -0.0048313214 | T8: =+EXP(E8)-1 -> -0.0046967815 | U8: =+EXP(F8)-1 -> -0.0043692947 | V8: =+EXP(G8)-1 -> -0.0029391482
B9: 43864 | C9: -0.005149316 | D9: -0.00507515 | E9: -0.004910228 | F9: -0.004516396 | G9: -0.00290901 | H9: =EXP(-0.25*C9) -> 1.0012882 | I9: =EXP(-0.5*D9) -> 1.0025408 | J9: =EXP(-1*E9) -> 1.0049223 | K9: =EXP(-2*F9) -> 1.0090737 | L9: =EXP(-5*G9) -> 1.0146513 | M9: =+LN(H9/H8) -> 6.14065e-05 | N9: =+LN(I9/I8) -> 0.00011606 | O9: =+LN(J9/J8) -> 0.000202382 | P9: =+LN(K9/K8) -> 0.000275056 | Q9: =+LN(L9/L8) -> -0.00017233 | R9: =+EXP(C9)-1 -> -0.005136081 | S9: =+EXP(D9)-1 -> -0.0050622932 | T9: =+EXP(E9)-1 -> -0.0048981925 | U9: =+EXP(F9)-1 -> -0.0045062124 | V9: =+EXP(G9)-1 -> -0.0029047829
B10: 43871 | C10: -0.005274408 | D10: -0.00518219 | E10: -0.004985684 | F10: -0.004548278 | G10: -0.00295818 | H10: =EXP(-0.25*C10) -> 1.0013195 | I10: =EXP(-0.5*D10) -> 1.0025945 | J10: =EXP(-1*E10) -> 1.0049981 | K10: =EXP(-2*F10) -> 1.0091381 | L10: =EXP(-5*G10) -> 1.0149008 | M10: =+LN(H10/H9) -> 3.1273e-05 | N10: =+LN(I10/I9) -> 5.352e-05 | O10: =+LN(J10/J9) -> 7.5456e-05 | P10: =+LN(K10/K9) -> 6.3764e-05 | Q10: =+LN(L10/L9) -> 0.00024585 | R10: =+EXP(C10)-1 -> -0.0052605227 | S10: =+EXP(D10)-1 -> -0.0051687856 | T10: =+EXP(E10)-1 -> -0.0049732761 | U10: =+EXP(F10)-1 -> -0.0045379502 | V10: =+EXP(G10)-1 -> -0.0029538089
B11: 43878 | C11: -0.005192664 | D11: -0.005132996 | E11: -0.00499222 | F11: -0.004634458 | G11: -0.003117912 | H11: =EXP(-0.25*C11) -> 1.001299 | I11: =EXP(-0.5*D11) -> 1.0025698 | J11: =EXP(-1*E11) -> 1.0050047 | K11: =EXP(-2*F11) -> 1.009312 | L11: =EXP(-5*G11) -> 1.0157117 | M11: =+LN(H11/H10) -> -2.0436e-05 | N11: =+LN(I11/I10) -> -2.4597e-05 | O11: =+LN(J11/J10) -> 6.536e-06 | P11: =+LN(K11/K10) -> 0.00017236 | Q11: =+LN(L11/L10) -> 0.00079866 | R11: =+EXP(C11)-1 -> -0.0051792054 | S11: =+EXP(D11)-1 -> -0.0051198447 | T11: =+EXP(E11)-1 -> -0.0049797796 | U11: =+EXP(F11)-1 -> -0.0046237355 | V11: =+EXP(G11)-1 -> -0.0031130564
B12: 43885 | C12: -0.005246292 | D12: -0.00517287 | E12: -0.005010478 | F12: -0.004630088 | G12: -0.00315976 | H12: =EXP(-0.25*C12) -> 1.0013124 | I12: =EXP(-0.5*D12) -> 1.0025898 | J12: =EXP(-1*E12) -> 1.0050231 | K12: =EXP(-2*F12) -> 1.0093032 | L12: =EXP(-5*G12) -> 1.0159243 | M12: =+LN(H12/H11) -> 1.3407e-05 | N12: =+LN(I12/I11) -> 1.9937e-05 | O12: =+LN(J12/J11) -> 1.8258e-05 | P12: =+LN(K12/K11) -> -8.74e-06 | Q12: =+LN(L12/L11) -> 0.00020924 | R12: =+EXP(C12)-1 -> -0.0052325542 | S12: =+EXP(D12)-1 -> -0.0051595137 | T12: =+EXP(E12)-1 -> -0.0049979465 | U12: =+EXP(F12)-1 -> -0.0046193857 | V12: =+EXP(G12)-1 -> -0.0031547732
B13: 43892 | C13: -0.005320852 | D13: -0.005283442 | E13: -0.005181416 | F13: -0.004882578 | G13: -0.00346323 | H13: =EXP(-0.25*C13) -> 1.0013311 | I13: =EXP(-0.5*D13) -> 1.0026452 | J13: =EXP(-1*E13) -> 1.0051949 | K13: =EXP(-2*F13) -> 1.009813 | L13: =EXP(-5*G13) -> 1.0174669 | M13: =+LN(H13/H12) -> 1.864e-05 | N13: =+LN(I13/I12) -> 5.5286e-05 | O13: =+LN(J13/J12) -> 0.000170938 | P13: =+LN(K13/K12) -> 0.00050498 | Q13: =+LN(L13/L12) -> 0.00151735 | R13: =+EXP(C13)-1 -> -0.0053067213 | S13: =+EXP(D13)-1 -> -0.0052695092 | T13: =+EXP(E13)-1 -> -0.0051680156 | U13: =+EXP(F13)-1 -> -0.0048706776 | V13: =+EXP(G13)-1 -> -0.0034572399
B14: 43899 | C14: -0.004679946 | D14: -0.004643822 | E14: -0.004528996 | F14: -0.00416294 | G14: -0.002469534 | H14: =EXP(-0.25*C14) -> 1.0011707 | I14: =EXP(-0.5*D14) -> 1.0023246 | J14: =EXP(-1*E14) -> 1.0045393 | K14: =EXP(-2*F14) -> 1.0083606 | L14: =EXP(-5*G14) -> 1.0124242 | M14: =+LN(H14/H13) -> -0.0001602265 | N14: =+LN(I14/I13) -> -0.00031981 | O14: =+LN(J14/J13) -> -0.00065242 | P14: =+LN(K14/K13) -> -0.001439276 | Q14: =+LN(L14/L13) -> -0.00496848 | R14: =+EXP(C14)-1 -> -0.0046690121 | S14: =+EXP(D14)-1 -> -0.0046330561 | T14: =+EXP(E14)-1 -> -0.0045187556 | U14: =+EXP(F14)-1 -> -0.004154287 | V14: =+EXP(G14)-1 -> -0.0024664872
B15: 43906 | C15: -0.00348285 | D15: -0.002853954 | E15: -0.001859882 | F15: -0.000498352 | G15: 0.002173908 | H15: =EXP(-0.25*C15) -> 1.0008711 | I15: =EXP(-0.5*D15) -> 1.001428 | J15: =EXP(-1*E15) -> 1.0018616 | K15: =EXP(-2*F15) -> 1.0009972 | L15: =EXP(-5*G15) -> 0.98918932 | M15: =+LN(H15/H14) -> -0.000299274 | N15: =+LN(I15/I14) -> -0.000894934 | O15: =+LN(J15/J14) -> -0.002669114 | P15: =+LN(K15/K14) -> -0.007329176 | Q15: =+LN(L15/L14) -> -0.02321721 | R15: =+EXP(C15)-1 -> -0.0034767919 | S15: =+EXP(D15)-1 -> -0.0028498853 | T15: =+EXP(E15)-1 -> -0.0018581535 | U15: =+EXP(F15)-1 -> -0.00049822784 | V15: =+EXP(G15)-1 -> 0.0021762727
B16: 43913 | C16: -0.003760184 | D16: -0.003383794 | E16: -0.002786454 | F16: -0.001920582 | G16: 0.000398698 | H16: =EXP(-0.25*C16) -> 1.0009405 | I16: =EXP(-0.5*D16) -> 1.0016933 | J16: =EXP(-1*E16) -> 1.0027903 | K16: =EXP(-2*F16) -> 1.0038486 | L16: =EXP(-5*G16) -> 0.9980085 | M16: =+LN(H16/H15) -> 6.93335e-05 | N16: =+LN(I16/I15) -> 0.00026492 | O16: =+LN(J16/J15) -> 0.000926572 | P16: =+LN(K16/K15) -> 0.00284446 | Q16: =+LN(L16/L15) -> 0.00887605 | R16: =+EXP(C16)-1 -> -0.0037531234 | S16: =+EXP(D16)-1 -> -0.0033780754 | T16: =+EXP(E16)-1 -> -0.0027825754 | U16: =+EXP(F16)-1 -> -0.0019187389 | V16: =+EXP(G16)-1 -> 0.00039877749
... B319: 46034 | C319: 0.020262282 | D319: 0.020258162 | E319: 0.02043664 | F319: 0.021377836 | G319: 0.025927362 | H319: =EXP(-0.25*C319) -> 0.99494724 | I319: =EXP(-0.5*D319) -> 0.98992205 | J319: =EXP(-1*E319) -> 0.97977077 | K319: =EXP(-2*F319) -> 0.95814546 | L319: =EXP(-5*G319) -> 0.8784144 | M319: =+LN(H319/H318) -> 2.3407e-05 | N319: =+LN(I319/I318) -> 1.8497e-05 | O319: =+LN(J319/J318) -> 8.574e-06 | P319: =+LN(K319/K318) -> 0.0001871 | Q319: =+LN(L319/L318) -> 0.00173182 | R319: =+EXP(C319)-1 -> 0.020468956 | S319: =+EXP(D319)-1 -> 0.020464751 | T319: =+EXP(E319)-1 -> 0.020646898 | U319: =+EXP(F319)-1 -> 0.021607979 | V319: =+EXP(G319)-1 -> 0.0262664

Sheet Computations -->
D9: Computations

Sheet 31Mar24
B3: Legend
D5: Cashflows to be clumped
D6: Cashflows already at the correct nodes
B9: Date at which cashflows must be computed
B11: VaR comp. date | C11: 45382
B13: Nodes | C13: =+EOMONTH($C$11,'ZCB rates'!C$3) -> 45473 | D13: =+EOMONTH($C$11,'ZCB rates'!D$3) -> 45565 | E13: =+EOMONTH($C$11,'ZCB rates'!E$3) -> 45747 | F13: =+EOMONTH($C$11,'ZCB rates'!F$3) -> 46112 | G13: =+EOMONTH($C$11,'ZCB rates'!G$3) -> 47208
B14: Diff from today (days) | C14: =+C13-C11 -> 91 | D14: =+D13-$C$11 -> 183 | E14: =+E13-$C$11 -> 365 | F14: =+F13-$C$11 -> 730 | G14: =+G13-$C$11 -> 1826
B17: Term structure of int rates
C19: =+'ZCB rates'!C3 -> 3 | D19: =+'ZCB rates'!D3 -> 6 | E19: =+'ZCB rates'!E3 -> 12 | F19: =+'ZCB rates'!F3 -> 24 | G19: =+'ZCB rates'!G3 -> 60
B20: =+C11 -> 45382 | C20: =+'ZCB rates'!R225 -> 0.039148292 | D20: =+'ZCB rates'!S225 -> 0.037100348 | E20: =+'ZCB rates'!T225 -> 0.033890367 | F20: =+'ZCB rates'!U225 -> 0.030018486 | G20: =+'ZCB rates'!V225 -> 0.027648924
B23: Security 7
C26: =+Assumptions!E7 -> 45657 | D26: =+Assumptions!F7 -> 45838 | E26: =+Assumptions!G7 -> 46022 | F26: =+Assumptions!H7 -> 46203 | G26: =+Assumptions!I7 -> 46387
B27: t from today (duration) | C27: =+(C26-$C$11)/365 -> 0.75342466 | D27: =+(D26-$C$11)/365 -> 1.2493151 | E27: =+(E26-$C$11)/365 -> 1.7534247 | F27: =+(F26-$C$11)/365 -> 2.2493151 | G27: =+(G26-$C$11)/365 -> 2.7534247
B28: Interpolated rate | C28: =+_xlfn.LET(_xlpm.t_remaining,C27,_xlpm.r_m1,D20,_xlpm.r_m2,E20,_xlpm.mone,D19,_xlpm.mtwo,E19,_xlpm.r_m1+(_xlpm.r_m2-_xlpm.r_m1)/(_xlpm.mtwo/month_in_a_year-_xlpm.mone/month_in_a_year)*(_xlpm.t_remaining-_xlpm.mone/month_in_a_year)) -> 0.035473372 | D28: =+_xlfn.LET(_xlpm.t_rem,D27,_xlpm.r_m1,E20,_xlpm.r_m2,F20,_xlpm.mone,E19,_xlpm.mtwo,F19,_xlpm.r_m1+(_xlpm.r_m2-_xlpm.r_m1)/(_xlpm.mtwo/month_in_a_year-_xlpm.mone/month_in_a_year)*(_xlpm.t_rem-_xlpm.mone/month_in_a_year)) -> 0.032925049 | E28: =+_xlfn.LET(_xlpm.t_rem,E27,_xlpm.r_m1,E20,_xlpm.r_m2,F20,_xlpm.mone,E19,_xlpm.mtwo,F19,_xlpm.r_m1+(_xlpm.r_m2-_xlpm.r_m1)/(_xlpm.mtwo/month_in_a_year-_xlpm.mone/month_in_a_year)*(_xlpm.t_rem-_xlpm.mone/month_in_a_year)) -> 0.030973197 | F28: =+_xlfn.LET(_xlpm.t_rem,F27,_xlpm.r_m1,F20,_xlpm.r_m2,G20,_xlpm.mone,F19,_xlpm.mtwo,G19,_xlpm.r_m1+(_xlpm.r_m2-_xlpm.r_m1)/(_xlpm.mtwo/month_in_a_year-_xlpm.mone/month_in_a_year)*(_xlpm.t_rem-_xlpm.mone/month_in_a_year)) -> 0.029821564 | G28: =+_xlfn.LET(_xlpm.t_rem,G27,_xlpm.r_m1,F20,_xlpm.r_m2,G20,_xlpm.mone,F19,_xlpm.mtwo,G19,_xlpm.r_m1+(_xlpm.r_m2-_xlpm.r_m1)/(_xlpm.mtwo/month_in_a_year-_xlpm.mone/month_in_a_year)*(_xlpm.t_rem-_xlpm.mone/month_in_a_year)) -> 0.029423391
B29: Modified Duration | C29: =+C27/(1+C28) -> 0.72761374 | D29: =+D27/(1+D28) -> 1.2094925 | E29: =+E27/(1+E28) -> 1.7007471 | F29: =+F27/(1+F28) -> 2.1841794 | G29: =+G27/(1+G28) -> 2.6747252
B31: Goal nodes | C31: 6m & 12m | D31: 12m & 24m | E31: 12m & 24m | F31: 24m & 60m | G31: 24m & 60m
B32: MD 1 | C32: =+(D$19/month_in_a_year)/(1+D$20) -> 0.48211342 | D32: =+(E$19/month_in_a_year)/(1+E$20) -> 0.96722054 | E32: =+(E$19/month_in_a_year)/(1+E$20) -> 0.96722054 | F32: =+(F$19/month_in_a_year)/(1+F$20) -> 1.9417127 | G32: =+(F$19/month_in_a_year)/(1+F$20) -> 1.9417127
B33: MD 2 | C33: =+(E$19/month_in_a_year)/(1+E$20) -> 0.96722054 | D33: =+(F$19/month_in_a_year)/(1+F$20) -> 1.9417127 | E33: =+(F$19/month_in_a_year)/(1+F$20) -> 1.9417127 | F33: =+(G$19/month_in_a_year)/(1+G$20) -> 4.8654749 | G33: =+(G$19/month_in_a_year)/(1+G$20) -> 4.8654749
B35: Market value real cashflow | C35: =+Assumptions!E$8/(1+C28)^C27 -> 194.8157 | D35: =+Assumptions!F8/(1+D28)^D27 -> 192.06738 | E35: =+Assumptions!G8/(1+E28)^E27 -> 189.58402 | F35: =+Assumptions!H8/(1+F28)^F27 -> 187.20795 | G35: =+Assumptions!I8/(1+G28)^G27 -> 9417.236
B37: Mkt value virtual cashflow 1 | C37: =+_xlfn.LET(_xlpm.MDvirt1,C32,_xlpm.MDvirt2,C33,_xlpm.MDreal,C29,_xlpm.Mvreal,C35,(_xlpm.MDvirt2-_xlpm.MDreal)/(_xlpm.MDvirt2-_xlpm.MDvirt1)*_xlpm.Mvreal) -> 96.224449 | D37: =+_xlfn.LET(_xlpm.MDvirt1,D32,_xlpm.MDvirt2,D33,_xlpm.MDreal,D29,_xlpm.Mvreal,D35,(_xlpm.MDvirt2-_xlpm.MDreal)/(_xlpm.MDvirt2-_xlpm.MDvirt1)*_xlpm.Mvreal) -> 144.31684 | E37: =+_xlfn.LET(_xlpm.MDvirt1,E32,_xlpm.MDvirt2,E33,_xlpm.MDreal,E29,_xlpm.Mvreal,E35,(_xlpm.MDvirt2-_xlpm.MDreal)/(_xlpm.MDvirt2-_xlpm.MDvirt1)*_xlpm.Mvreal) -> 46.879015 | F37: =+_xlfn.LET(_xlpm.MDvirt1,F32,_xlpm.MDvirt2,F33,_xlpm.MDreal,F29,_xlpm.Mvreal,F35,(_xlpm.MDvirt2-_xlpm.MDreal)/(_xlpm.MDvirt2-_xlpm.MDvirt1)*_xlpm.Mvreal) -> 171.68285 | G37: =+_xlfn.LET(_xlpm.MDvirt1,G32,_xlpm.MDvirt2,G33,_xlpm.MDreal,G29,_xlpm.Mvreal,G35,(_xlpm.MDvirt2-_xlpm.MDreal)/(_xlpm.MDvirt2-_xlpm.MDvirt1)*_xlpm.Mvreal) -> 7056.2535
B38: Mkt value Virtual cashflow 2 | C38: =+C35-C37 -> 98.591249 | D38: =+D35-D37 -> 47.750548 | E38: =+E35-E37 -> 142.705 | F38: =+F35-F37 -> 15.525098 | G38: =+G35-G37 -> 2360.9825
B40: Face value 1 | C40: =+C37*(1+D20)^(D19/month_in_a_year) -> 97.993174 | D40: =+D37*(1+E20)^(E19/month_in_a_year) -> 149.20779 | E40: =+E37*(1+E20)^(E19/month_in_a_year) -> 48.467762 | F40: =+F37*(1+F20)^(F19/month_in_a_year) -> 182.14487 | G40: =+G37*(1+F20)^(F19/month_in_a_year) -> 7486.248
B41: Face value 2 | C41: =+C38*(1+E20)^(E19/month_in_a_year) -> 101.93254 | D41: =+D38*(1+F20)^(F19/month_in_a_year) -> 50.660375 | E41: =+E38*(1+F20)^(F19/month_in_a_year) -> 151.40117 | F41: =+F38*(1+G20)^(G19/month_in_a_year) -> 17.79337 | G41: =+G38*(1+G20)^(G19/month_in_a_year) -> 2705.9304
B43: Check | C43: =ROUND(+C29-C32*C37/C35-C33*C38/C35,5) -> 0 | D43: =ROUND(+D29-D32*D37/D35-D33*D38/D35,5) -> 0 | E43: =ROUND(+E29-E32*E37/E35-E33*E38/E35,5) -> 0 | F43: =ROUND(+F29-F32*F37/F35-F33*F38/F35,5) -> 0 | G43: =+G29-G32*G37/G35-G33*G38/G35 -> 0
B47: Security 10
C50: =+Assumptions!E10 -> 45747 | D50: =+Assumptions!F10 -> 45838 | E50: =+Assumptions!G10 -> 46022 | F50: =+Assumptions!H10 -> 46203
B51: t from today (duration) | C51: =+(C50-$C$11)/365 -> 1 | D51: =+(D50-$C$11)/365 -> 1.2493151 | E51: =+(E50-$C$11)/365 -> 1.7534247 | F51: =+(F50-$C$11)/365 -> 2.2493151
B52: Interpolated rate | D52: =+_xlfn.LET(_xlpm.t_rem,D51,_xlpm.r_m1,E20,_xlpm.r_m2,F20,_xlpm.mone,E19,_xlpm.mtwo,F19,_xlpm.r_m1+(_xlpm.r_m2-_xlpm.r_m1)/(_xlpm.mtwo/month_in_a_year-_xlpm.mone/month_in_a_year)*(_xlpm.t_rem-_xlpm.mone/month_in_a_year)) -> 0.032925049 | E52: =+_xlfn.LET(_xlpm.t_rem,E51,_xlpm.r_m1,E20,_xlpm.r_m2,F20,_xlpm.mone,E19,_xlpm.mtwo,F19,_xlpm.r_m1+(_xlpm.r_m2-_xlpm.r_m1)/(_xlpm.mtwo/month_in_a_year-_xlpm.mone/month_in_a_year)*(_xlpm.t_rem-_xlpm.mone/month_in_a_year)) -> 0.030973197 | F52: =+_xlfn.LET(_xlpm.t_rem,F51,_xlpm.r_m1,F20,_xlpm.r_m2,G20,_xlpm.mone,F19,_xlpm.mtwo,G19,_xlpm.r_m1+(_xlpm.r_m2-_xlpm.r_m1)/(_xlpm.mtwo/month_in_a_year-_xlpm.mone/month_in_a_year)*(_xlpm.t_rem-_xlpm.mone/month_in_a_year)) -> 0.029821564
B53: Modified Duration | D53: =+D51/(1+D52) -> 1.2094925 | E53: =+E51/(1+E52) -> 1.7007471 | F53: =+F51/(1+F52) -> 2.1841794
B55: Goal nodes | C55: 12m | D55: 12m & 24m | E55: 12m & 24m | F55: 24m & 60m
B56: MD 1 | D56: =+(E$19/12)/(1+E$20) -> 0.96722054 | E56: =+(E$19/12)/(1+E$20) -> 0.96722054 | F56: =+(F$19/12)/(1+F$20) -> 1.9417127
B57: MD 2 | D57: =+(F$19/12)/(1+F$20) -> 1.9417127 | E57: =+(F$19/12)/(1+F$20) -> 1.9417127 | F57: =+(G$19/12)/(1+G$20) -> 4.8654749
B59: Market value real cashflow | C59: =C64/(1+E20) -> 145.08308 | D59: =+Assumptions!F$11/(1+D52)^D51 -> 144.05054 | E59: =+Assumptions!G$11/(1+E52)^E51 -> 142.18801 | F59: =+Assumptions!H$11/(1+F52)^F51 -> 4820.6046
B61: Mkt value Virtual cashflow 1 | D61: =+_xlfn.LET(_xlpm.MDvirt1,D56,_xlpm.MDvirt2,D57,_xlpm.MDreal,D53,_xlpm.Mvreal,D59,(_xlpm.MDvirt2-_xlpm.MDreal)/(_xlpm.MDvirt2-_xlpm.MDvirt1)*_xlpm.Mvreal) -> 108.23763 | E61: =+_xlfn.LET(_xlpm.MDvirt1,E56,_xlpm.MDvirt2,E57,_xlpm.MDreal,E53,_xlpm.Mvreal,E59,(_xlpm.MDvirt2-_xlpm.MDreal)/(_xlpm.MDvirt2-_xlpm.MDvirt1)*_xlpm.Mvreal) -> 35.159262 | F61: =+_xlfn.LET(_xlpm.MDvirt1,F56,_xlpm.MDvirt2,F57,_xlpm.MDreal,F53,_xlpm.Mvreal,F59,(_xlpm.MDvirt2-_xlpm.MDreal)/(_xlpm.MDvirt2-_xlpm.MDvirt1)*_xlpm.Mvreal) -> 4420.8333
B62: Mkt value Virtual cashflow 2 | D62: =+D59-D61 -> 35.812911 | E62: =+E59-E61 -> 107.02875 | F62: =+F59-F61 -> 399.77127
B64: Face value 1 | C64: =Assumptions!E11 -> 150 | D64: =+D61*(1+E20)^(E19/month_in_a_year) -> 111.90584 | E64: =+E61*(1+E20)^(E19/month_in_a_year) -> 36.350822 | F64: =+F61*(1+F20)^(F19/month_in_a_year) -> 4690.2305
B65: Face value 2 | C65: 0 | D65: =+D62*(1+F20)^(F19/month_in_a_year) -> 37.995281 | E65: =+E62*(1+F20)^(F19/month_in_a_year) -> 113.55088 | F65: =+F62*(1+G20)^(G19/month_in_a_year) -> 458.17927
B67: Check | D67: =ROUND(+D53-D56*D61/D59-D57*D62/D59,5) -> 0 | E67: =ROUND(+E53-E56*E61/E59-E57*E62/E59,5) -> 0 | F67: =ROUND(+F53-F56*F61/F59-F57*F62/F59,5) -> 0
B69: New Portfolio
C71: =+C72-$C$11 -> 91 | D71: =+D72-$C$11 -> 183 | E71: =+E72-$C$11 -> 365 | F71: =+F72-$C$11 -> 730 | G71: =+G72-$C$11 -> 1826
C72: =+C13 -> 45473 | D72: =+D13 -> 45565 | E72: =+E13 -> 45747 | F72: =+F13 -> 46112 | G72: =+G13 -> 47208
B73: Cashflows | C73: 0 | D73: =+C40 -> 97.993174 | E73: =+C41+D40+D64+E64+E40+C64 -> 597.86475 | F73: =+SUM(D65:E65,F64,D41:E41,F40:G40) -> 12712.231 | G73: =+SUM(F65,F41:G41) -> 3181.9031
B74: Disc factor | C74: =+'ZCB rates'!H225 -> 0.99044558 | D74: =+'ZCB rates'!I225 -> 0.98195053 | E74: =+'ZCB rates'!J225 -> 0.96722054 | F74: =+'ZCB rates'!K225 -> 0.94256207 | G74: =+'ZCB rates'!L225 -> 0.87252151
C75: =1/(1+C20)^(C71/365) -> 0.99047163 | D75: =1/(1+D20)^(D71/365) -> 0.98190153 | E75: =1/(1+E20)^(E71/365) -> 0.96722054 | F75: =1/(1+F20)^(F71/365) -> 0.94256207 | G75: =1/(1+G20)^(G71/365) -> 0.87245631
B78: PV of cashflow | C78: =+C73*C74 -> 0 | D78: =+D73*D74 -> 96.224449 | E78: =+E73*E74 -> 578.26707 | F78: =+F73*F74 -> 11982.067 | G78: =+G73*G74 -> 2776.2789
B80: Sum of PV | G80: =+SUM(C78:G78) -> 15432.837 | I80: Check | J80: =ROUND(SUM(C59:F59)+SUM(C35:G35)-G80,1) -> 0
B82: Var computation - parametric approach
C84: =+C72 -> 45473 | D84: =+D72 -> 45565 | E84: =+E72 -> 45747 | F84: =+F72 -> 46112 | G84: =+G72 -> 47208
B85: δ' | C85: =C78 -> 0 | D85: =D78 -> 96.224449 | E85: =E78 -> 578.26707 | F85: =F78 -> 11982.067 | G85: =G78 -> 2776.2789
B87: δ | C87: {=+TRANSPOSE(C85:G85)} -> 0
C88: 96.224449
C89: 578.26707
C90: 11982.067
C91: 2776.2789
C94: EWMA | L94: Simple moving average
B96: Σ | C96: {=+EWMACovMatrix('ZCB rates'!M174:Q225,Lambda)} -> 7.0437767e-09 | D96: 1.1679188e-08 | E96: 1.9861476e-08 | F96: 4.1360782e-08 | G96: 1.3114266e-07 | L96: {=CovarianceMatrix('ZCB rates'!M174:Q225)} -> 8.9925447e-09 | M96: 1.5202664e-08 | N96: 3.0800414e-08 | O96: 7.8649448e-08 | P96: 2.2344545e-07
C97: 1.1679188e-08 | D97: 3.6297125e-08 | E97: 1.0263093e-07 | F97: 2.4959426e-07 | G97: 6.4809638e-07 | L97: 1.5202664e-08 | M97: 5.3290244e-08 | N97: 1.4816567e-07 | O97: 3.2312748e-07 | P97: 7.6632519e-07
C98: 1.9861476e-08 | D98: 1.0263093e-07 | E98: 3.6063341e-07 | F98: 9.6555425e-07 | G98: 2.4628539e-06 | L98: 3.0800414e-08 | M98: 1.4816567e-07 | N98: 4.6826429e-07 | O98: 1.0917924e-06 | P98: 2.6037109e-06
C99: 4.1360782e-08 | D99: 2.4959426e-07 | E99: 9.6555425e-07 | F99: 2.8044213e-06 | G99: 7.4614937e-06 | L99: 7.8649448e-08 | M99: 3.2312748e-07 | N99: 1.0917924e-06 | O99: 2.9410068e-06 | P99: 7.7157024e-06
C100: 1.3114266e-07 | D100: 6.4809638e-07 | E100: 2.4628539e-06 | F100: 7.4614937e-06 | G100: 2.197564e-05 | L100: 2.2344545e-07 | M100: 7.6632519e-07 | N100: 2.6037109e-06 | O100: 7.7157024e-06 | P100: 2.3333525e-05
B103: σ2ΔV | C103: {=+MMULT(TRANSPOSE(_xlfn.ANCHORARRAY(C87)),MMULT(_xlfn.ANCHORARRAY(C96),_xlfn.ANCHORARRAY(C87)))} -> 1090.7766 | K103: σ2ΔV | L103: {=+MMULT(TRANSPOSE(_xlfn.ANCHORARRAY(C87)),MMULT(_xlfn.ANCHORARRAY(L96),_xlfn.ANCHORARRAY(C87)))} -> 1140.2408
B105: CI | C105: 0.95 | D105: 0.99 | K105: CI | L105: 0.95 | M105: 0.99
B106: Var | C106: =+SQRT($C$103)*(-1)*_xlfn.NORM.S.INV(1-C105) -> 54.324429 | D106: =+SQRT($C$103)*(-1)*_xlfn.NORM.S.INV(1-D105) -> 76.832077 | K106: Var | L106: =+SQRT($L$103)*(-1)*_xlfn.NORM.S.INV(1-L105) -> 55.542515 | M106: =+SQRT($L$103)*(-1)*_xlfn.NORM.S.INV(1-M105) -> 78.554839
B110: Var computation - hybrid approach
C112: =+C72 -> 45473 | D112: =+D72 -> 45565 | E112: =+E72 -> 45747 | F112: =+F72 -> 46112 | G112: =+G72 -> 47208
B113: =+B73 -> Cashflows | C113: =+C73 -> 0 | D113: =+D73 -> 97.993174 | E113: =+E73 -> 597.86475 | F113: =+F73 -> 12712.231 | G113: =+G73 -> 3181.9031
B114: Discount factor | C114: =+C74 -> 0.99044558 | D114: =+D74 -> 0.98195053 | E114: =+E74 -> 0.96722054 | F114: =+F74 -> 0.94256207 | G114: =+G74 -> 0.87252151
B116: PV of Cashflows | C116: =+C114*C113 -> 0 | D116: =+D114*D113 -> 96.224449 | E116: =+E114*E113 -> 578.26707 | F116: =+F114*F113 -> 11982.067 | G116: =+G114*G113 -> 2776.2789
G117: =+SUM(C116:G116) -> 15432.837
B119: CI | C119: 0.95 | D119: 0.99 | N119: Check | Q119: =+SUM(Q129:Q180)-1 -> 0 | W119: =+SUM(W129:W180)-1 -> 0
B120: Plain vanilla Var | C120: {=-(INDEX(_xlfn.ANCHORARRAY(V129),MATCH(TRUE,X129:X181>=1-C119,0))-$C$123)} -> 51.377143 | D120: {=-(INDEX(_xlfn.ANCHORARRAY(V129),MATCH(TRUE,X129:X349>=1-D119,0))-$C$123)} -> 60.071147
B121: Interpolated Var | C121: =+_xlfn.LET(_xlpm.x_1,V129,_xlpm.x_2,V130,_xlpm.alfa_1,X129,_xlpm.alfa_2,X130,_xlpm.p,(1-C119),_xlpm.mu,C123,(-1)*(_xlpm.x_1*(_xlpm.alfa_2-_xlpm.p)/(_xlpm.alfa_2-_xlpm.alfa_1)+_xlpm.x_2*(_xlpm.p-_xlpm.alfa_1)/(_xlpm.alfa_2-_xlpm.alfa_1)-_xlpm.mu)) -> 57.303996 | D121: n.m.
B123: Mean | C123: =+SUMPRODUCT(O129:O180,Q129:Q180) -> 1.5994232
B124: Variance | C124: =+SUMPRODUCT(Q129:Q180,R129:R180) -> 1087.7042
B125: Skewness | C125: =+(SUMPRODUCT(Q129:Q180,S129:S180)/(C124^(3/2))-3) -> -2.6615197
B126: Excess Kurtosis | C126: =+(SUMPRODUCT(Q129:Q180,T129:T180)/(C124^2))-3 -> -0.32102463 | AU126: Parametric
AA127: Hybrid | AU127: EWMA | AW127: SMA
B128: Ordering factor | C128: Date | D128: r 3m | E128: r 6m | F128: r 12m | G128: r 24m | H128: r 60m | I128: PZCB3M | J128: PZCB6M | K128: PZCB12M | L128: PZCB24M | M128: PZCB60M | N128: V | O128: ΔV | P128: λi | Q128: Frequency | R128: (ΔV-μ)2 | S128: (ΔV-μ)3 | T128: (ΔV-μ)4 | V128: Sorted ΔV | W128: Frequency | X128: Cum. Frequency | AA128: Bands | AB128: Band average | AC128: Frequency | AE128: Changes in the portfolio's value: frequency distribution | AU128: Cum. Freq. | AV128: PseudoN | AW128: Cum. Freq. | AX128: PseudoN
B129: =+B130+1 -> 52 | C129: =+'ZCB rates'!B174 -> 45019 | D129: =+'ZCB rates'!M174 -> -0.0001609975 | E129: =+'ZCB rates'!N174 -> -0.00025245225 | F129: =+'ZCB rates'!O174 -> -0.0002641385 | G129: =+'ZCB rates'!P174 -> 0.000185534 | H129: =+'ZCB rates'!Q174 -> 0.0027176975 | I129: =+C$114*EXP(D129) -> 0.99028613 | J129: =+D$114*EXP(E129) -> 0.98170267 | K129: =+E$114*EXP(F129) -> 0.96696509 | L129: =+F$114*EXP(G129) -> 0.94273697 | M129: =+G$114*EXP(H129) -> 0.87489598 | N129: =+SUMPRODUCT(I129:M129,$C$113:$G$113) -> 15442.439 | O129: =+N129-$G$117 -> 9.6016236 | P129: =+Lambda^B129 -> 0.04005423 | Q129: =+P129/$P$182 -> 0.0026633306 | R129: =+($O129-$C$123)^2 -> 64.035212 | S129: =+($O129-$C$123)^3 -> 512.42261 | T129: =+($O129-$C$123)^4 -> 4100.5084 | V129: {=+_xlfn._xlws.SORT(O129:O180)} -> -58.471724 | W129: =+_xlfn.XLOOKUP(V129,$O$129:$O$180,$Q$129:$Q$180) -> 0.040532139 | X129: =+SUM($W$129:W129) -> 0.040532139 | AA129: =+AA130-$AA$141/2.5 -> -125.50225 | AU129: =+NORMDIST('31Mar24'!$AA129,0,SQRT('31Mar24'!$C$103),TRUE) -> 7.2348044e-05 | AW129: =+NORMDIST('31Mar24'!$AA129,0,SQRT($L$103),TRUE) -> 0.00010093557
B130: =+B131+1 -> 51 | C130: =+'ZCB rates'!B175 -> 45026 | D130: =+'ZCB rates'!M175 -> -0.00021563688 | E130: =+'ZCB rates'!N175 -> -0.00047342875 | F130: =+'ZCB rates'!O175 -> -0.001081825 | G130: =+'ZCB rates'!P175 -> -0.002485405 | H130: =+'ZCB rates'!Q175 -> -0.00616845 | I130: =+C$114*EXP(D130) -> 0.99023203 | J130: =+D$114*EXP(E130) -> 0.98148576 | K130: =+E$114*EXP(F130) -> 0.96617474 | L130: =+F$114*EXP(G130) -> 0.94022234 | M130: =+G$114*EXP(H130) -> 0.86715597 | N130: =+SUMPRODUCT(I130:M130,$C$113:$G$113) -> 15385.351 | O130: =+N130-$G$117 -> -47.486729 | P130: =+Lambda^B130 -> 0.042610883 | Q130: =+P130/$P$182 -> 0.0028333305 | R130: =+($O130-$C$123)^2 -> 2409.4503 | S130: =+($O130-$C$123)^3 -> -118270.65 | T130: =+($O130-$C$123)^4 -> 5805451 | V130: -49.777719 | W130: =+_xlfn.XLOOKUP(V130,$O$129:$O$180,$Q$129:$Q$180) -> 0.0297467 | X130: =+SUM($W$129:W130) -> 0.070278839 | AA130: =+AA131-$AA$141/2.5 -> -112.29149 | AB130: =+AVERAGE(AA129:AA130) -> -118.89687 | AC130: =SUMIFS($W$129:$W$349,$V$129:$V$349,">="&AA129,$V$129:$V$349,"<"&AA130) -> 0 | AU130: =+NORMDIST('31Mar24'!$AA130,0,SQRT('31Mar24'!$C$103),TRUE) -> 0.00033692927 | AV130: =+AU130-AU129 -> 0.00026458122 | AW130: =+NORMDIST('31Mar24'!$AA130,0,SQRT($L$103),TRUE) -> 0.00044140242 | AX130: =+AW130-AW129 -> 0.00034046685
B131: =+B132+1 -> 50 | C131: =+'ZCB rates'!B176 -> 45033 | D131: =+'ZCB rates'!M176 -> -0.00031711463 | E131: =+'ZCB rates'!N176 -> -0.000639212 | F131: =+'ZCB rates'!O176 -> -0.0012925725 | G131: =+'ZCB rates'!P176 -> -0.002605929 | H131: =+'ZCB rates'!Q176 -> -0.0063132475 | I131: =+C$114*EXP(D131) -> 0.99013154 | J131: =+D$114*EXP(E131) -> 0.98132306 | K131: =+E$114*EXP(F131) -> 0.96597115 | L131: =+F$114*EXP(G131) -> 0.94010902 | M131: =+G$114*EXP(H131) -> 0.86703041 | N131: =+SUMPRODUCT(I131:M131,$C$113:$G$113) -> 15383.373 | O131: =+N131-$G$117 -> -49.464349 | P131: =+Lambda^B131 -> 0.045330727 | Q131: =+P131/$P$182 -> 0.0030141813 | R131: =+($O131-$C$123)^2 -> 2607.5088 | S131: =+($O131-$C$123)^3 -> -133149.23 | T131: =+($O131-$C$123)^4 -> 6799102.1 | V131: -49.464349 | W131: =+_xlfn.XLOOKUP(V131,$O$129:$O$180,$Q$129:$Q$180) -> 0.0030141813 | X131: =+SUM($W$129:W131) -> 0.073293021 | AA131: =+AA132-$AA$141/2.5 -> -99.080723 | AB131: =+AVERAGE(AA130:AA131) -> -105.6861 | AC131: =SUMIFS($W$129:$W$349,$V$129:$V$349,">="&AA130,$V$129:$V$349,"<"&AA131) -> 0 | AU131: =+NORMDIST('31Mar24'!$AA131,0,SQRT('31Mar24'!$C$103),TRUE) -> 0.001349898 | AV131: =+AU131-AU130 -> 0.0010129688 | AW131: =+NORMDIST('31Mar24'!$AA131,0,SQRT($L$103),TRUE) -> 0.0016720007 | AX131: =+AW131-AW130 -> 0.0012305983
B132: =+B133+1 -> 49 | C132: =+'ZCB rates'!B177 -> 45040 | D132: =+'ZCB rates'!M177 -> 0.000112161 | E132: =+'ZCB rates'!N177 -> 0.000239553 | F132: =+'ZCB rates'!O177 -> 0.000532358 | G132: =+'ZCB rates'!P177 -> 0.001224228 | H132: =+'ZCB rates'!Q177 -> 0.00350667 | I132: =+C$114*EXP(D132) -> 0.99055668 | J132: =+D$114*EXP(E132) -> 0.98218579 | K132: =+E$114*EXP(F132) -> 0.96773559 | L132: =+F$114*EXP(G132) -> 0.94371669 | M132: =+G$114*EXP(H132) -> 0.87558652 | N132: =+SUMPRODUCT(I132:M132,$C$113:$G$113) -> 15457.599 | O132: =+N132-$G$117 -> 24.761328 | P132: =+Lambda^B132 -> 0.048224177 | Q132: =+P132/$P$182 -> 0.0032065759 | R132: =+($O132-$C$123)^2 -> 536.47385 | S132: =+($O132-$C$123)^3 -> 12425.757 | T132: =+($O132-$C$123)^4 -> 287804.2 | V132: -48.932764 | W132: =+_xlfn.XLOOKUP(V132,$O$129:$O$180,$Q$129:$Q$180) -> 0.0059533716 | X132: =+SUM($W$129:W132) -> 0.079246392 | AA132: =+AA133-$AA$141/2.5 -> -85.86996 | AB132: =+AVERAGE(AA131:AA132) -> -92.475342 | AC132: =SUMIFS($W$129:$W$349,$V$129:$V$349,">="&AA131,$V$129:$V$349,"<"&AA132) -> 0 | AU132: =+NORMDIST('31Mar24'!$AA132,0,SQRT('31Mar24'!$C$103),TRUE) -> 0.004661188 | AV132: =+AU132-AU131 -> 0.00331129 | AW132: =+NORMDIST('31Mar24'!$AA132,0,SQRT($L$103),TRUE) -> 0.0054955731 | AX132: =+AW132-AW131 -> 0.0038235724
B133: =+B134+1 -> 48 | C133: =+'ZCB rates'!B178 -> 45047 | D133: =+'ZCB rates'!M178 -> 3.6056125e-05 | E133: =+'ZCB rates'!N178 -> 0.0001783115 | F133: =+'ZCB rates'!O178 -> 0.000713342 | G133: =+'ZCB rates'!P178 -> 0.002401056 | H133: =+'ZCB rates'!Q178 -> 0.0077575275 | I133: =+C$114*EXP(D133) -> 0.99048129 | J133: =+D$114*EXP(E133) -> 0.98212564 | K133: =+E$114*EXP(F133) -> 0.96791075 | L133: =+F$114*EXP(G133) -> 0.94482794 | M133: =+G$114*EXP(H133) -> 0.87931644 | N133: =+SUMPRODUCT(I133:M133,$C$113:$G$113) -> 15483.692 | O133: =+N133-$G$117 -> 50.854802 | P133: =+Lambda^B133 -> 0.051302316 | Q133: =+P133/$P$182 -> 0.003411251 | R133: =+($O133-$C$123)^2 -> 2426.0923 | S133: =+($O133-$C$123)^3 -> 119498.1 | T133: =+($O133-$C$123)^4 -> 5885924.1 | V133: -47.486729 | W133: =+_xlfn.XLOOKUP(V133,$O$129:$O$180,$Q$129:$Q$180) -> 0.0028333305 | X133: =+SUM($W$129:W133) -> 0.082079723 | AA133: =+AA134-$AA$141/2.5 -> -72.659197 | AB133: =+AVERAGE(AA132:AA133) -> -79.264579 | AC133: =SUMIFS($W$129:$W$349,$V$129:$V$349,">="&AA132,$V$129:$V$349,"<"&AA133) -> 0 | AU133: =+NORMDIST('31Mar24'!$AA133,0,SQRT('31Mar24'!$C$103),TRUE) -> 0.013903448 | AV133: =+AU133-AU132 -> 0.0092422595 | AW133: =+NORMDIST('31Mar24'!$AA133,0,SQRT($L$103),TRUE) -> 0.015708428 | AX133: =+AW133-AW132 -> 0.010212855
B134: =+B135+1 -> 47 | C134: =+'ZCB rates'!B179 -> 45054 | D134: =+'ZCB rates'!M179 -> -2.3091625e-05 | E134: =+'ZCB rates'!N179 -> -1.20325e-05 | F134: =+'ZCB rates'!O179 -> 8.7232e-05 | G134: =+'ZCB rates'!P179 -> 0.000452704 | H134: =+'ZCB rates'!Q179 -> 0.0012225325 | I134: =+C$114*EXP(D134) -> 0.99042271 | J134: =+D$114*EXP(E134) -> 0.98193872 | K134: =+E$114*EXP(F134) -> 0.96730492 | L134: =+F$114*EXP(G134) -> 0.94298887 | M134: =+G$114*EXP(H134) -> 0.87358885 | N134: =+SUMPRODUCT(I134:M134,$C$113:$G$113) -> 15441.708 | O134: =+N134-$G$117 -> 8.8710121 | P134: =+Lambda^B134 -> 0.054576932 | Q134: =+P134/$P$182 -> 0.0036289904 | R134: =+($O134-$C$123)^2 -> 52.876005 | S134: =+($O134-$C$123)^3 -> 384.49257 | T134: =+($O134-$C$123)^4 -> 2795.8719 | V134: -42.798879 | W134: =+_xlfn.XLOOKUP(V134,$O$129:$O$180,$Q$129:$Q$180) -> 0.0041070511 | X134: =+SUM($W$129:W134) -> 0.086186774 | AA134: =+AA135-$AA$141/2.5 -> -59.448434 | AB134: =+AVERAGE(AA133:AA134) -> -66.053816 | AC134: =SUMIFS($W$129:$W$349,$V$129:$V$349,">="&AA133,$V$129:$V$349,"<"&AA134) -> 0 | AU134: =+NORMDIST('31Mar24'!$AA134,0,SQRT('31Mar24'!$C$103),TRUE) -> 0.035930319 | AV134: =+AU134-AU133 -> 0.022026872 | AW134: =+NORMDIST('31Mar24'!$AA134,0,SQRT($L$103),TRUE) -> 0.039159438 | AX134: =+AW134-AW133 -> 0.02345101
B135: =+B136+1 -> 46 | C135: =+'ZCB rates'!B180 -> 45061 | D135: =+'ZCB rates'!M180 -> -0.0001292615 | E135: =+'ZCB rates'!N180 -> -0.000290516 | F135: =+'ZCB rates'!O180 -> -0.000688786 | G135: =+'ZCB rates'!P180 -> -0.00167596 | H135: =+'ZCB rates'!Q180 -> -0.00485521 | I135: =+C$114*EXP(D135) -> 0.99031756 | J135: =+D$114*EXP(E135) -> 0.9816653 | K135: =+E$114*EXP(F135) -> 0.96655456 | L135: =+F$114*EXP(G135) -> 0.9409837 | M135: =+G$114*EXP(H135) -> 0.8682955 | N135: =+SUMPRODUCT(I135:M135,$C$113:$G$113) -> 15398.9 | O135: =+N135-$G$117 -> -33.937509 | P135: =+Lambda^B135 -> 0.058060566 | Q135: =+P135/$P$182 -> 0.0038606281 | R135: =+($O135-$C$123)^2 -> 1262.8736 | S135: =+($O135-$C$123)^3 -> -44878.653 | T135: =+($O135-$C$123)^4 -> 1594849.6 | V135: -42.647919 | W135: =+_xlfn.XLOOKUP(V135,$O$129:$O$180,$Q$129:$Q$180) -> 0.0052603991 | X135: =+SUM($W$129:W135) -> 0.091447173 | AA135: =+AA136-$AA$141/2.5 -> -46.237671 | AB135: =+AVERAGE(AA134:AA135) -> -52.843052 | AC135: =SUMIFS($W$129:$W$349,$V$129:$V$349,">="&AA134,$V$129:$V$349,"<"&AA135) -> 0.082079723 | AU135: =+NORMDIST('31Mar24'!$AA135,0,SQRT('31Mar24'!$C$103),TRUE) -> 0.080756659 | AV135: =+AU135-AU134 -> 0.04482634 | AW135: =+NORMDIST('31Mar24'!$AA135,0,SQRT($L$103),TRUE) -> 0.085453224 | AX135: =+AW135-AW134 -> 0.046293786
B136: =+B137+1 -> 45 | C136: =+'ZCB rates'!B181 -> 45068 | D136: =+'ZCB rates'!M181 -> -0.000138981 | E136: =+'ZCB rates'!N181 -> -0.000329905 | F136: =+'ZCB rates'!O181 -> -0.000833178 | G136: =+'ZCB rates'!P181 -> -0.002132008 | H136: =+'ZCB rates'!Q181 -> -0.00605765 | I136: =+C$114*EXP(D136) -> 0.99030794 | J136: =+D$114*EXP(E136) -> 0.98162664 | K136: =+E$114*EXP(F136) -> 0.96641501 | L136: =+F$114*EXP(G136) -> 0.94055467 | M136: =+G$114*EXP(H136) -> 0.86725205 | N136: =+SUMPRODUCT(I136:M136,$C$113:$G$113) -> 15390.038 | O136: =+N136-$G$117 -> -42.798879 | P136: =+Lambda^B136 -> 0.06176656 | Q136: =+P136/$P$182 -> 0.0041070511 | R136: =+($O136-$C$123)^2 -> 1971.2092 | S136: =+($O136-$C$123)^3 -> -87518.341 | T136: =+($O136-$C$123)^4 -> 3885665.7 | V136: -42.105413 | W136: =+_xlfn.XLOOKUP(V136,$O$129:$O$180,$Q$129:$Q$180) -> 0.0086297033 | X136: =+SUM($W$129:W136) -> 0.10007688 | AA136: =+AA137-$AA$141/2.5 -> -33.026908 | AB136: =+AVERAGE(AA135:AA136) -> -39.632289 | AC136: =SUMIFS($W$129:$W$349,$V$129:$V$349,">="&AA135,$V$129:$V$349,"<"&AA136) -> 0.033616408 | AU136: =+NORMDIST('31Mar24'!$AA136,0,SQRT('31Mar24'!$C$103),TRUE) -> 0.15865525 | AV136: =+AU136-AU135 -> 0.077898595 | AW136: =+NORMDIST('31Mar24'!$AA136,0,SQRT($L$103),TRUE) -> 0.16402002 | AX136: =+AW136-AW135 -> 0.078566801
B137: =+B138+1 -> 44 | C137: =+'ZCB rates'!B182 -> 45075 | D137: =+'ZCB rates'!M182 -> -9.0783e-05 | E137: =+'ZCB rates'!N182 -> -9.1309e-05 | F137: =+'ZCB rates'!O182 -> 0.000136748 | G137: =+'ZCB rates'!P182 -> 0.001268472 | H137: =+'ZCB rates'!Q182 -> 0.00692658 | I137: =+C$114*EXP(D137) -> 0.99035567 | J137: =+D$114*EXP(E137) -> 0.98186088 | K137: =+E$114*EXP(F137) -> 0.96735282 | L137: =+F$114*EXP(G137) -> 0.94375845 | M137: =+G$114*EXP(H137) -> 0.87858608 | N137: =+SUMPRODUCT(I137:M137,$C$113:$G$113) -> 15467.413 | O137: =+N137-$G$117 -> 34.575728 | P137: =+Lambda^B137 -> 0.065709106 | Q137: =+P137/$P$182 -> 0.0043692033 | R137: =+($O137-$C$123)^2 -> 1087.4367 | S137: =+($O137-$C$123)^3 -> 35859.643 | T137: =+($O137-$C$123)^4 -> 1182518.5 | V137: -34.656662 | W137: =+_xlfn.XLOOKUP(V137,$O$129:$O$180,$Q$129:$Q$180) -> 0.011758627 | X137: =+SUM($W$129:W137) -> 0.1118355 | AA137: =+AA138-$AA$141/2.5 -> -19.816145 | AB137: =+AVERAGE(AA136:AA137) -> -26.421526 | AC137: =SUMIFS($W$129:$W$349,$V$129:$V$349,">="&AA136,$V$129:$V$349,"<"&AA137) -> 0.15927096 | AU137: =+NORMDIST('31Mar24'!$AA137,0,SQRT('31Mar24'!$C$103),TRUE) -> 0.27425312 | AV137: =+AU137-AU136 -> 0.11559786 | AW137: =+NORMDIST('31Mar24'!$AA137,0,SQRT($L$103),TRUE) -> 0.27865505 | AX137: =+AW137-AW136 -> 0.11463503
B138: =+B139+1 -> 43 | C138: =+'ZCB rates'!B183 -> 45082 | D138: =+'ZCB rates'!M183 -> -0.0001920995 | E138: =+'ZCB rates'!N183 -> -0.000389552 | F138: =+'ZCB rates'!O183 -> -0.000790354 | G138: =+'ZCB rates'!P183 -> -0.001562264 | H138: =+'ZCB rates'!Q183 -> -0.00314186 | I138: =+C$114*EXP(D138) -> 0.99025533 | J138: =+D$114*EXP(E138) -> 0.98156809 | K138: =+E$114*EXP(F138) -> 0.9664564 | L138: =+F$114*EXP(G138) -> 0.94109069 | M138: =+G$114*EXP(H138) -> 0.86978447 | N138: =+SUMPRODUCT(I138:M138,$C$113:$G$113) -> 15404.929 | O138: =+N138-$G$117 -> -27.907861 | P138: =+Lambda^B138 -> 0.069903304 | Q138: =+P138/$P$182 -> 0.0046480886 | R138: =+($O138-$C$123)^2 -> 870.6798 | S138: =+($O138-$C$123)^3 -> -25691.396 | T138: =+($O138-$C$123)^4 -> 758083.31 | V138: -33.937509 | W138: =+_xlfn.XLOOKUP(V138,$O$129:$O$180,$Q$129:$Q$180) -> 0.0038606281 | X138: =+SUM($W$129:W138) -> 0.11569613 | AA138: =+AA139-$AA$141/2.5 -> -6.6053816 | AB138: =+AVERAGE(AA137:AA138) -> -13.210763 | AC138: =SUMIFS($W$129:$W$349,$V$129:$V$349,">="&AA137,$V$129:$V$349,"<"&AA138) -> 0.16118936 | AU138: =+NORMDIST('31Mar24'!$AA138,0,SQRT('31Mar24'!$C$103),TRUE) -> 0.42074029 | AV138: =+AU138-AU137 -> 0.14648717 | AW138: =+NORMDIST('31Mar24'!$AA138,0,SQRT($L$103),TRUE) -> 0.42245621 | AX138: =+AW138-AW137 -> 0.14380115
B139: =+B140+1 -> 42 | C139: =+'ZCB rates'!B184 -> 45089 | D139: =+'ZCB rates'!M184 -> 6.98765e-05 | E139: =+'ZCB rates'!N184 -> -0.000762187 | F139: =+'ZCB rates'!O184 -> -0.002240784 | G139: =+'ZCB rates'!P184 -> -0.002055712 | H139: =+'ZCB rates'!Q184 -> -0.00107824 | I139: =+C$114*EXP(D139) -> 0.99051479 | J139: =+D$114*EXP(E139) -> 0.98120239 | K139: =+E$114*EXP(F139) -> 0.96505563 | L139: =+F$114*EXP(G139) -> 0.94062643 | M139: =+G$114*EXP(H139) -> 0.87158123 | N139: =+SUMPRODUCT(I139:M139,$C$113:$G$113) -> 15403.871 | O139: =+N139-$G$117 -> -28.965894 | P139: =+Lambda^B139 -> 0.074365217 | Q139: =+P139/$P$182 -> 0.0049447752 | R139: =+($O139-$C$123)^2 -> 934.2386 | S139: =+($O139-$C$123)^3 -> -28555.299 | T139: =+($O139-$C$123)^4 -> 872801.77 | V139: -30.655518 | W139: =+_xlfn.XLOOKUP(V139,$O$129:$O$180,$Q$129:$Q$180) -> 0.043119297 | X139: =+SUM($W$129:W139) -> 0.15881543 | AA139: =+AA140-$AA$141/2.5 -> 6.6053816 | AB139: =+AVERAGE(AA138:AA139) -> 0 | AC139: =SUMIFS($W$129:$W$349,$V$129:$V$349,">="&AA138,$V$129:$V$349,"<"&AA139) -> 0.1310724 | AU139: =+NORMDIST('31Mar24'!$AA139,0,SQRT('31Mar24'!$C$103),TRUE) -> 0.57925971 | AV139: =+AU139-AU138 -> 0.15851942 | AW139: =+NORMDIST('31Mar24'!$AA139,0,SQRT($L$103),TRUE) -> 0.57754379 | AX139: =+AW139-AW138 -> 0.15508759
B140: =+B141+1 -> 41 | C140: =+'ZCB rates'!B185 -> 45096 | D140: =+'ZCB rates'!M185 -> -0.0001485155 | E140: =+'ZCB rates'!N185 -> -0.000378545 | F140: =+'ZCB rates'!O185 -> -0.00114649 | G140: =+'ZCB rates'!P185 -> -0.002730564 | H140: =+'ZCB rates'!Q185 -> -0.00334666 | I140: =+C$114*EXP(D140) -> 0.99029849 | J140: =+D$114*EXP(E140) -> 0.98157889 | K140: =+E$114*EXP(F140) -> 0.96611227 | L140: =+F$114*EXP(G140) -> 0.93999186 | M140: =+G$114*EXP(H140) -> 0.86960636 | N140: =+SUMPRODUCT(I140:M140,$C$113:$G$113) -> 15390.189 | O140: =+N140-$G$117 -> -42.647919 | P140: =+Lambda^B140 -> 0.079111933 | Q140: =+P140/$P$182 -> 0.0052603991 | R140: =+($O140-$C$123)^2 -> 1957.8273 | S140: =+($O140-$C$123)^3 -> -86628.656 | T140: =+($O140-$C$123)^4 -> 3833087.8 | V140: -29.660908 | W140: =+_xlfn.XLOOKUP(V140,$O$129:$O$180,$Q$129:$Q$180) -> 0.015060701 | X140: =+SUM($W$129:W140) -> 0.17387613 | AA140: =+AA141-$AA$141/2.5 -> 19.816145 | AB140: =+AVERAGE(AA139:AA140) -> 13.210763 | AC140: =SUMIFS($W$129:$W$349,$V$129:$V$349,">="&AA139,$V$129:$V$349,"<"&AA140) -> 0.16932552 | AU140: =+NORMDIST('31Mar24'!$AA140,0,SQRT('31Mar24'!$C$103),TRUE) -> 0.72574688 | AV140: =+AU140-AU139 -> 0.14648717 | AW140: =+NORMDIST('31Mar24'!$AA140,0,SQRT($L$103),TRUE) -> 0.72134495 | AX140: =+AW140-AW139 -> 0.14380115
B141: =+B142+1 -> 40 | C141: =+'ZCB rates'!B186 -> 45103 | D141: =+'ZCB rates'!M186 -> -0.0001030005 | E141: =+'ZCB rates'!N186 -> -0.000233121 | F141: =+'ZCB rates'!O186 -> -0.000439416 | G141: =+'ZCB rates'!P186 -> -0.000426912 | H141: =+'ZCB rates'!Q186 -> 0.00158293 | I141: =+C$114*EXP(D141) -> 0.99034357 | J141: =+D$114*EXP(E141) -> 0.98172165 | K141: =+E$114*EXP(F141) -> 0.96679562 | L141: =+F$114*EXP(G141) -> 0.94215977 | M141: =+G$114*EXP(H141) -> 0.87390374 | N141: =+SUMPRODUCT(I141:M141,$C$113:$G$113) -> 15431.845 | O141: =+N141-$G$117 -> -0.99253457 | P141: =+Lambda^B141 -> 0.084161631 | Q141: =+P141/$P$182 -> 0.0055961693 | R141: =+($O141-$C$123)^2 -> 6.7182449 | S141: =+($O141-$C$123)^3 -> -17.413407 | T141: =+($O141-$C$123)^4 -> 45.134815 | V141: -28.965894 | W141: =+_xlfn.XLOOKUP(V141,$O$129:$O$180,$Q$129:$Q$180) -> 0.0049447752 | X141: =+SUM($W$129:W141) -> 0.1788209 | AA141: =+SQRT(C103) -> 33.026908 | AB141: =+AVERAGE(AA140:AA141) -> 26.421526 | AC141: =SUMIFS($W$129:$W$349,$V$129:$V$349,">="&AA140,$V$129:$V$349,"<"&AA141) -> 0.042566192 | AU141: =+NORMDIST('31Mar24'!$AA141,0,SQRT('31Mar24'!$C$103),TRUE) -> 0.84134475 | AV141: =+AU141-AU140 -> 0.11559786 | AW141: =+NORMDIST('31Mar24'!$AA141,0,SQRT($L$103),TRUE) -> 0.83597998 | AX141: =+AW141-AW140 -> 0.11463503
B142: =+B143+1 -> 39 | C142: =+'ZCB rates'!B187 -> 45110 | D142: =+'ZCB rates'!M187 -> -0.0001739605 | E142: =+'ZCB rates'!N187 -> -0.00027584 | F142: =+'ZCB rates'!O187 -> -0.000697886 | G142: =+'ZCB rates'!P187 -> -0.002337252 | H142: =+'ZCB rates'!Q187 -> -0.00742241 | I142: =+C$114*EXP(D142) -> 0.9902733 | J142: =+D$114*EXP(E142) -> 0.98167971 | K142: =+E$114*EXP(F142) -> 0.96654577 | L142: =+F$114*EXP(G142) -> 0.94036164 | M142: =+G$114*EXP(H142) -> 0.86606927 | N142: =+SUMPRODUCT(I142:M142,$C$113:$G$113) -> 15383.905 | O142: =+N142-$G$117 -> -48.932764 | P142: =+Lambda^B142 -> 0.08953365 | Q142: =+P142/$P$182 -> 0.0059533716 | R142: =+($O142-$C$123)^2 -> 2553.5019 | S142: =+($O142-$C$123)^3 -> -129034.03 | T142: =+($O142-$C$123)^4 -> 6520372 | V142: -27.907861 | W142: =+_xlfn.XLOOKUP(V142,$O$129:$O$180,$Q$129:$Q$180) -> 0.0046480886 | X142: =+SUM($W$129:W142) -> 0.18346899 | AA142: =+AA141+$AA$141/2.5 -> 46.237671 | AB142: =+AVERAGE(AA141:AA142) -> 39.632289 | AC142: =SUMIFS($W$129:$W$349,$V$129:$V$349,">="&AA141,$V$129:$V$349,"<"&AA142) -> 0.12908338 | AU142: =+NORMDIST('31Mar24'!$AA142,0,SQRT('31Mar24'!$C$103),TRUE) -> 0.91924334 | AV142: =+AU142-AU141 -> 0.077898595 | AW142: =+NORMDIST('31Mar24'!$AA142,0,SQRT($L$103),TRUE) -> 0.91454678 | AX142: =+AW142-AW141 -> 0.078566801
B143: =+B144+1 -> 38 | C143: =+'ZCB rates'!B188 -> 45117 | D143: =+'ZCB rates'!M188 -> -0.0001474505 | E143: =+'ZCB rates'!N188 -> -0.000177877 | F143: =+'ZCB rates'!O188 -> 7.71e-06 | G143: =+'ZCB rates'!P188 -> 0.00042886 | H143: =+'ZCB rates'!Q188 -> -0.00107586 | I143: =+C$114*EXP(D143) -> 0.99029955 | J143: =+D$114*EXP(E143) -> 0.98177588 | K143: =+E$114*EXP(F143) -> 0.967228 | L143: =+F$114*EXP(G143) -> 0.94296639 | M143: =+G$114*EXP(H143) -> 0.8715833 | N143: =+SUMPRODUCT(I143:M143,$C$113:$G$113) -> 15434.979 | O143: =+N143-$G$117 -> 2.1417939 | P143: =+Lambda^B143 -> 0.095248564 | Q143: =+P143/$P$182 -> 0.006333374 | R143: =+($O143-$C$123)^2 -> 0.29416599 | S143: =+($O143-$C$123)^3 -> 0.15954701 | T143: =+($O143-$C$123)^4 -> 0.086533628 | V143: -27.840523 | W143: =+_xlfn.XLOOKUP(V143,$O$129:$O$180,$Q$129:$Q$180) -> 0.011053109 | X143: =+SUM($W$129:W143) -> 0.1945221 | AA143: =+AA142+$AA$141/2.5 -> 59.448434 | AB143: =+AVERAGE(AA142:AA143) -> 52.843052 | AC143: =SUMIFS($W$129:$W$349,$V$129:$V$349,">="&AA142,$V$129:$V$349,"<"&AA143) -> 0.042287178 | AU143: =+NORMDIST('31Mar24'!$AA143,0,SQRT('31Mar24'!$C$103),TRUE) -> 0.96406968 | AV143: =+AU143-AU142 -> 0.04482634 | AW143: =+NORMDIST('31Mar24'!$AA143,0,SQRT($L$103),TRUE) -> 0.96084056 | AX143: =+AW143-AW142 -> 0.046293786
B144: =+B145+1 -> 37 | C144: =+'ZCB rates'!B189 -> 45124 | D144: =+'ZCB rates'!M189 -> 2.7487e-05 | E144: =+'ZCB rates'!N189 -> 9.434e-06 | F144: =+'ZCB rates'!O189 -> 0.000367032 | G144: =+'ZCB rates'!P189 -> 0.002117252 | H144: =+'ZCB rates'!Q189 -> 0.00729552 | I144: =+C$114*EXP(D144) -> 0.9904728 | J144: =+D$114*EXP(E144) -> 0.9819598 | K144: =+E$114*EXP(F144) -> 0.96757561 | L144: =+F$114*EXP(G144) -> 0.94455983 | M144: =+G$114*EXP(H144) -> 0.87891028 | N144: =+SUMPRODUCT(I144:M144,$C$113:$G$113) -> 15478.775 | O144: =+N144-$G$117 -> 45.937581 | P144: =+Lambda^B144 -> 0.10132826 | Q144: =+P144/$P$182 -> 0.0067376319 | R144: =+($O144-$C$123)^2 -> 1965.8722 | S144: =+($O144-$C$123)^3 -> 87163.152 | T144: =+($O144-$C$123)^4 -> 3864653.6 | V144: -26.545663 | W144: =+_xlfn.XLOOKUP(V144,$O$129:$O$180,$Q$129:$Q$180) -> 0.031645426 | X144: =+SUM($W$129:W144) -> 0.22616753 | AA144: =+AA143+$AA$141/2.5 -> 72.659197 | AB144: =+AVERAGE(AA143:AA144) -> 66.053816 | AC144: =SUMIFS($W$129:$W$349,$V$129:$V$349,">="&AA143,$V$129:$V$349,"<"&AA144) -> 0 | AU144: =+NORMDIST('31Mar24'!$AA144,0,SQRT('31Mar24'!$C$103),TRUE) -> 0.98609655 | AV144: =+AU144-AU143 -> 0.022026872 | AW144: =+NORMDIST('31Mar24'!$AA144,0,SQRT($L$103),TRUE) -> 0.98429157 | AX144: =+AW144-AW143 -> 0.02345101
B145: =+B146+1 -> 36 | C145: =+'ZCB rates'!B190 -> 45131 | D145: =+'ZCB rates'!M190 -> -6.15055e-05 | E145: =+'ZCB rates'!N190 -> 1.2188e-05 | F145: =+'ZCB rates'!O190 -> 0.000244512 | G145: =+'ZCB rates'!P190 -> 0.000471952 | H145: =+'ZCB rates'!Q190 -> 0.0001164 | I145: =+C$114*EXP(D145) -> 0.99038466 | J145: =+D$114*EXP(E145) -> 0.9819625 | K145: =+E$114*EXP(F145) -> 0.96745707 | L145: =+F$114*EXP(G145) -> 0.94300702 | M145: =+G$114*EXP(H145) -> 0.87262307 | N145: =+SUMPRODUCT(I145:M145,$C$113:$G$113) -> 15438.959 | O145: =+N145-$G$117 -> 6.1220561 | P145: =+Lambda^B145 -> 0.10779602 | Q145: =+P145/$P$182 -> 0.0071676935 | R145: =+($O145-$C$123)^2 -> 20.454208 | S145: =+($O145-$C$123)^3 -> 92.506875 | T145: =+($O145-$C$123)^4 -> 418.37463 | V145: -24.848618 | W145: =+_xlfn.XLOOKUP(V145,$O$129:$O$180,$Q$129:$Q$180) -> 0.048799567 | X145: =+SUM($W$129:W145) -> 0.27496709 | AA145: =+AA144+$AA$141/2.5 -> 85.86996 | AB145: =+AVERAGE(AA144:AA145) -> 79.264579 | AC145: =SUMIFS($W$129:$W$349,$V$129:$V$349,">="&AA144,$V$129:$V$349,"<"&AA145) -> 0.049508889 | AU145: =+NORMDIST('31Mar24'!$AA145,0,SQRT('31Mar24'!$C$103),TRUE) -> 0.99533881 | AV145: =+AU145-AU144 -> 0.0092422595 | AW145: =+NORMDIST('31Mar24'!$AA145,0,SQRT($L$103),TRUE) -> 0.99450443 | AX145: =+AW145-AW144 -> 0.010212855
B146: =+B147+1 -> 35 | C146: =+'ZCB rates'!B191 -> 45138 | D146: =+'ZCB rates'!M191 -> -2.10335e-05 | E146: =+'ZCB rates'!N191 -> 8.4768e-05 | F146: =+'ZCB rates'!O191 -> 0.00036628 | G146: =+'ZCB rates'!P191 -> 0.000468644 | H146: =+'ZCB rates'!Q191 -> -0.00224308 | I146: =+C$114*EXP(D146) -> 0.99042475 | J146: =+D$114*EXP(E146) -> 0.98203377 | K146: =+E$114*EXP(F146) -> 0.96757488 | L146: =+F$114*EXP(G146) -> 0.9430039 | M146: =+G$114*EXP(H146) -> 0.87056657 | N146: =+SUMPRODUCT(I146:M146,$C$113:$G$113) -> 15432.453 | O146: =+N146-$G$117 -> -0.3837932 | P146: =+Lambda^B146 -> 0.11467662 | Q146: =+P146/$P$182 -> 0.0076252059 | R146: =+($O146-$C$123)^2 -> 3.9331472 | S146: =+($O146-$C$123)^3 -> -7.8002819 | T146: =+($O146-$C$123)^4 -> 15.469647 | V146: -18.040699 | W146: =+_xlfn.XLOOKUP(V146,$O$129:$O$180,$Q$129:$Q$180) -> 0.033665346 | X146: =+SUM($W$129:W146) -> 0.30863244 | AA146: =+AA145+$AA$141/2.5 -> 99.080723 | AB146: =+AVERAGE(AA145:AA146) -> 92.475342 | AC146: =SUMIFS($W$129:$W$349,$V$129:$V$349,">="&AA145,$V$129:$V$349,"<"&AA146) -> 0 | AU146: =+NORMDIST('31Mar24'!$AA146,0,SQRT('31Mar24'!$C$103),TRUE) -> 0.9986501 | AV146: =+AU146-AU145 -> 0.00331129 | AW146: =+NORMDIST('31Mar24'!$AA146,0,SQRT($L$103),TRUE) -> 0.998328 | AX146: =+AW146-AW145 -> 0.0038235724
B147: =+B148+1 -> 34 | C147: =+'ZCB rates'!B192 -> 45145 | D147: =+'ZCB rates'!M192 -> 5.79015e-05 | E147: =+'ZCB rates'!N192 -> 0.000108496 | F147: =+'ZCB rates'!O192 -> 0.000275188 | G147: =+'ZCB rates'!P192 -> 0.000679644 | H147: =+'ZCB rates'!Q192 -> 0.00097357 | I147: =+C$114*EXP(D147) -> 0.99050293 | J147: =+D$114*EXP(E147) -> 0.98205708 | K147: =+E$114*EXP(F147) -> 0.96748674 | L147: =+F$114*EXP(G147) -> 0.9432029 | M147: =+G$114*EXP(H147) -> 0.87337138 | N147: =+SUMPRODUCT(I147:M147,$C$113:$G$113) -> 15443.857 | O147: =+N147-$G$117 -> 11.02012 | P147: =+Lambda^B147 -> 0.1219964 | Q147: =+P147/$P$182 -> 0.0081119211 | R147: =+($O147-$C$123)^2 -> 88.749536 | S147: =+($O147-$C$123)^3 -> 836.08251 | T147: =+($O147-$C$123)^4 -> 7876.4802 | V147: -17.573404 | W147: =+_xlfn.XLOOKUP(V147,$O$129:$O$180,$Q$129:$Q$180) -> 0.012509177 | X147: =+SUM($W$129:W147) -> 0.32114162 | AA147: =+AA146+$AA$141/2.5 -> 112.29149 | AB147: =+AVERAGE(AA146:AA147) -> 105.6861 | AC147: =SUMIFS($W$129:$W$349,$V$129:$V$349,">="&AA146,$V$129:$V$349,"<"&AA147) -> 0 | AU147: =+NORMDIST('31Mar24'!$AA147,0,SQRT('31Mar24'!$C$103),TRUE) -> 0.99966307 | AV147: =+AU147-AU146 -> 0.0010129688 | AW147: =+NORMDIST('31Mar24'!$AA147,0,SQRT($L$103),TRUE) -> 0.9995586 | AX147: =+AW147-AW146 -> 0.0012305983
B148: =+B149+1 -> 33 | C148: =+'ZCB rates'!B193 -> 45152 | D148: =+'ZCB rates'!M193 -> -0.0001037445 | E148: =+'ZCB rates'!N193 -> -0.000215482 | F148: =+'ZCB rates'!O193 -> -0.000669054 | G148: =+'ZCB rates'!P193 -> -0.002035212 | H148: =+'ZCB rates'!Q193 -> -0.00626415 | I148: =+C$114*EXP(D148) -> 0.99034283 | J148: =+D$114*EXP(E148) -> 0.98173896 | K148: =+E$114*EXP(F148) -> 0.96657363 | L148: =+F$114*EXP(G148) -> 0.94064571 | M148: =+G$114*EXP(H148) -> 0.86707298 | N148: =+SUMPRODUCT(I148:M148,$C$113:$G$113) -> 15390.732 | O148: =+N148-$G$117 -> -42.105413 | P148: =+Lambda^B148 -> 0.12978341 | Q148: =+P148/$P$182 -> 0.0086297033 | R148: =+($O148-$C$123)^2 -> 1910.1127 | S148: =+($O148-$C$123)^3 -> -83481.165 | T148: =+($O148-$C$123)^4 -> 3648530.7 | V148: -13.855725 | W148: =+_xlfn.XLOOKUP(V148,$O$129:$O$180,$Q$129:$Q$180) -> 0.010389922 | X148: =+SUM($W$129:W148) -> 0.33153154 | AA148: =+AA147+$AA$141/2.5 -> 125.50225 | AB148: =+AVERAGE(AA147:AA148) -> 118.89687 | AC148: =SUMIFS($W$129:$W$349,$V$129:$V$349,">="&AA147,$V$129:$V$349,"<"&AA148) -> 0 | AU148: =+NORMDIST('31Mar24'!$AA148,0,SQRT('31Mar24'!$C$103),TRUE) -> 0.99992765 | AV148: =+AU148-AU147 -> 0.00026458122 | AW148: =+NORMDIST('31Mar24'!$AA148,0,SQRT($L$103),TRUE) -> 0.99989906 | AX148: =+AW148-AW147 -> 0.00034046685
B149: =+B150+1 -> 32 | C149: =+'ZCB rates'!B194 -> 45159 | D149: =+'ZCB rates'!M194 -> -6.6815e-06 | E149: =+'ZCB rates'!N194 -> 4.1621e-05 | F149: =+'ZCB rates'!O194 -> 0.000323556 | G149: =+'ZCB rates'!P194 -> 0.001113952 | H149: =+'ZCB rates'!Q194 -> 0.00307796 | I149: =+C$114*EXP(D149) -> 0.99043896 | J149: =+D$114*EXP(E149) -> 0.9819914 | K149: =+E$114*EXP(F149) -> 0.96753354 | L149: =+F$114*EXP(G149) -> 0.94361263 | M149: =+G$114*EXP(H149) -> 0.87521123 | N149: =+SUMPRODUCT(I149:M149,$C$113:$G$113) -> 15454.942 | O149: =+N149-$G$117 -> 22.104461 | P149: =+Lambda^B149 -> 0.13806745 | Q149: =+P149/$P$182 -> 0.0091805355 | R149: =+($O149-$C$123)^2 -> 420.45659 | S149: =+($O149-$C$123)^3 -> 8621.4783 | T149: =+($O149-$C$123)^4 -> 176783.74 | V149: -12.394564 | W149: =+_xlfn.XLOOKUP(V149,$O$129:$O$180,$Q$129:$Q$180) -> 0.058753319 | X149: =+SUM($W$129:W149) -> 0.39028486
B150: =+B151+1 -> 31 | C150: =+'ZCB rates'!B195 -> 45166 | D150: =+'ZCB rates'!M195 -> -1.8691e-05 | E150: =+'ZCB rates'!N195 -> -7.7828e-05 | F150: =+'ZCB rates'!O195 -> -0.000124864 | G150: =+'ZCB rates'!P195 -> 0.000152324 | H150: =+'ZCB rates'!Q195 -> 0.0020439 | I150: =+C$114*EXP(D150) -> 0.99042707 | J150: =+D$114*EXP(E150) -> 0.98187411 | K150: =+E$114*EXP(F150) -> 0.96709978 | L150: =+F$114*EXP(G150) -> 0.94270566 | M150: =+G$114*EXP(H150) -> 0.87430668 | N150: =+SUMPRODUCT(I150:M150,$C$113:$G$113) -> 15440.263 | O150: =+N150-$G$117 -> 7.4258458 | P150: =+Lambda^B150 -> 0.14688027 | Q150: =+P150/$P$182 -> 0.0097665271 | R150: =+($O150-$C$123)^2 -> 33.9472 | S150: =+($O150-$C$123)^3 -> 197.79074 | T150: =+($O150-$C$123)^4 -> 1152.4124 | V150: -11.955047 | W150: =+_xlfn.XLOOKUP(V150,$O$129:$O$180,$Q$129:$Q$180) -> 0.045871593 | X150: =+SUM($W$129:W150) -> 0.43615645
...

Sheet 30Jun24
B3: Legend
D5: Cashflows to be clumped
D6: Cashflows already at the correct nodes
B9: Date at which cashflows must be computed
B11: VaR comp. date | C11: 45473
B13: Nodes | C13: =+EOMONTH($C$11,'ZCB rates'!C$3) -> 45565 | D13: =+EOMONTH($C$11,'ZCB rates'!D$3) -> 45657 | E13: =+EOMONTH($C$11,'ZCB rates'!E$3) -> 45838 | F13: =+EOMONTH($C$11,'ZCB rates'!F$3) -> 46203 | G13: =+EOMONTH($C$11,'ZCB rates'!G$3) -> 47299
B14: Diff from today | C14: =+C13-$C$11 -> 92 | D14: =+D13-$C$11 -> 184 | E14: =+E13-$C$11 -> 365 | F14: =+F13-$C$11 -> 730 | G14: =+G13-$C$11 -> 1826
B17: Term structure of int rates
C19: =+'ZCB rates'!C3 -> 3 | D19: =+'ZCB rates'!D3 -> 6 | E19: =+'ZCB rates'!E3 -> 12 | F19: =+'ZCB rates'!F3 -> 24 | G19: =+'ZCB rates'!G3 -> 60
B20: =+C11 -> 45473 | C20: ='ZCB rates'!R238 -> 0.036486102 | D20: ='ZCB rates'!S238 -> 0.035332016 | E20: ='ZCB rates'!T238 -> 0.03345475 | F20: ='ZCB rates'!U238 -> 0.031036344 | G20: ='ZCB rates'!V238 -> 0.029483088
B23: Security 7
C26: =+Assumptions!E7 -> 45657 | D26: =+Assumptions!F7 -> 45838 | E26: =+Assumptions!G7 -> 46022 | F26: =+Assumptions!H7 -> 46203 | G26: =+Assumptions!I7 -> 46387
B27: t from today (duration) | C27: =+(C26-$C$11)/365 -> 0.50410959 | D27: =+(D26-$C$11)/365 -> 1 | E27: =+(E26-$C$11)/365 -> 1.5041096 | F27: =+(F26-$C$11)/365 -> 2 | G27: =+(G26-$C$11)/365 -> 2.5041096
B28: Interpolated rate | E28: =+_xlfn.LET(_xlpm.t_rem,E27,_xlpm.r_m1,E20,_xlpm.r_m2,F20,_xlpm.mone,E19,_xlpm.mtwo,F19,_xlpm.r_m1+(_xlpm.r_m2-_xlpm.r_m1)/(_xlpm.mtwo/month_in_a_year-_xlpm.mone/month_in_a_year)*(_xlpm.t_rem-_xlpm.mone/month_in_a_year)) -> 0.032235609 | G28: =+_xlfn.LET(_xlpm.t_rem,G27,_xlpm.r_m1,F20,_xlpm.r_m2,G20,_xlpm.mone,F19,_xlpm.mtwo,G19,_xlpm.r_m1+(_xlpm.r_m2-_xlpm.r_m1)/(_xlpm.mtwo/month_in_a_year-_xlpm.mone/month_in_a_year)*(_xlpm.t_rem-_xlpm.mone/month_in_a_year)) -> 0.030775341
B29: Modified Duration | E29: =+E27/(1+E28) -> 1.4571379 | G29: =+G27/(1+G28) -> 2.4293456
B31: Goal nodes | C31: 6m | D31: 12m | E31: 12m & 24m | F31: 24m | G31: 24m & 60m
B32: MD 1 | E32: =+(E$19/month_in_a_year)/(1+E$20) -> 0.96762824 | G32: =+(F$19/month_in_a_year)/(1+F$20) -> 1.9397958
B33: MD 2 | E33: =+(F$19/month_in_a_year)/(1+F$20) -> 1.9397958 | G33: =+(G$19/month_in_a_year)/(1+G$20) -> 4.8568064
B35: Market value real cashflow | C35: =Assumptions!E8/(1+D20)^C27 -> 196.52971 | D35: =Assumptions!F8/(1+'30Jun24'!E20)^'30Jun24'!D27 -> 193.52565 | E35: =+Assumptions!G8/(1+E28)^E27 -> 190.67999 | F35: =F40/(1+F20)^F27 -> 188.14039 | G35: =+Assumptions!I8/(1+G28)^G27 -> 9454.4446
B37: Mkt value virtual cashflow | E37: =+_xlfn.LET(_xlpm.MDvirt1,E32,_xlpm.MDvirt2,E33,_xlpm.MDreal,E29,_xlpm.Mvreal,E35,(_xlpm.MDvirt2-_xlpm.MDreal)/(_xlpm.MDvirt2-_xlpm.MDvirt1)*_xlpm.Mvreal) -> 94.668055 | G37: =+_xlfn.LET(_xlpm.MDvirt1,G32,_xlpm.MDvirt2,G33,_xlpm.MDreal,G29,_xlpm.Mvreal,G35,(_xlpm.MDvirt2-_xlpm.MDreal)/(_xlpm.MDvirt2-_xlpm.MDvirt1)*_xlpm.Mvreal) -> 7867.7443
B38: Mkt value Virtual cashflow | E38: =+E35-E37 -> 96.011933 | G38: =+G35-G37 -> 1586.7004
B40: Face value 1 | C40: =Assumptions!E8 -> 200 | D40: =Assumptions!F8 -> 200 | E40: =+E37*(1+E20)^(E19/month_in_a_year) -> 97.835151 | F40: =Assumptions!H8 -> 200 | G40: =+G37*(1+F20)^(F19/month_in_a_year) -> 8363.6949
B41: Face value 2 | E41: =+E38*(1+F20)^(F19/month_in_a_year) -> 102.06414 | G41: =+G38*(1+G20)^(G19/month_in_a_year) -> 1834.8096
B43: Check | E43: =ROUND(+E29-E32*E37/E35-E33*E38/E35,5) -> 0 | G43: =+G29-G32*G37/G35-G33*G38/G35 -> 0
B47: Security 10
C50: =+Assumptions!E10 -> 45747 | D50: =+Assumptions!F10 -> 45838 | E50: =+Assumptions!G10 -> 46022 | F50: =+Assumptions!H10 -> 46203
B51: t from today (duration) | C51: =+(C50-$C$11)/365 -> 0.75068493 | D51: =+(D50-$C$11)/365 -> 1 | E51: =+(E50-$C$11)/365 -> 1.5041096 | F51: =+(F50-$C$11)/365 -> 2
B52: Interpolated rate | C52: =+_xlfn.LET(_xlpm.t_rem,C51,_xlpm.r_m1,D20,_xlpm.r_m2,E20,_xlpm.mone,D19,_xlpm.mtwo,E19,_xlpm.r_m1+(_xlpm.r_m2-_xlpm.r_m1)/(_xlpm.mtwo/month_in_a_year-_xlpm.mone/month_in_a_year)*(_xlpm.t_rem-_xlpm.mone/month_in_a_year)) -> 0.034390812 | E52: =+_xlfn.LET(_xlpm.t_rem,E51,_xlpm.r_m1,E20,_xlpm.r_m2,F20,_xlpm.mone,E19,_xlpm.mtwo,F19,_xlpm.r_m1+(_xlpm.r_m2-_xlpm.r_m1)/(_xlpm.mtwo/month_in_a_year-_xlpm.mone/month_in_a_year)*(_xlpm.t_rem-_xlpm.mone/month_in_a_year)) -> 0.032235609
B53: Modified Duration | C53: =+C51/(1+C52) -> 0.7257266 | E53: =+E51/(1+E52) -> 1.4571379
B55: Goal nodes | C55: 6m & 12m | D55: 12m | E55: 12m & 24m | F55: 24m
B56: MD 1 | C56: =+(D$19/12)/(1+D$20) -> 0.48293687 | E56: =+(E$19/12)/(1+E$20) -> 0.96762824
B57: MD 2 | C57: =+(E$19/12)/(1+E$20) -> 0.96762824 | E57: =+(F$19/12)/(1+F$20) -> 1.9397958
B59: Market value real cashflow | C59: =+Assumptions!E$11/(1+C52)^C51 -> 146.24052 | D59: =D64/(1+E20)^D51 -> 145.14424 | E59: =+Assumptions!G$11/(1+E52)^E51 -> 143.00999 | F59: =F64/(1+F20)^F51 -> 4844.6151
B61: Mkt value Virtual cashflow 1 | C61: =+_xlfn.LET(_xlpm.MDvirt1,C56,_xlpm.MDvirt2,C57,_xlpm.MDreal,C53,_xlpm.Mvreal,C59,(_xlpm.MDvirt2-_xlpm.MDreal)/(_xlpm.MDvirt2-_xlpm.MDvirt1)*_xlpm.Mvreal) -> 72.986279 | E61: =+_xlfn.LET(_xlpm.MDvirt1,E56,_xlpm.MDvirt2,E57,_xlpm.MDreal,E53,_xlpm.Mvreal,E59,(_xlpm.MDvirt2-_xlpm.MDreal)/(_xlpm.MDvirt2-_xlpm.MDvirt1)*_xlpm.Mvreal) -> 71.001041
B62: Mkt value Virtual cashflow 2 | C62: =+C59-C61 -> 73.254237 | E62: =+E59-E61 -> 72.008949
B64: Face value 1 | C64: =+C61*(1+D20)^(D19/month_in_a_year) -> 74.264463 | D64: =Assumptions!F11 -> 150 | E64: =+E61*(1+E20)^(E19/month_in_a_year) -> 73.376363 | F64: =Assumptions!H11 -> 5150
B65: Face value 2 | C65: =+C62*(1+E20)^(E19/month_in_a_year) -> 75.704939 | E65: =+E62*(1+F20)^(F19/month_in_a_year) -> 76.548102
B67: Check | C67: =ROUND(+C53-C56*C61/C59-C57*C62/C59,5) -> 0 | E67: =ROUND(+E53-E56*E61/E59-E57*E62/E59,5) -> 0
B69: New Portfolio
C71: =+C72-$C$11 -> 92 | D71: =+D72-$C$11 -> 184 | E71: =+E72-$C$11 -> 365 | F71: =+F72-$C$11 -> 730 | G71: =+G72-$C$11 -> 1826
C72: =+C13 -> 45565 | D72: =+D13 -> 45657 | E72: =+E13 -> 45838 | F72: =+F13 -> 46203 | G72: =+G13 -> 47299
B73: Cashflows | C73: 0 | D73: =C40+C64 -> 274.26446 | E73: =D40+'30Jun24'!C65+D64+'30Jun24'!E64+E40 -> 596.91645 | F73: =E41+G40+E65+F40+F64 -> 13892.307 | G73: =G41 -> 1834.8096
B74: Disc factor | C74: =+'ZCB rates'!H238 -> 0.99108095 | D74: =+'ZCB rates'!I238 -> 0.98278875 | E74: =+'ZCB rates'!J238 -> 0.96762824 | F74: =+'ZCB rates'!K238 -> 0.94070196 | G74: =+'ZCB rates'!L238 -> 0.86477658
C75: =1/(1+C20)^(C71/365) -> 0.99100798 | D75: =1/(1+D20)^(D71/365) -> 0.98264853 | E75: =1/(1+E20)^(E71/365) -> 0.96762824 | F75: =1/(1+F20)^(F71/365) -> 0.94070196 | G75: =1/(1+G20)^(G71/365) -> 0.86470774
B78: PV of cashflow | C78: =+C73*C74 -> 0 | D78: =+D73*D74 -> 269.54403 | E78: =+E73*E74 -> 577.59322 | F78: =+F73*F74 -> 13068.521 | G78: =+G73*G74 -> 1586.7004
B80: Sum of PV | G80: =+SUM(C78:G78) -> 15502.358 | I80: Check | J80: =ROUND(SUM(C59:F59)+SUM(C35:G35)-G80,1) -> 0
B82: Var computation - parametric approach
C84: =+C72 -> 45565 | D84: =+D72 -> 45657 | E84: =+E72 -> 45838 | F84: =+F72 -> 46203 | G84: =+G72 -> 47299
B85: δ' | C85: =C78 -> 0 | D85: =D78 -> 269.54403 | E85: =E78 -> 577.59322 | F85: =F78 -> 13068.521 | G85: =G78 -> 1586.7004
B87: δ | C87: {=+TRANSPOSE(C85:G85)} -> 0
C88: 269.54403
C89: 577.59322
C90: 13068.521
C91: 1586.7004
C94: EWMA | L94: Simple moving average
B96: Σ | C96: {=+EWMACovMatrix('ZCB rates'!M187:Q238,Lambda)} -> 4.9820745e-09 | D96: 7.1073742e-09 | E96: 8.6219813e-09 | F96: 1.2617017e-08 | G96: 4.0529228e-08 | L96: {=CovarianceMatrix('ZCB rates'!M187:Q238)} -> 5.9550025e-09 | M96: 8.9389395e-09 | N96: 1.4410115e-08 | O96: 3.3132942e-08 | P96: 1.1331767e-07
C97: 7.1073742e-09 | D97: 1.6921355e-08 | E97: 4.3593813e-08 | F97: 1.1171551e-07 | G97: 3.0524833e-07 | L97: 8.9389395e-09 | M97: 2.3927758e-08 | N97: 6.8095392e-08 | O97: 1.8052594e-07 | P97: 4.9590065e-07
C98: 8.6219813e-09 | D98: 4.3593813e-08 | E98: 1.6311586e-07 | F98: 4.7761043e-07 | G98: 1.303132e-06 | L98: 1.4410115e-08 | M98: 6.8095392e-08 | N98: 2.5218228e-07 | O98: 7.2526437e-07 | P98: 1.9353713e-06
C99: 1.2617017e-08 | D99: 1.1171551e-07 | E99: 4.7761043e-07 | F99: 1.4812031e-06 | G99: 4.2194721e-06 | L99: 3.3132942e-08 | M99: 1.8052594e-07 | N99: 7.2526437e-07 | O99: 2.2087494e-06 | P99: 6.1617516e-06
C100: 4.0529228e-08 | D100: 3.0524833e-07 | E100: 1.303132e-06 | F100: 4.2194721e-06 | G100: 1.3464665e-05 | L100: 1.1331767e-07 | M100: 4.9590065e-07 | N100: 1.9353713e-06 | O100: 6.1617516e-06 | P100: 1.9379826e-05
B103: σ2ΔV | C103: {=+MMULT(TRANSPOSE(_xlfn.ANCHORARRAY(C87)),MMULT(_xlfn.ANCHORARRAY(C96),_xlfn.ANCHORARRAY(C87)))} -> 472.57266 | K103: σ2ΔV | L103: {=+MMULT(TRANSPOSE(_xlfn.ANCHORARRAY(C87)),MMULT(_xlfn.ANCHORARRAY(L96),_xlfn.ANCHORARRAY(C87)))} -> 697.85251
B105: CI | C105: 0.95 | D105: 0.99 | K105: CI | L105: 0.95 | M105: 0.99
B106: Var | C106: =+SQRT($C$103)*(-1)*_xlfn.NORM.S.INV(1-C105) -> 35.75704 | D106: =+SQRT($C$103)*(-1)*_xlfn.NORM.S.INV(1-D105) -> 50.571863 | K106: Var | L106: =+SQRT($L$103)*(-1)*_xlfn.NORM.S.INV(1-L105) -> 43.451931 | M106: =+SQRT($L$103)*(-1)*_xlfn.NORM.S.INV(1-M105) -> 61.454895
B110: Var computation - hybrid approach
C112: =+C72 -> 45565 | D112: =+D72 -> 45657 | E112: =+E72 -> 45838 | F112: =+F72 -> 46203 | G112: =+G72 -> 47299
B113: =+B73 -> Cashflows | C113: =+C73 -> 0 | D113: =+D73 -> 274.26446 | E113: =+E73 -> 596.91645 | F113: =+F73 -> 13892.307 | G113: =+G73 -> 1834.8096
B114: Discount factor | C114: =+C74 -> 0.99108095 | D114: =+D74 -> 0.98278875 | E114: =+E74 -> 0.96762824 | F114: =+F74 -> 0.94070196 | G114: =+G74 -> 0.86477658
B116: PV of Cashflows | C116: =+C114*C113 -> 0 | D116: =+D114*D113 -> 269.54403 | E116: =+E114*E113 -> 577.59322 | F116: =+F114*F113 -> 13068.521 | G116: =+G114*G113 -> 1586.7004
G117: =+SUM(C116:G116) -> 15502.358
B119: CI | C119: 0.95 | D119: 0.99 | N119: Check | Q119: =+SUM(Q129:Q389)-1 -> 0 | W119: =+SUM(W129:W389)-1 -> 0
B120: Plain vanilla VaR | C120: {=-(INDEX(_xlfn.ANCHORARRAY(V129),MATCH(TRUE,X129:X349>=1-C119,0))-$C$123)} -> 28.40084 | D120: {=-(INDEX(_xlfn.ANCHORARRAY(V129),MATCH(TRUE,X129:X180>=1-D119,0))-$C$123)} -> 53.008952
B121: Interpolated Var | C121: =+_xlfn.LET(_xlpm.x_1,V133,_xlpm.x_2,V134,_xlpm.alfa_1,X133,_xlpm.alfa_2,X134,_xlpm.p,(1-C119),_xlpm.mu,C123,(-1)*(_xlpm.x_1*(_xlpm.alfa_2-_xlpm.p)/(_xlpm.alfa_2-_xlpm.alfa_1)+_xlpm.x_2*(_xlpm.p-_xlpm.alfa_1)/(_xlpm.alfa_2-_xlpm.alfa_1)-_xlpm.mu)) -> 30.156328 | D121: n.m.
B123: Mean | C123: =+SUMPRODUCT(O129:O180,Q129:Q180) -> -0.020245369
B124: Variance | C124: =+SUMPRODUCT(Q129:Q180,R129:R180) -> 471.21895
B125: Skewness | C125: =+(SUMPRODUCT(Q129:Q180,S129:S180)/(C124^(3/2))-3) -> -2.4383922
B126: Excess Kurtosis | C126: =+(SUMPRODUCT(Q129:Q180,T129:T180)/(C124^2))-3 -> 1.1292165 | AU126: Parametric
Z127: Hybrid | AU127: EWMA | AW127: SMA
B128: Ordering factor | C128: Date | D128: r 3m | E128: r 6m | F128: r 12m | G128: r 24m | H128: r 60m | I128: PZCB3M | J128: PZCB6M | K128: PZCB12M | L128: PZCB24M | M128: PZCB60M | N128: V | O128: ΔV | P128: λi | Q128: frequency | R128: (ΔV-μ)2 | S128: (ΔV-μ)3 | T128: (ΔV-μ)4 | V128: Sorted ΔV | W128: Frequency | X128: Cum Frequency | Z128: Bands | AA128: Band average | AB128: Frequency | AE128: Changes in the portfolio's value: frequency distribution | AU128: Cum. Freq. | AV128: PseudoN | AW128: Cum. Freq. | AX128: PseudoN
B129: =+B130+1 -> 52 | C129: =+'ZCB rates'!B187 -> 45110 | D129: =+'ZCB rates'!M187 -> -0.0001739605 | E129: =+'ZCB rates'!N187 -> -0.00027584 | F129: =+'ZCB rates'!O187 -> -0.000697886 | G129: =+'ZCB rates'!P187 -> -0.002337252 | H129: =+'ZCB rates'!Q187 -> -0.00742241 | I129: =+C$114*EXP(D129) -> 0.99090856 | J129: =+D$114*EXP(E129) -> 0.9825177 | K129: =+E$114*EXP(F129) -> 0.96695318 | L129: =+F$114*EXP(G129) -> 0.93850587 | M129: =+G$114*EXP(H129) -> 0.85838161 | N129: =+SUMPRODUCT(I129:M129,$C$113:$G$113) -> 15459.639 | O129: =+N129-$G$117 -> -42.719594 | P129: =+Lambda^B129 -> 0.04005423 | Q129: =+P129/$P$184 -> 0.0026633306 | R129: =+(O129-$C$123)^2 -> 1823.2344 | S129: =+($O129-$C$123)^3 -> -77850.922 | T129: =+($O129-$C$123)^4 -> 3324183.7 | V129: {=+_xlfn._xlws.SORT(O129:O180)} -> -53.029197 | W129: =+_xlfn.XLOOKUP(V129,$O$129:$O$180,$Q$129:$Q$180) -> 0.018132664 | X129: =+SUM($W$129:W129) -> 0.018132664 | Z129: =+Z130-$Z$141/2.5 -> -82.607199 | AU129: =+NORMDIST($Z129,0,SQRT($C$103),TRUE) -> 7.2348044e-05 | AW129: =+NORMDIST($Z129,0,SQRT($L$103),TRUE) -> 0.00088282251
B130: =+B131+1 -> 51 | C130: =+'ZCB rates'!B188 -> 45117 | D130: =+'ZCB rates'!M188 -> -0.0001474505 | E130: =+'ZCB rates'!N188 -> -0.000177877 | F130: =+'ZCB rates'!O188 -> 7.71e-06 | G130: =+'ZCB rates'!P188 -> 0.00042886 | H130: =+'ZCB rates'!Q188 -> -0.00107586 | I130: =+C$114*EXP(D130) -> 0.99093483 | J130: =+D$114*EXP(E130) -> 0.98261395 | K130: =+E$114*EXP(F130) -> 0.9676357 | L130: =+F$114*EXP(G130) -> 0.94110548 | M130: =+G$114*EXP(H130) -> 0.8638467 | N130: =+SUMPRODUCT(I130:M130,$C$113:$G$113) -> 15506.214 | O130: =+N130-$G$117 -> 3.8561301 | P130: =+Lambda^B130 -> 0.042610883 | Q130: =+P130/$P$184 -> 0.0028333305 | R130: =+(O130-$C$123)^2 -> 15.026286 | S130: =+($O130-$C$123)^3 -> 58.247528 | T130: =+($O130-$C$123)^4 -> 225.78928 | V130: -43.022537 | W130: =+_xlfn.XLOOKUP(V130,$O$129:$O$180,$Q$129:$Q$180) -> 0.013307635 | X130: =+SUM($W$129:W130) -> 0.0314403 | Z130: =+Z131-$Z$141/2.5 -> -73.911704 | AA130: =+AVERAGE(Z129:Z130) -> -78.259451 | AB130: =SUMIFS($W$129:$W$362,$V$129:$V$362,">="&Z129,$V$129:$V$362,"<"&Z130) -> 0 | AU130: =+NORMDIST($Z130,0,SQRT($C$103),TRUE) -> 0.00033692927 | AV130: =+AU130-AU129 -> 0.00026458122 | AW130: =+NORMDIST($Z130,0,SQRT($L$103),TRUE) -> 0.0025718425 | AX130: =+AW130-AW129 -> 0.00168902
B131: =+B132+1 -> 50 | C131: =+'ZCB rates'!B189 -> 45124 | D131: =+'ZCB rates'!M189 -> 2.7487e-05 | E131: =+'ZCB rates'!N189 -> 9.434e-06 | F131: =+'ZCB rates'!O189 -> 0.000367032 | G131: =+'ZCB rates'!P189 -> 0.002117252 | H131: =+'ZCB rates'!Q189 -> 0.00729552 | I131: =+C$114*EXP(D131) -> 0.99110819 | J131: =+D$114*EXP(E131) -> 0.98279802 | K131: =+E$114*EXP(F131) -> 0.96798345 | L131: =+F$114*EXP(G131) -> 0.94269578 | M131: =+G$114*EXP(H131) -> 0.87110864 | N131: =+SUMPRODUCT(I131:M131,$C$113:$G$113) -> 15541.89 | O131: =+N131-$G$117 -> 39.531374 | P131: =+Lambda^B131 -> 0.045330727 | Q131: =+P131/$P$184 -> 0.0030141813 | R131: =+(O131-$C$123)^2 -> 1564.3306 | S131: =+($O131-$C$123)^3 -> 61871.806 | T131: =+($O131-$C$123)^4 -> 2447130.1 | V131: -42.719594 | W131: =+_xlfn.XLOOKUP(V131,$O$129:$O$180,$Q$129:$Q$180) -> 0.0026633306 | X131: =+SUM($W$129:W131) -> 0.03410363 | Z131: =+Z132-$Z$141/2.5 -> -65.21621 | AA131: =+AVERAGE(Z130:Z131) -> -69.563957 | AB131: =SUMIFS($W$129:$W$362,$V$129:$V$362,">="&Z130,$V$129:$V$362,"<"&Z131) -> 0 | AU131: =+NORMDIST($Z131,0,SQRT($C$103),TRUE) -> 0.001349898 | AV131: =+AU131-AU130 -> 0.0010129688 | AW131: =+NORMDIST($Z131,0,SQRT($L$103),TRUE) -> 0.0067796595 | AX131: =+AW131-AW130 -> 0.004207817
B132: =+B133+1 -> 49 | C132: =+'ZCB rates'!B190 -> 45131 | D132: =+'ZCB rates'!M190 -> -6.15055e-05 | E132: =+'ZCB rates'!N190 -> 1.2188e-05 | F132: =+'ZCB rates'!O190 -> 0.000244512 | G132: =+'ZCB rates'!P190 -> 0.000471952 | H132: =+'ZCB rates'!Q190 -> 0.0001164 | I132: =+C$114*EXP(D132) -> 0.99102 | J132: =+D$114*EXP(E132) -> 0.98280073 | K132: =+E$114*EXP(F132) -> 0.96786486 | L132: =+F$114*EXP(G132) -> 0.94114604 | M132: =+G$114*EXP(H132) -> 0.86487724 | N132: =+SUMPRODUCT(I132:M132,$C$113:$G$113) -> 15508.857 | O132: =+N132-$G$117 -> 6.4984038 | P132: =+Lambda^B132 -> 0.048224177 | Q132: =+P132/$P$184 -> 0.0032065759 | R132: =+(O132-$C$123)^2 -> 42.492786 | S132: =+($O132-$C$123)^3 -> 276.99556 | T132: =+($O132-$C$123)^4 -> 1805.6369 | V132: -36.922814 | W132: =+_xlfn.XLOOKUP(V132,$O$129:$O$180,$Q$129:$Q$180) -> 0.0038606281 | X132: =+SUM($W$129:W132) -> 0.037964258 | Z132: =+Z133-$Z$141/2.5 -> -56.520715 | AA132: =+AVERAGE(Z131:Z132) -> -60.868462 | AB132: =SUMIFS($W$129:$W$362,$V$129:$V$362,">="&Z131,$V$129:$V$362,"<"&Z132) -> 0 | AU132: =+NORMDIST($Z132,0,SQRT($C$103),TRUE) -> 0.004661188 | AV132: =+AU132-AU131 -> 0.00331129 | AW132: =+NORMDIST($Z132,0,SQRT($L$103),TRUE) -> 0.016194901 | AX132: =+AW132-AW131 -> 0.0094152418
B133: =+B134+1 -> 48 | C133: =+'ZCB rates'!B191 -> 45138 | D133: =+'ZCB rates'!M191 -> -2.10335e-05 | E133: =+'ZCB rates'!N191 -> 8.4768e-05 | F133: =+'ZCB rates'!O191 -> 0.00036628 | G133: =+'ZCB rates'!P191 -> 0.000468644 | H133: =+'ZCB rates'!Q191 -> -0.00224308 | I133: =+C$114*EXP(D133) -> 0.99106011 | J133: =+D$114*EXP(E133) -> 0.98287207 | K133: =+E$114*EXP(F133) -> 0.96798273 | L133: =+F$114*EXP(G133) -> 0.94114292 | M133: =+G$114*EXP(H133) -> 0.86283899 | N133: =+SUMPRODUCT(I133:M133,$C$113:$G$113) -> 15505.164 | O133: =+N133-$G$117 -> 2.8052612 | P133: =+Lambda^B133 -> 0.051302316 | Q133: =+P133/$P$184 -> 0.003411251 | R133: =+(O133-$C$123)^2 -> 7.9834874 | S133: =+($O133-$C$123)^3 -> 22.557396 | T133: =+($O133-$C$123)^4 -> 63.736071 | V133: -31.126977 | W133: =+_xlfn.XLOOKUP(V133,$O$129:$O$180,$Q$129:$Q$180) -> 0.0052603991 | X133: =+SUM($W$129:W133) -> 0.043224658 | Z133: =+Z134-$Z$141/2.5 -> -47.82522 | AA133: =+AVERAGE(Z132:Z133) -> -52.172968 | AB133: =SUMIFS($W$129:$W$362,$V$129:$V$362,">="&Z132,$V$129:$V$362,"<"&Z133) -> 0.018132664 | AU133: =+NORMDIST($Z133,0,SQRT($C$103),TRUE) -> 0.013903448 | AV133: =+AU133-AU132 -> 0.0092422595 | AW133: =+NORMDIST($Z133,0,SQRT($L$103),TRUE) -> 0.035116691 | AX133: =+AW133-AW132 -> 0.018921789
B134: =+B135+1 -> 47 | C134: =+'ZCB rates'!B192 -> 45145 | D134: =+'ZCB rates'!M192 -> 5.79015e-05 | E134: =+'ZCB rates'!N192 -> 0.000108496 | F134: =+'ZCB rates'!O192 -> 0.000275188 | G134: =+'ZCB rates'!P192 -> 0.000679644 | H134: =+'ZCB rates'!Q192 -> 0.00097357 | I134: =+C$114*EXP(D134) -> 0.99113834 | J134: =+D$114*EXP(E134) -> 0.98289539 | K134: =+E$114*EXP(F134) -> 0.96789456 | L134: =+F$114*EXP(G134) -> 0.94134152 | M134: =+G$114*EXP(H134) -> 0.86561891 | N134: =+SUMPRODUCT(I134:M134,$C$113:$G$113) -> 15512.977 | O134: =+N134-$G$117 -> 10.618691 | P134: =+Lambda^B134 -> 0.054576932 | Q134: =+P134/$P$184 -> 0.0036289904 | R134: =+(O134-$C$123)^2 -> 113.18697 | S134: =+($O134-$C$123)^3 -> 1204.1891 | T134: =+($O134-$C$123)^4 -> 12811.291 | V134: -28.421085 | W134: =+_xlfn.XLOOKUP(V134,$O$129:$O$180,$Q$129:$Q$180) -> 0.019290068 | X134: =+SUM($W$129:W134) -> 0.062514726 | Z134: =+Z135-$Z$141/2.5 -> -39.129726 | AA134: =+AVERAGE(Z133:Z134) -> -43.477473 | AB134: =SUMIFS($W$129:$W$362,$V$129:$V$362,">="&Z133,$V$129:$V$362,"<"&Z134) -> 0.015970966 | AU134: =+NORMDIST($Z134,0,SQRT($C$103),TRUE) -> 0.035930319 | AV134: =+AU134-AU133 -> 0.022026872 | AW134: =+NORMDIST($Z134,0,SQRT($L$103),TRUE) -> 0.06927152 | AX134: =+AW134-AW133 -> 0.034154829
B135: =+B136+1 -> 46 | C135: =+'ZCB rates'!B193 -> 45152 | D135: =+'ZCB rates'!M193 -> -0.0001037445 | E135: =+'ZCB rates'!N193 -> -0.000215482 | F135: =+'ZCB rates'!O193 -> -0.000669054 | G135: =+'ZCB rates'!P193 -> -0.002035212 | H135: =+'ZCB rates'!Q193 -> -0.00626415 | I135: =+C$114*EXP(D135) -> 0.99097814 | J135: =+D$114*EXP(E135) -> 0.982577 | K135: =+E$114*EXP(F135) -> 0.96698106 | L135: =+F$114*EXP(G135) -> 0.93878938 | M135: =+G$114*EXP(H135) -> 0.85937642 | N135: =+SUMPRODUCT(I135:M135,$C$113:$G$113) -> 15465.435 | O135: =+N135-$G$117 -> -36.922814 | P135: =+Lambda^B135 -> 0.058060566 | Q135: =+P135/$P$184 -> 0.0038606281 | R135: =+(O135-$C$123)^2 -> 1361.7995 | S135: =+($O135-$C$123)^3 -> -50253.901 | T135: =+($O135-$C$123)^4 -> 1854498 | V135: -26.139806 | W135: =+_xlfn.XLOOKUP(V135,$O$129:$O$180,$Q$129:$Q$180) -> 0.0067376319 | X135: =+SUM($W$129:W135) -> 0.069252358 | Z135: =+Z136-$Z$141/2.5 -> -30.434231 | AA135: =+AVERAGE(Z134:Z135) -> -34.781978 | AB135: =SUMIFS($W$129:$W$362,$V$129:$V$362,">="&Z134,$V$129:$V$362,"<"&Z135) -> 0.0091210272 | AU135: =+NORMDIST($Z135,0,SQRT($C$103),TRUE) -> 0.080756659 | AV135: =+AU135-AU134 -> 0.04482634 | AW135: =+NORMDIST($Z135,0,SQRT($L$103),TRUE) -> 0.12464526 | AX135: =+AW135-AW134 -> 0.055373739
B136: =+B137+1 -> 45 | C136: =+'ZCB rates'!B194 -> 45159 | D136: =+'ZCB rates'!M194 -> -6.6815e-06 | E136: =+'ZCB rates'!N194 -> 4.1621e-05 | F136: =+'ZCB rates'!O194 -> 0.000323556 | G136: =+'ZCB rates'!P194 -> 0.001113952 | H136: =+'ZCB rates'!Q194 -> 0.00307796 | I136: =+C$114*EXP(D136) -> 0.99107433 | J136: =+D$114*EXP(E136) -> 0.98282966 | K136: =+E$114*EXP(F136) -> 0.96794137 | L136: =+F$114*EXP(G136) -> 0.94175044 | M136: =+G$114*EXP(H136) -> 0.86744242 | N136: =+SUMPRODUCT(I136:M136,$C$113:$G$113) -> 15522.014 | O136: =+N136-$G$117 -> 19.655273 | P136: =+Lambda^B136 -> 0.06176656 | Q136: =+P136/$P$184 -> 0.0041070511 | R136: =+(O136-$C$123)^2 -> 387.12602 | S136: =+($O136-$C$123)^3 -> 7616.9052 | T136: =+($O136-$C$123)^4 -> 149866.56 | V136: -26.031125 | W136: =+_xlfn.XLOOKUP(V136,$O$129:$O$180,$Q$129:$Q$180) -> 0.0049447752 | X136: =+SUM($W$129:W136) -> 0.074197133 | Z136: =+Z137-$Z$141/2.5 -> -21.738737 | AA136: =+AVERAGE(Z135:Z136) -> -26.086484 | AB136: =SUMIFS($W$129:$W$362,$V$129:$V$362,">="&Z135,$V$129:$V$362,"<"&Z136) -> 0.066960757 | AU136: =+NORMDIST($Z136,0,SQRT($C$103),TRUE) -> 0.15865525 | AV136: =+AU136-AU135 -> 0.077898595 | AW136: =+NORMDIST($Z136,0,SQRT($L$103),TRUE) -> 0.20527951 | AX136: =+AW136-AW135 -> 0.080634256
B137: =+B138+1 -> 44 | C137: =+'ZCB rates'!B195 -> 45166 | D137: =+'ZCB rates'!M195 -> -1.8691e-05 | E137: =+'ZCB rates'!N195 -> -7.7828e-05 | F137: =+'ZCB rates'!O195 -> -0.000124864 | G137: =+'ZCB rates'!P195 -> 0.000152324 | H137: =+'ZCB rates'!Q195 -> 0.0020439 | I137: =+C$114*EXP(D137) -> 0.99106243 | J137: =+D$114*EXP(E137) -> 0.98271227 | K137: =+E$114*EXP(F137) -> 0.96750742 | L137: =+F$114*EXP(G137) -> 0.94084527 | M137: =+G$114*EXP(H137) -> 0.8665459 | N137: =+SUMPRODUCT(I137:M137,$C$113:$G$113) -> 15507.502 | O137: =+N137-$G$117 -> 5.144081 | P137: =+Lambda^B137 -> 0.065709106 | Q137: =+P137/$P$184 -> 0.0043692033 | R137: =+(O137-$C$123)^2 -> 26.670267 | S137: =+($O137-$C$123)^3 -> 137.73396 | T137: =+($O137-$C$123)^4 -> 711.30313 | V137: -24.700418 | W137: =+_xlfn.XLOOKUP(V137,$O$129:$O$180,$Q$129:$Q$180) -> 0.014157059 | X137: =+SUM($W$129:W137) -> 0.088354192 | Z137: =+Z138-$Z$141/2.5 -> -13.043242 | AA137: =+AVERAGE(Z136:Z137) -> -17.390989 | AB137: =SUMIFS($W$129:$W$362,$V$129:$V$362,">="&Z136,$V$129:$V$362,"<"&Z137) -> 0.18480757 | AU137: =+NORMDIST($Z137,0,SQRT($C$103),TRUE) -> 0.27425312 | AV137: =+AU137-AU136 -> 0.11559786 | AW137: =+NORMDIST($Z137,0,SQRT($L$103),TRUE) -> 0.31074273 | AX137: =+AW137-AW136 -> 0.10546322
B138: =+B139+1 -> 43 | C138: =+'ZCB rates'!B196 -> 45173 | D138: =+'ZCB rates'!M196 -> -4.05505e-05 | E138: =+'ZCB rates'!N196 -> -0.000100704 | F138: =+'ZCB rates'!O196 -> -0.000216968 | G138: =+'ZCB rates'!P196 -> -0.000546276 | H138: =+'ZCB rates'!Q196 -> -0.00258841 | I138: =+C$114*EXP(D138) -> 0.99104076 | J138: =+D$114*EXP(E138) -> 0.98268979 | K138: =+E$114*EXP(F138) -> 0.96741832 | L138: =+F$114*EXP(G138) -> 0.94018822 | M138: =+G$114*EXP(H138) -> 0.86254107 | N138: =+SUMPRODUCT(I138:M138,$C$113:$G$113) -> 15490.967 | O138: =+N138-$G$117 -> -11.391238 | P138: =+Lambda^B138 -> 0.069903304 | Q138: =+P138/$P$184 -> 0.0046480886 | R138: =+(O138-$C$123)^2 -> 129.29948 | S138: =+($O138-$C$123)^3 -> -1470.2635 | T138: =+($O138-$C$123)^4 -> 16718.356 | V138: -23.093332 | W138: =+_xlfn.XLOOKUP(V138,$O$129:$O$180,$Q$129:$Q$180) -> 0.021831223 | X138: =+SUM($W$129:W138) -> 0.11018541 | Z138: =+Z139-$Z$141/2.5 -> -4.3477473 | AA138: =+AVERAGE(Z137:Z138) -> -8.6954946 | AB138: =SUMIFS($W$129:$W$362,$V$129:$V$362,">="&Z137,$V$129:$V$362,"<"&Z138) -> 0.18409589 | AU138: =+NORMDIST($Z138,0,SQRT($C$103),TRUE) -> 0.42074029 | AV138: =+AU138-AU137 -> 0.14648717 | AW138: =+NORMDIST($Z138,0,SQRT($L$103),TRUE) -> 0.43463648 | AX138: =+AW138-AW137 -> 0.12389375
B139: =+B140+1 -> 42 | C139: =+'ZCB rates'!B197 -> 45180 | D139: =+'ZCB rates'!M197 -> -0.0002023405 | E139: =+'ZCB rates'!N197 -> -0.000370192 | F139: =+'ZCB rates'!O197 -> -0.000766312 | G139: =+'ZCB rates'!P197 -> -0.001584884 | H139: =+'ZCB rates'!Q197 -> -0.00302545 | I139: =+C$114*EXP(D139) -> 0.99088044 | J139: =+D$114*EXP(E139) -> 0.982425 | K139: =+E$114*EXP(F139) -> 0.96688702 | L139: =+F$114*EXP(G139) -> 0.93921224 | M139: =+G$114*EXP(H139) -> 0.86216419 | N139: =+SUMPRODUCT(I139:M139,$C$113:$G$113) -> 15476.327 | O139: =+N139-$G$117 -> -26.031125 | P139: =+Lambda^B139 -> 0.074365217 | Q139: =+P139/$P$184 -> 0.0049447752 | R139: =+(O139-$C$123)^2 -> 676.56584 | S139: =+($O139-$C$123)^3 -> -17598.072 | T139: =+($O139-$C$123)^4 -> 457741.33 | V139: -20.162934 | W139: =+_xlfn.XLOOKUP(V139,$O$129:$O$180,$Q$129:$Q$180) -> 0.045871593 | X139: =+SUM($W$129:W139) -> 0.15605701 | Z139: =+Z140-$Z$141/2.5 -> 4.3477473 | AA139: =+AVERAGE(Z138:Z139) -> 0 | AB139: =SUMIFS($W$129:$W$362,$V$129:$V$362,">="&Z138,$V$129:$V$362,"<"&Z139) -> 0.18062812 | AU139: =+NORMDIST($Z139,0,SQRT($C$103),TRUE) -> 0.57925971 | AV139: =+AU139-AU138 -> 0.15851942 | AW139: =+NORMDIST($Z139,0,SQRT($L$103),TRUE) -> 0.56536352 | AX139: =+AW139-AW138 -> 0.13072704
B140: =+B141+1 -> 41 | C140: =+'ZCB rates'!B198 -> 45187 | D140: =+'ZCB rates'!M198 -> -0.000170099 | E140: =+'ZCB rates'!N198 -> -0.000334365 | F140: =+'ZCB rates'!O198 -> -0.000762048 | G140: =+'ZCB rates'!P198 -> -0.001779572 | H140: =+'ZCB rates'!Q198 -> -0.0046501 | I140: =+C$114*EXP(D140) -> 0.99091238 | J140: =+D$114*EXP(E140) -> 0.9824602 | K140: =+E$114*EXP(F140) -> 0.96689114 | L140: =+F$114*EXP(G140) -> 0.93902941 | M140: =+G$114*EXP(H140) -> 0.86076461 | N140: =+SUMPRODUCT(I140:M140,$C$113:$G$113) -> 15471.231 | O140: =+N140-$G$117 -> -31.126977 | P140: =+Lambda^B140 -> 0.079111933 | Q140: =+P140/$P$184 -> 0.0052603991 | R140: =+(O140-$C$123)^2 -> 967.62873 | S140: =+($O140-$C$123)^3 -> -30099.767 | T140: =+($O140-$C$123)^4 -> 936305.35 | V140: -17.047441 | W140: =+_xlfn.XLOOKUP(V140,$O$129:$O$180,$Q$129:$Q$180) -> 0.033665346 | X140: =+SUM($W$129:W140) -> 0.18972235 | Z140: =+Z141-$Z$141/2.5 -> 13.043242 | AA140: =+AVERAGE(Z139:Z140) -> 8.6954946 | AB140: =SUMIFS($W$129:$W$362,$V$129:$V$362,">="&Z139,$V$129:$V$362,"<"&Z140) -> 0.091464768 | AU140: =+NORMDIST($Z140,0,SQRT($C$103),TRUE) -> 0.72574688 | AV140: =+AU140-AU139 -> 0.14648717 | AW140: =+NORMDIST($Z140,0,SQRT($L$103),TRUE) -> 0.68925727 | AX140: =+AW140-AW139 -> 0.12389375
B141: =+B142+1 -> 40 | C141: =+'ZCB rates'!B199 -> 45194 | D141: =+'ZCB rates'!M199 -> 1.3341e-05 | E141: =+'ZCB rates'!N199 -> 3.3977e-05 | F141: =+'ZCB rates'!O199 -> -1.9416e-05 | G141: =+'ZCB rates'!P199 -> -0.000528936 | H141: =+'ZCB rates'!Q199 -> -0.00405296 | I141: =+C$114*EXP(D141) -> 0.99109417 | J141: =+D$114*EXP(E141) -> 0.98282215 | K141: =+E$114*EXP(F141) -> 0.96760945 | L141: =+F$114*EXP(G141) -> 0.94020452 | M141: =+G$114*EXP(H141) -> 0.86127876 | N141: =+SUMPRODUCT(I141:M141,$C$113:$G$113) -> 15489.028 | O141: =+N141-$G$117 -> -13.330458 | P141: =+Lambda^B141 -> 0.084161631 | Q141: =+P141/$P$184 -> 0.0055961693 | R141: =+(O141-$C$123)^2 -> 177.16176 | S141: =+($O141-$C$123)^3 -> -2358.0607 | T141: =+($O141-$C$123)^4 -> 31386.289 | V141: -16.413122 | W141: =+_xlfn.XLOOKUP(V141,$O$129:$O$180,$Q$129:$Q$180) -> 0.035814198 | X141: =+SUM($W$129:W141) -> 0.22553655 | Z141: =+SQRT(C103) -> 21.738737 | AA141: =+AVERAGE(Z140:Z141) -> 17.390989 | AB141: =SUMIFS($W$129:$W$362,$V$129:$V$362,">="&Z140,$V$129:$V$362,"<"&Z141) -> 0.094731859 | AU141: =+NORMDIST($Z141,0,SQRT($C$103),TRUE) -> 0.84134475 | AV141: =+AU141-AU140 -> 0.11559786 | AW141: =+NORMDIST($Z141,0,SQRT($L$103),TRUE) -> 0.79472049 | AX141: =+AW141-AW140 -> 0.10546322
B142: =+B143+1 -> 39 | C142: =+'ZCB rates'!B200 -> 45201 | D142: =+'ZCB rates'!M200 -> -0.000116852 | E142: =+'ZCB rates'!N200 -> -6.06e-06 | F142: =+'ZCB rates'!O200 -> 0.000304596 | G142: =+'ZCB rates'!P200 -> 0.000243268 | H142: =+'ZCB rates'!Q200 -> -0.00311794 | I142: =+C$114*EXP(D142) -> 0.99096515 | J142: =+D$114*EXP(E142) -> 0.9827828 | K142: =+E$114*EXP(F142) -> 0.96792302 | L142: =+F$114*EXP(G142) -> 0.94093083 | M142: =+G$114*EXP(H142) -> 0.86208445 | N142: =+SUMPRODUCT(I142:M142,$C$113:$G$113) -> 15500.773 | O142: =+N142-$G$117 -> -1.5856664 | P142: =+Lambda^B142 -> 0.08953365 | Q142: =+P142/$P$184 -> 0.0059533716 | R142: =+(O142-$C$123)^2 -> 2.450543 | S142: =+($O142-$C$123)^3 -> -3.8361316 | T142: =+($O142-$C$123)^4 -> 6.0051611 | V142: -14.370537 | W142: =+_xlfn.XLOOKUP(V142,$O$129:$O$180,$Q$129:$Q$180) -> 0.015060701 | X142: =+SUM($W$129:W142) -> 0.24059725 | Z142: =+Z141+$Z$141/2.5 -> 30.434231 | AA142: =+AVERAGE(Z141:Z142) -> 26.086484 | AB142: =SUMIFS($W$129:$W$362,$V$129:$V$362,">="&Z141,$V$129:$V$362,"<"&Z142) -> 0.081978024 | AU142: =+NORMDIST($Z142,0,SQRT($C$103),TRUE) -> 0.91924334 | AV142: =+AU142-AU141 -> 0.077898595 | AW142: =+NORMDIST($Z142,0,SQRT($L$103),TRUE) -> 0.87535474 | AX142: =+AW142-AW141 -> 0.080634256
B143: =+B144+1 -> 38 | C143: =+'ZCB rates'!B201 -> 45208 | D143: =+'ZCB rates'!M201 -> -6.38e-05 | E143: =+'ZCB rates'!N201 -> 9.8379e-05 | F143: =+'ZCB rates'!O201 -> 0.000474938 | G143: =+'ZCB rates'!P201 -> 0.001024112 | H143: =+'ZCB rates'!Q201 -> 0.00439932 | I143: =+C$114*EXP(D143) -> 0.99101772 | J143: =+D$114*EXP(E143) -> 0.98288544 | K143: =+E$114*EXP(F143) -> 0.96808791 | L143: =+F$114*EXP(G143) -> 0.94166584 | M143: =+G$114*EXP(H143) -> 0.86858938 | N143: =+SUMPRODUCT(I143:M143,$C$113:$G$113) -> 15523.045 | O143: =+N143-$G$117 -> 20.687169 | P143: =+Lambda^B143 -> 0.095248564 | Q143: =+P143/$P$184 -> 0.006333374 | R143: =+(O143-$C$123)^2 -> 428.79701 | S143: =+($O143-$C$123)^3 -> 8879.2773 | T143: =+($O143-$C$123)^4 -> 183866.87 | V143: -13.330458 | W143: =+_xlfn.XLOOKUP(V143,$O$129:$O$180,$Q$129:$Q$180) -> 0.0055961693 | X143: =+SUM($W$129:W143) -> 0.24619342 | Z143: =+Z142+$Z$141/2.5 -> 39.129726 | AA143: =+AVERAGE(Z142:Z143) -> 34.781978 | AB143: =SUMIFS($W$129:$W$362,$V$129:$V$362,">="&Z142,$V$129:$V$362,"<"&Z143) -> 0.029553882 | AU143: =+NORMDIST($Z143,0,SQRT($C$103),TRUE) -> 0.96406968 | AV143: =+AU143-AU142 -> 0.04482634 | AW143: =+NORMDIST($Z143,0,SQRT($L$103),TRUE) -> 0.93072848 | AX143: =+AW143-AW142 -> 0.055373739
B144: =+B145+1 -> 37 | C144: =+'ZCB rates'!B202 -> 45215 | D144: =+'ZCB rates'!M202 -> 4.0046e-05 | E144: =+'ZCB rates'!N202 -> -4.6794e-05 | F144: =+'ZCB rates'!O202 -> -0.000442302 | G144: =+'ZCB rates'!P202 -> -0.001458928 | H144: =+'ZCB rates'!Q202 -> -0.00430727 | I144: =+C$114*EXP(D144) -> 0.99112064 | J144: =+D$114*EXP(E144) -> 0.98274277 | K144: =+E$114*EXP(F144) -> 0.96720035 | L144: =+F$114*EXP(G144) -> 0.93933055 | M144: =+G$114*EXP(H144) -> 0.86105976 | N144: =+SUMPRODUCT(I144:M144,$C$113:$G$113) -> 15476.218 | O144: =+N144-$G$117 -> -26.139806 | P144: =+Lambda^B144 -> 0.10132826 | Q144: =+P144/$P$184 -> 0.0067376319 | R144: =+(O144-$C$123)^2 -> 682.23143 | S144: =+($O144-$C$123)^3 -> -17819.585 | T144: =+($O144-$C$123)^4 -> 465439.72 | V144: -13.174263 | W144: =+_xlfn.XLOOKUP(V144,$O$129:$O$180,$Q$129:$Q$180) -> 0.048799567 | X144: =+SUM($W$129:W144) -> 0.29499299 | Z144: =+Z143+$Z$141/2.5 -> 47.82522 | AA144: =+AVERAGE(Z143:Z144) -> 43.477473 | AB144: =SUMIFS($W$129:$W$362,$V$129:$V$362,">="&Z143,$V$129:$V$362,"<"&Z144) -> 0.010639387 | AU144: =+NORMDIST($Z144,0,SQRT($C$103),TRUE) -> 0.98609655 | AV144: =+AU144-AU143 -> 0.022026872 | AW144: =+NORMDIST($Z144,0,SQRT($L$103),TRUE) -> 0.96488331 | AX144: =+AW144-AW143 -> 0.034154829
B145: =+B146+1 -> 36 | C145: =+'ZCB rates'!B203 -> 45222 | D145: =+'ZCB rates'!M203 -> -8.85485e-05 | E145: =+'ZCB rates'!N203 -> 7.3673e-05 | F145: =+'ZCB rates'!O203 -> 0.000631296 | G145: =+'ZCB rates'!P203 -> 0.00143662 | H145: =+'ZCB rates'!Q203 -> 0.00157164 | I145: =+C$114*EXP(D145) -> 0.9909932 | J145: =+D$114*EXP(E145) -> 0.98286116 | K145: =+E$114*EXP(F145) -> 0.96823929 | L145: =+F$114*EXP(G145) -> 0.94205437 | M145: =+G$114*EXP(H145) -> 0.86613676 | N145: =+SUMPRODUCT(I145:M145,$C$113:$G$113) -> 15524.027 | O145: =+N145-$G$117 -> 21.668279 | P145: =+Lambda^B145 -> 0.10779602 | Q145: =+P145/$P$184 -> 0.0071676935 | R145: =+(O145-$C$123)^2 -> 470.3921 | S145: =+($O145-$C$123)^3 -> 10202.111 | T145: =+($O145-$C$123)^4 -> 221268.72 | V145: -11.69996 | W145: =+_xlfn.XLOOKUP(V145,$O$129:$O$180,$Q$129:$Q$180) -> 0.020521349 | X145: =+SUM($W$129:W145) -> 0.31551434 | Z145: =+Z144+$Z$141/2.5 -> 56.520715 | AA145: =+AVERAGE(Z144:Z145) -> 52.172968 | AB145: =SUMIFS($W$129:$W$362,$V$129:$V$362,">="&Z144,$V$129:$V$362,"<"&Z145) -> 0.0097665271 | AU145: =+NORMDIST($Z145,0,SQRT($C$103),TRUE) -> 0.99533881 | AV145: =+AU145-AU144 -> 0.0092422595 | AW145: =+NORMDIST($Z145,0,SQRT($L$103),TRUE) -> 0.9838051 | AX145: =+AW145-AW144 -> 0.018921789
B146: =+B147+1 -> 35 | C146: =+'ZCB rates'!B204 -> 45229 | D146: =+'ZCB rates'!M204 -> -9.995e-06 | E146: =+'ZCB rates'!N204 -> 0.0002135885 | F146: =+'ZCB rates'!O204 -> 0.000956395 | G146: =+'ZCB rates'!P204 -> 0.002547301 | H146: =+'ZCB rates'!Q204 -> 0.0065319975 | I146: =+C$114*EXP(D146) -> 0.99107105 | J146: =+D$114*EXP(E146) -> 0.98299869 | K146: =+E$114*EXP(F146) -> 0.96855412 | L146: =+F$114*EXP(G146) -> 0.94310127 | M146: =+G$114*EXP(H146) -> 0.87044378 | N146: =+SUMPRODUCT(I146:M146,$C$113:$G$113) -> 15546.699 | O146: =+N146-$G$117 -> 44.340387 | P146: =+Lambda^B146 -> 0.11467662 | Q146: =+P146/$P$184 -> 0.0076252059 | R146: =+(O146-$C$123)^2 -> 1967.8657 | S146: =+($O146-$C$123)^3 -> 87295.764 | T146: =+($O146-$C$123)^4 -> 3872495.3 | V146: -11.391238 | W146: =+_xlfn.XLOOKUP(V146,$O$129:$O$180,$Q$129:$Q$180) -> 0.0046480886 | X146: =+SUM($W$129:W146) -> 0.32016243 | Z146: =+Z145+$Z$141/2.5 -> 65.21621 | AA146: =+AVERAGE(Z145:Z146) -> 60.868462 | AB146: =SUMIFS($W$129:$W$362,$V$129:$V$362,">="&Z145,$V$129:$V$362,"<"&Z146) -> 0.011758627 | AU146: =+NORMDIST($Z146,0,SQRT($C$103),TRUE) -> 0.9986501 | AV146: =+AU146-AU145 -> 0.00331129 | AW146: =+NORMDIST($Z146,0,SQRT($L$103),TRUE) -> 0.99322034 | AX146: =+AW146-AW145 -> 0.0094152418
B147: =+B148+1 -> 34 | C147: =+'ZCB rates'!B205 -> 45236 | D147: =+'ZCB rates'!M205 -> 2.5464e-05 | E147: =+'ZCB rates'!N205 -> -1.1305e-06 | F147: =+'ZCB rates'!O205 -> -8.7767e-05 | G147: =+'ZCB rates'!P205 -> 8.771e-06 | H147: =+'ZCB rates'!Q205 -> 0.0027716725 | I147: =+C$114*EXP(D147) -> 0.99110619 | J147: =+D$114*EXP(E147) -> 0.98278764 | K147: =+E$114*EXP(F147) -> 0.96754332 | L147: =+F$114*EXP(G147) -> 0.94071022 | M147: =+G$114*EXP(H147) -> 0.86717678 | N147: =+SUMPRODUCT(I147:M147,$C$113:$G$113) -> 15506.826 | O147: =+N147-$G$117 -> 4.4675424 | P147: =+Lambda^B147 -> 0.1219964 | Q147: =+P147/$P$184 -> 0.0081119211 | R147: =+(O147-$C$123)^2 -> 20.140239 | S147: =+($O147-$C$123)^3 -> 90.385121 | T147: =+($O147-$C$123)^4 -> 405.62924 | V147: -10.821853 | W147: =+_xlfn.XLOOKUP(V147,$O$129:$O$180,$Q$129:$Q$180) -> 0.026284184 | X147: =+SUM($W$129:W147) -> 0.34644661 | Z147: =+Z146+$Z$141/2.5 -> 73.911704 | AA147: =+AVERAGE(Z146:Z147) -> 69.563957 | AB147: =SUMIFS($W$129:$W$362,$V$129:$V$362,">="&Z146,$V$129:$V$362,"<"&Z147) -> 0.010389922 | AU147: =+NORMDIST($Z147,0,SQRT($C$103),TRUE) -> 0.99966307 | AV147: =+AU147-AU146 -> 0.0010129688 | AW147: =+NORMDIST($Z147,0,SQRT($L$103),TRUE) -> 0.99742816 | AX147: =+AW147-AW146 -> 0.004207817
B148: =+B149+1 -> 33 | C148: =+'ZCB rates'!B206 -> 45243 | D148: =+'ZCB rates'!M206 -> -5.2641e-05 | E148: =+'ZCB rates'!N206 -> 7.7092e-05 | F148: =+'ZCB rates'!O206 -> 0.0003528 | G148: =+'ZCB rates'!P206 -> 0.000679292 | H148: =+'ZCB rates'!Q206 -> 0.00350692 | I148: =+C$114*EXP(D148) -> 0.99102878 | J148: =+D$114*EXP(E148) -> 0.98286452 | K148: =+E$114*EXP(F148) -> 0.96796968 | L148: =+F$114*EXP(G148) -> 0.94134119 | M148: =+G$114*EXP(H148) -> 0.8678146 | N148: =+SUMPRODUCT(I148:M148,$C$113:$G$113) -> 15517.037 | O148: =+N148-$G$117 -> 14.679148 | P148: =+Lambda^B148 -> 0.12978341 | Q148: =+P148/$P$184 -> 0.0086297033 | R148: =+(O148-$C$123)^2 -> 216.07218 | S148: =+($O148-$C$123)^3 -> 3176.13 | T148: =+($O148-$C$123)^4 -> 46687.185 | V148: -9.8032568 | W148: =+_xlfn.XLOOKUP(V148,$O$129:$O$180,$Q$129:$Q$180) -> 0.031645426 | X148: =+SUM($W$129:W148) -> 0.37809204 | Z148: =+Z147+$Z$141/2.5 -> 82.607199 | AA148: =+AVERAGE(Z147:Z148) -> 78.259451 | AB148: =SUMIFS($W$129:$W$362,$V$129:$V$362,">="&Z147,$V$129:$V$362,"<"&Z148) -> 0 | AU148: =+NORMDIST($Z148,0,SQRT($C$103),TRUE) -> 0.99992765 | AV148: =+AU148-AU147 -> 0.00026458122 | AW148: =+NORMDIST($Z148,0,SQRT($L$103),TRUE) -> 0.99911718 | AX148: =+AW148-AW147 -> 0.00168902
B149: =+B150+1 -> 32 | C149: =+'ZCB rates'!B207 -> 45250 | D149: =+'ZCB rates'!M207 -> 1.23305e-05 | E149: =+'ZCB rates'!N207 -> 5.9285e-05 | F149: =+'ZCB rates'!O207 -> 0.000163408 | G149: =+'ZCB rates'!P207 -> 0.000354256 | H149: =+'ZCB rates'!Q207 -> 0.0019214 | I149: =+C$114*EXP(D149) -> 0.99109317 | J149: =+D$114*EXP(E149) -> 0.98284702 | K149: =+E$114*EXP(F149) -> 0.96778637 | L149: =+F$114*EXP(G149) -> 0.94103527 | M149: =+G$114*EXP(H149) -> 0.86643975 | N149: =+SUMPRODUCT(I149:M149,$C$113:$G$113) -> 15510.151 | O149: =+N149-$G$117 -> 7.7924103 | P149: =+Lambda^B149 -> 0.13806745 | Q149: =+P149/$P$184 -> 0.0091805355 | R149: =+(O149-$C$123)^2 -> 61.037588 | S149: =+($O149-$C$123)^3 -> 476.86566 | T149: =+($O149-$C$123)^4 -> 3725.5872 | V149: -9.0607361 | W149: =+_xlfn.XLOOKUP(V149,$O$129:$O$180,$Q$129:$Q$180) -> 0.0297467 | X149: =+SUM($W$129:W149) -> 0.40783874
B150: =+B151+1 -> 31 | C150: =+'ZCB rates'!B208 -> 45257 | D150: =+'ZCB rates'!M208 -> 2.73855e-05 | E150: =+'ZCB rates'!N208 -> 0.000203885 | F150: =+'ZCB rates'!O208 -> 0.000861532 | G150: =+'ZCB rates'!P208 -> 0.00272762 | H150: =+'ZCB rates'!Q208 -> 0.00742205 | I150: =+C$114*EXP(D150) -> 0.99110809 | J150: =+D$114*EXP(E150) -> 0.98298915 | K150: =+E$114*EXP(F150) -> 0.96846224 | L150: =+F$114*EXP(G150) -> 0.94327134 | M150: =+G$114*EXP(H150) -> 0.87121887 | N150: =+SUMPRODUCT(I150:M150,$C$113:$G$113) -> 15550.426 | O150: =+N150-$G$117 -> 48.067789 | P150: =+Lambda^B150 -> 0.14688027 | Q150: =+P150/$P$184 -> 0.0097665271 | R150: =+(O150-$C$123)^2 -> 2312.459 | S150: =+($O150-$C$123)^3 -> 111201.61 | T150: =+($O150-$C$123)^4 -> 5347466.8 | V150: -5.0591983 | W150: =+_xlfn.XLOOKUP(V150,$O$129:$O$180,$Q$129:$Q$180) -> 0.05522812 | X150: =+SUM($W$129:W150) -> 0.46306686
...

Sheet 30Sep24
B3: Legend
D5: Cashflows to be clumped
D6: Cashflows already at the correct nodes
B9: Date at which cashflows must be computed
B11: VaR comp. date | C11: 45565
B13: Nodes | C13: =+EOMONTH($C$11,'ZCB rates'!C$3) -> 45657 | D13: =+EOMONTH($C$11,'ZCB rates'!D$3) -> 45747 | E13: =+EOMONTH($C$11,'ZCB rates'!E$3) -> 45930 | F13: =+EOMONTH($C$11,'ZCB rates'!F$3) -> 46295 | G13: =+EOMONTH($C$11,'ZCB rates'!G$3) -> 47391
B14: Diff from today | C14: =+C13-$C$11 -> 92 | D14: =+D13-$C$11 -> 182 | E14: =+E13-$C$11 -> 365 | F14: =+F13-$C$11 -> 730 | G14: =+G13-$C$11 -> 1826
B17: Term structure of int rates
C19: =+'ZCB rates'!C3 -> 3 | D19: =+'ZCB rates'!D3 -> 6 | E19: =+'ZCB rates'!E3 -> 12 | F19: =+'ZCB rates'!F3 -> 24 | G19: =+'ZCB rates'!G3 -> 60
B20: =+C11 -> 45565 | C20: ='ZCB rates'!R252 -> 0.032779852 | D20: ='ZCB rates'!S252 -> 0.029806831 | E20: ='ZCB rates'!T252 -> 0.025732802 | F20: ='ZCB rates'!U252 -> 0.022240957 | G20: ='ZCB rates'!V252 -> 0.023772414
B23: Security 7
C26: =+Assumptions!E7 -> 45657 | D26: =+Assumptions!F7 -> 45838 | E26: =+Assumptions!G7 -> 46022 | F26: =+Assumptions!H7 -> 46203 | G26: =+Assumptions!I7 -> 46387
B27: t from today (duration) | C27: =+(C26-$C$11)/365 -> 0.25205479 | D27: =+(D26-$C$11)/365 -> 0.74794521 | E27: =+(E26-$C$11)/365 -> 1.2520548 | F27: =+(F26-$C$11)/365 -> 1.7479452 | G27: =+(G26-$C$11)/365 -> 2.2520548
B28: Interpolated rate | D28: =+_xlfn.LET(_xlpm.t_rem,D27,_xlpm.r_m1,D20,_xlpm.r_m2,E20,_xlpm.mone,D19,_xlpm.mtwo,E19,_xlpm.r_m1+(_xlpm.r_m2-_xlpm.r_m1)/(_xlpm.mtwo/month_in_a_year-_xlpm.mone/month_in_a_year)*(_xlpm.t_rem-_xlpm.mone/month_in_a_year)) -> 0.027786559 | E28: =+_xlfn.LET(_xlpm.t_rem,E27,_xlpm.r_m1,E20,_xlpm.r_m2,F20,_xlpm.mone,E19,_xlpm.mtwo,F19,_xlpm.r_m1+(_xlpm.r_m2-_xlpm.r_m1)/(_xlpm.mtwo/month_in_a_year-_xlpm.mone/month_in_a_year)*(_xlpm.t_rem-_xlpm.mone/month_in_a_year)) -> 0.024852666 | F28: =+_xlfn.LET(_xlpm.t_rem,F27,_xlpm.r_m1,E20,_xlpm.r_m2,F20,_xlpm.mone,E19,_xlpm.mtwo,F19,_xlpm.r_m1+(_xlpm.r_m2-_xlpm.r_m1)/(_xlpm.mtwo/month_in_a_year-_xlpm.mone/month_in_a_year)*(_xlpm.t_rem-_xlpm.mone/month_in_a_year)) -> 0.023121093 | G28: =+_xlfn.LET(_xlpm.t_rem,G27,_xlpm.r_m1,F20,_xlpm.r_m2,G20,_xlpm.mone,F19,_xlpm.mtwo,G19,_xlpm.r_m1+(_xlpm.r_m2-_xlpm.r_m1)/(_xlpm.mtwo/month_in_a_year-_xlpm.mone/month_in_a_year)*(_xlpm.t_rem-_xlpm.mone/month_in_a_year)) -> 0.022369627
B29: Modified Duration | D29: =+D27/(1+D28) -> 0.72772425 | E29: =+E27/(1+E28) -> 1.2216925 | F29: =+F27/(1+F28) -> 1.7084441 | G29: =+G27/(1+G28) -> 2.2027794
B31: Goal nodes | C31: 3m | D31: 6m & 12m | E31: 12m & 24m | F31: 12m & 24m | G31: 24m & 60m
B32: MD 1 | D32: =+(D$19/month_in_a_year)/(1+D$20) -> 0.48552795 | E32: =+(E$19/month_in_a_year)/(1+E$20) -> 0.97491276 | F32: =+(E$19/month_in_a_year)/(1+E$20) -> 0.97491276 | G32: =+(F$19/month_in_a_year)/(1+F$20) -> 1.9564859
B33: MD 2 | D33: =+(E$19/month_in_a_year)/(1+E$20) -> 0.97491276 | E33: =+(F$19/month_in_a_year)/(1+F$20) -> 1.9564859 | F33: =+(F$19/month_in_a_year)/(1+F$20) -> 1.9564859 | G33: =+(G$19/month_in_a_year)/(1+G$20) -> 4.883898
B35: Market value real cashflow | C35: =C40/(1+C20)^C27 -> 198.38063 | D35: =+Assumptions!F8/(1+D28)^D27 -> 195.94187 | E35: =+Assumptions!G8/(1+E28)^E27 -> 193.94621 | F35: =+Assumptions!H8/(1+F28)^F27 -> 192.16668 | G35: =+Assumptions!I8/(1+G28)^G27 -> 9704.2632
B37: Mkt value virtual cashflow | D37: =+_xlfn.LET(_xlpm.MDvirt1,D32,_xlpm.MDvirt2,D33,_xlpm.MDreal,D29,_xlpm.Mvreal,D35,(_xlpm.MDvirt2-_xlpm.MDreal)/(_xlpm.MDvirt2-_xlpm.MDvirt1)*_xlpm.Mvreal) -> 98.970336 | E37: =+_xlfn.LET(_xlpm.MDvirt1,E32,_xlpm.MDvirt2,E33,_xlpm.MDreal,E29,_xlpm.Mvreal,E35,(_xlpm.MDvirt2-_xlpm.MDreal)/(_xlpm.MDvirt2-_xlpm.MDvirt1)*_xlpm.Mvreal) -> 145.18571 | F37: =+_xlfn.LET(_xlpm.MDvirt1,F32,_xlpm.MDvirt2,F33,_xlpm.MDreal,F29,_xlpm.Mvreal,F35,(_xlpm.MDvirt2-_xlpm.MDreal)/(_xlpm.MDvirt2-_xlpm.MDvirt1)*_xlpm.Mvreal) -> 48.560175 | G37: =+_xlfn.LET(_xlpm.MDvirt1,G32,_xlpm.MDvirt2,G33,_xlpm.MDreal,G29,_xlpm.Mvreal,G35,(_xlpm.MDvirt2-_xlpm.MDreal)/(_xlpm.MDvirt2-_xlpm.MDvirt1)*_xlpm.Mvreal) -> 8887.8091
B38: Mkt value Virtual cashflow | D38: =+D35-D37 -> 96.971536 | E38: =+E35-E37 -> 48.760494 | F38: =+F35-F37 -> 143.6065 | G38: =+G35-G37 -> 816.45407
B40: Face value 1 | C40: =Assumptions!E8 -> 200 | D40: =+D37*(1+D20)^(D19/month_in_a_year) -> 100.4345 | E40: =+E37*(1+E20)^(E19/month_in_a_year) -> 148.92175 | F40: =+F37*(1+E20)^(E19/month_in_a_year) -> 49.809765 | G40: =+G37*(1+F20)^(F19/month_in_a_year) -> 9287.5523
B41: Face value 2 | D41: =+D38*(1+E20)^(E19/month_in_a_year) -> 99.466885 | E41: =+E38*(1+F20)^(F19/month_in_a_year) -> 50.953574 | F41: =+F38*(1+F20)^(F19/month_in_a_year) -> 150.06543 | G41: =+G38*(1+G20)^(G19/month_in_a_year) -> 918.2245
B43: Check | C43: =ROUND(+C29-C32*C37/C35-C33*C38/C35,5) -> 0 | D43: =ROUND(+D29-D32*D37/D35-D33*D38/D35,5) -> 0 | E43: =ROUND(+E29-E32*E37/E35-E33*E38/E35,5) -> 0 | F43: =+F29-F32*F37/F35-F33*F38/F35 -> 0 | G43: =+G29-G32*G37/G35-G33*G38/G35 -> 0
B47: Security 10
C50: =+Assumptions!E10 -> 45747 | D50: =+Assumptions!F10 -> 45838 | E50: =+Assumptions!G10 -> 46022 | F50: =+Assumptions!H10 -> 46203
B51: t from today (duration) | C51: =+(C50-$C$11)/365 -> 0.49863014 | D51: =+(D50-$C$11)/365 -> 0.74794521 | E51: =+(E50-$C$11)/365 -> 1.2520548 | F51: =+(F50-$C$11)/365 -> 1.7479452
B52: Interpolated rate | D52: =+_xlfn.LET(_xlpm.t_rem,D51,_xlpm.r_m1,D20,_xlpm.r_m2,E20,_xlpm.mone,D19,_xlpm.mtwo,E19,_xlpm.r_m1+(_xlpm.r_m2-_xlpm.r_m1)/(_xlpm.mtwo/month_in_a_year-_xlpm.mone/month_in_a_year)*(_xlpm.t_rem-_xlpm.mone/month_in_a_year)) -> 0.027786559 | E52: =+_xlfn.LET(_xlpm.t_rem,E51,_xlpm.r_m1,E20,_xlpm.r_m2,F20,_xlpm.mone,E19,_xlpm.mtwo,F19,_xlpm.r_m1+(_xlpm.r_m2-_xlpm.r_m1)/(_xlpm.mtwo/month_in_a_year-_xlpm.mone/month_in_a_year)*(_xlpm.t_rem-_xlpm.mone/month_in_a_year)) -> 0.024852666 | F52: =+_xlfn.LET(_xlpm.t_rem,F51,_xlpm.r_m1,E20,_xlpm.r_m2,F20,_xlpm.mone,E19,_xlpm.mtwo,F19,_xlpm.r_m1+(_xlpm.r_m2-_xlpm.r_m1)/(_xlpm.mtwo/month_in_a_year-_xlpm.mone/month_in_a_year)*(_xlpm.t_rem-_xlpm.mone/month_in_a_year)) -> 0.023121093
B53: Modified Duration | D53: =+D51/(1+D52) -> 0.72772425 | E53: =+E51/(1+E52) -> 1.2216925 | F53: =+F51/(1+F52) -> 1.7084441
B55: Goal nodes | C55: 6m | D55: 6m & 12m | E55: 12m & 24m | F55: 12m & 24m
B56: MD 1 | D56: =+(D$19/12)/(1+D$20) -> 0.48552795 | E56: =+(E$19/12)/(1+E$20) -> 0.97491276 | F56: =+(E$19/12)/(1+E$20) -> 0.97491276
B57: MD 2 | D57: =+(E$19/12)/(1+E$20) -> 0.97491276 | E57: =+(F$19/12)/(1+F$20) -> 1.9564859 | F57: =+(F$19/12)/(1+F$20) -> 1.9564859
B59: Market value real cashflow | C59: =C64/(1+D20)^C51 -> 147.8192 | D59: =+Assumptions!F$11/(1+D52)^D51 -> 146.9564 | E59: =+Assumptions!G$11/(1+E52)^E51 -> 145.45966 | F59: =+Assumptions!H$11/(1+F52)^F51 -> 4948.2919
B61: Mkt value virtual cashflow | D61: =+_xlfn.LET(_xlpm.MDvirt1,D56,_xlpm.MDvirt2,D57,_xlpm.MDreal,D53,_xlpm.Mvreal,D59,(_xlpm.MDvirt2-_xlpm.MDreal)/(_xlpm.MDvirt2-_xlpm.MDvirt1)*_xlpm.Mvreal) -> 74.227752 | E61: =+_xlfn.LET(_xlpm.MDvirt1,E56,_xlpm.MDvirt2,E57,_xlpm.MDreal,E53,_xlpm.Mvreal,E59,(_xlpm.MDvirt2-_xlpm.MDreal)/(_xlpm.MDvirt2-_xlpm.MDvirt1)*_xlpm.Mvreal) -> 108.88929 | F61: =+_xlfn.LET(_xlpm.MDvirt1,F56,_xlpm.MDvirt2,F57,_xlpm.MDreal,F53,_xlpm.Mvreal,F59,(_xlpm.MDvirt2-_xlpm.MDreal)/(_xlpm.MDvirt2-_xlpm.MDvirt1)*_xlpm.Mvreal) -> 1250.4245
B62: Mkt value Virtual cashflow | D62: =+D59-D61 -> 72.728652 | E62: =+E59-E61 -> 36.570371 | F62: =+F59-F61 -> 3697.8674
B64: Face value 1 | C64: =Assumptions!E11 -> 150 | D64: =+D61*(1+D20)^(D19/month_in_a_year) -> 75.325876 | E64: =+E61*(1+E20)^(E19/month_in_a_year) -> 111.69131 | F64: =+F61*(1+E20)^(E19/month_in_a_year) -> 1282.6014
B65: Face value 2 | D65: =+D62*(1+E20)^(E19/month_in_a_year) -> 74.600164 | E65: =+E62*(1+F20)^(F19/month_in_a_year) -> 38.215181 | F65: =+F62*(1+F20)^(F19/month_in_a_year) -> 3864.1848
B67: Check | C67: =ROUND(+C53-C56*C61/C59-C57*C62/C59,5) -> 0 | D67: =ROUND(+D53-D56*D61/D59-D57*D62/D59,5) -> 0 | E67: =ROUND(+E53-E56*E61/E59-E57*E62/E59,5) -> 0 | F67: =ROUND(+F53-F56*F61/F59-F57*F62/F59,5) -> 0
B69: New Portfolio
C71: =+C72-$C$11 -> 92 | D71: =+D72-$C$11 -> 182 | E71: =+E72-$C$11 -> 365 | F71: =+F72-$C$11 -> 730 | G71: =+G72-$C$11 -> 1826
C72: =+C13 -> 45657 | D72: =+D13 -> 45747 | E72: =+E13 -> 45930 | F72: =+F13 -> 46295 | G72: =+G13 -> 47391
B73: Cashflows | C73: =C40 -> 200 | D73: =D40+D64+C64 -> 325.76038 | E73: =D41+SUM(E40:F40)+D65+SUM(E64:F64) -> 1767.0913 | F73: =SUM(E41:F41)+G40+SUM(E65:F65) -> 13390.971 | G73: =G41 -> 918.2245
B74: Disc factor | C74: =+'ZCB rates'!H252 -> 0.99196891 | D74: =+'ZCB rates'!I252 -> 0.98542169 | E74: =+'ZCB rates'!J252 -> 0.97491276 | F74: =+'ZCB rates'!K252 -> 0.95695925 | G74: =+'ZCB rates'!L252 -> 0.88916607
C75: =1/(1+C20)^(C71/365) -> 0.99190317 | D75: =1/(1+D20)^(D71/365) -> 0.98546134 | E75: =1/(1+E20)^(E71/365) -> 0.97491276 | F75: =1/(1+F20)^(F71/365) -> 0.95695925 | G75: =1/(1+G20)^(G71/365) -> 0.88910884
B78: PV of cashflow | C78: =+C73*C74 -> 198.39378 | D78: =+D73*D74 -> 321.01134 | E78: =+E73*E74 -> 1722.7599 | F78: =+F73*F74 -> 12814.614 | G78: =+G73*G74 -> 816.45407
B80: Sum of PV | G80: =+SUM(C78:G78) -> 15873.233 | I80: Check | J80: =ROUND(SUM(C59:F59)+SUM(C35:G35)-G80,1) -> 0
B82: Var computation - parametric approach
C84: =+C72 -> 45657 | D84: =+D72 -> 45747 | E84: =+E72 -> 45930 | F84: =+F72 -> 46295 | G84: =+G72 -> 47391
B85: δ' | C85: =C78 -> 198.39378 | D85: =D78 -> 321.01134 | E85: =E78 -> 1722.7599 | F85: =F78 -> 12814.614 | G85: =G78 -> 816.45407
B87: δ | C87: {=+TRANSPOSE(C85:G85)} -> 198.39378
C88: 321.01134
C89: 1722.7599
C90: 12814.614
C91: 816.45407
C94: EWMA | L94: Simple moving average
B96: Σ | C96: {=+EWMACovMatrix('ZCB rates'!M201:Q252,Lambda)} -> 6.34756e-09 | D96: 1.2781828e-08 | E96: 2.5729998e-08 | F96: 4.9250802e-08 | G96: 9.9129294e-08 | L96: {=CovarianceMatrix('ZCB rates'!M201:Q252)} -> 5.4560068e-09 | M96: 9.3616661e-09 | N96: 1.61689e-08 | O96: 3.1459139e-08 | P96: 7.8770957e-08
C97: 1.2781828e-08 | D97: 3.4256711e-08 | E97: 9.0985566e-08 | F97: 2.0964603e-07 | G97: 4.0468122e-07 | L97: 9.3616661e-09 | M97: 2.8080968e-08 | N97: 8.1973731e-08 | O97: 2.0973969e-07 | P97: 5.0448286e-07
C98: 2.5729998e-08 | D98: 9.0985566e-08 | E98: 2.8667812e-07 | F98: 7.2414542e-07 | G98: 1.4142042e-06 | L98: 1.61689e-08 | M98: 8.1973731e-08 | N98: 2.9726891e-07 | O98: 8.2430209e-07 | P98: 1.9860444e-06
C99: 4.9250802e-08 | D99: 2.0964603e-07 | E99: 7.2414542e-07 | F99: 1.9472104e-06 | G99: 4.0950255e-06 | L99: 3.1459139e-08 | M99: 2.0973969e-07 | N99: 8.2430209e-07 | O99: 2.3888604e-06 | P99: 5.9920509e-06
C100: 9.9129294e-08 | D100: 4.0468122e-07 | E100: 1.4142042e-06 | F100: 4.0950255e-06 | G100: 1.1181742e-05 | L100: 7.8770957e-08 | M100: 5.0448286e-07 | N100: 1.9860444e-06 | O100: 5.9920509e-06 | P100: 1.7436595e-05
B103: σ2ΔV | C103: {=+MMULT(TRANSPOSE(_xlfn.ANCHORARRAY(C87)),MMULT(_xlfn.ANCHORARRAY(C96),_xlfn.ANCHORARRAY(C87)))} -> 452.04779 | K103: σ2ΔV | L103: {=+MMULT(TRANSPOSE(_xlfn.ANCHORARRAY(C87)),MMULT(_xlfn.ANCHORARRAY(L96),_xlfn.ANCHORARRAY(C87)))} -> 574.43864
B105: CI | C105: 0.95 | D105: 0.99 | K105: CI | L105: 0.95 | M105: 0.99
B106: Var | C106: =+SQRT($C$103)*(-1)*_xlfn.NORM.S.INV(1-C105) -> 34.971916 | D106: =+SQRT($C$103)*(-1)*_xlfn.NORM.S.INV(1-D105) -> 49.461449 | K106: Var | L106: =+SQRT($L$103)*(-1)*_xlfn.NORM.S.INV(1-L105) -> 39.422946 | M106: =+SQRT($L$103)*(-1)*_xlfn.NORM.S.INV(1-M105) -> 55.756626
B110: Var computation - hybrid approach
C112: =+C72 -> 45657 | D112: =+D72 -> 45747 | E112: =+E72 -> 45930 | F112: =+F72 -> 46295 | G112: =+G72 -> 47391
B113: =+B73 -> Cashflows | C113: =+C73 -> 200 | D113: =+D73 -> 325.76038 | E113: =+E73 -> 1767.0913 | F113: =+F73 -> 13390.971 | G113: =+G73 -> 918.2245
B114: Discount factor | C114: =+C74 -> 0.99196891 | D114: =+D74 -> 0.98542169 | E114: =+E74 -> 0.97491276 | F114: =+F74 -> 0.95695925 | G114: =+G74 -> 0.88916607
B116: PV of Cashflows | C116: =+C114*C113 -> 198.39378 | D116: =+D114*D113 -> 321.01134 | E116: =+E114*E113 -> 1722.7599 | F116: =+F114*F113 -> 12814.614 | G116: =+G114*G113 -> 816.45407
G117: =+SUM(C116:G116) -> 15873.233
B119: CI | C119: 0.95 | D119: 0.99 | N119: Check | Q119: =+SUM(Q129:Q389)-1 -> 0 | W119: =+SUM(W129:W389)-1 -> 0
B120: Plain vanilla VaR | C120: {=-(INDEX(_xlfn.ANCHORARRAY(V129),MATCH(TRUE,X129:X349>=1-C119,0))-$C$123)} -> 29.42962 | D120: {=-(INDEX(_xlfn.ANCHORARRAY(V129),MATCH(TRUE,X129:X349>=1-D119,0))-$C$123)} -> 48.799783
B121: Interpolated Var | C121: =+_xlfn.LET(_xlpm.x_1,V134,_xlpm.x_2,V135,_xlpm.alfa_1,X134,_xlpm.alfa_2,X135,_xlpm.p,(1-C119),_xlpm.mu,C123,(-1)*(_xlpm.x_1*(_xlpm.alfa_2-_xlpm.p)/(_xlpm.alfa_2-_xlpm.alfa_1)+_xlpm.x_2*(_xlpm.p-_xlpm.alfa_1)/(_xlpm.alfa_2-_xlpm.alfa_1)-_xlpm.mu)) -> 30.921568 | D121: =+_xlfn.LET(_xlpm.x_1,V129,_xlpm.x_2,V130,_xlpm.alfa_1,X129,_xlpm.alfa_2,X130,_xlpm.p,(1-D119),_xlpm.mu,C123,(-1)*(_xlpm.x_1*(_xlpm.alfa_2-_xlpm.p)/(_xlpm.alfa_2-_xlpm.alfa_1)+_xlpm.x_2*(_xlpm.p-_xlpm.alfa_1)/(_xlpm.alfa_2-_xlpm.alfa_1)-_xlpm.mu)) -> 54.831299
B123: Mean | C123: =+SUMPRODUCT(O129:O180,Q129:Q180) -> 11.599316
B124: Variance | C124: =+SUMPRODUCT(Q129:Q180,R129:R180) -> 435.18868
B125: Skewness | C125: =+(SUMPRODUCT(Q129:Q180,S129:S180)/(C124^(3/2))-3) -> -2.8329518
B126: Excess Kurtosis | C126: =+(SUMPRODUCT(Q129:Q180,T129:T180)/(C124^2))-3 -> -0.43616852 | AU126: Parametric
Z127: Hybrid | AU127: EWMA | AW127: SMA
B128: Ordering factor | C128: =+SUMPRODUCT(Q129:Q323,R129:R323) -> 435.18868 | D128: r 3m | E128: r 6m | F128: r 12m | G128: r 24m | H128: r 60m | I128: PZCB3M | J128: PZCB6M | K128: PZCB12M | L128: PZCB24M | M128: PZCB60M | N128: V | O128: ΔV | P128: λi | Q128: frequency | R128: (ΔV-μ)2 | S128: (ΔV-μ)3 | T128: (ΔV-μ)4 | V128: Sorted ΔV | W128: Frequency | X128: Cum Frequency | Z128: Bands | AA128: Band average | AB128: Frequency | AE128: Changes in the portfolio's value: frequency distribution | AU128: Cum. Freq. | AV128: PseudoN | AW128: Cum. Freq. | AX128: PseudoN
B129: =+B130+1 -> 51 | C129: =+'ZCB rates'!B201 -> 45208 | D129: =+'ZCB rates'!M201 -> -6.38e-05 | E129: =+'ZCB rates'!N201 -> 9.8379e-05 | F129: =+'ZCB rates'!O201 -> 0.000474938 | G129: =+'ZCB rates'!P201 -> 0.001024112 | H129: =+'ZCB rates'!Q201 -> 0.00439932 | I129: =+C$114*EXP(D129) -> 0.99190562 | J129: =+D$114*EXP(E129) -> 0.98551864 | K129: =+E$114*EXP(F129) -> 0.9753759 | L129: =+F$114*EXP(G129) -> 0.95793979 | M129: =+G$114*EXP(H129) -> 0.89308642 | N129: =+SUMPRODUCT(I129:M129,$C$113:$G$113) -> 15890.8 | O129: =+N129-$G$117 -> 17.567401 | P129: =+Lambda^B129 -> 0.042610883 | Q129: =+P129/$P$378 -> 0.0026633306 | R129: =+($O129-$C$123)^2 -> 35.618044 | S129: =+($O129-$C$123)^3 -> 212.57153 | T129: =+($O129-$C$123)^4 -> 1268.6451 | V129: {=+_xlfn._xlws.SORT(O129:O180)} -> -47.678409 | W129: =+_xlfn.XLOOKUP(V129,$O$129:$O$180,$Q$129:$Q$180) -> 0.0076252059 | X129: =+SUM($W$129:W129) -> 0.0076252059 | Z129: =+Z130-$Z$141/2.5 -> -80.793379 | AU129: =+NORMDIST($Z129,0,SQRT($C$103),TRUE) -> 7.2348044e-05 | AW129: =+NORMDIST($Z129,0,SQRT($L$103),TRUE) -> 0.00037452999
B130: =+B131+1 -> 50 | C130: =+'ZCB rates'!B202 -> 45215 | D130: =+'ZCB rates'!M202 -> 4.0046e-05 | E130: =+'ZCB rates'!N202 -> -4.6794e-05 | F130: =+'ZCB rates'!O202 -> -0.000442302 | G130: =+'ZCB rates'!P202 -> -0.001458928 | H130: =+'ZCB rates'!Q202 -> -0.00430727 | I130: =+C$114*EXP(D130) -> 0.99200864 | J130: =+D$114*EXP(E130) -> 0.98537558 | K130: =+E$114*EXP(F130) -> 0.97448165 | L130: =+F$114*EXP(G130) -> 0.95556413 | M130: =+G$114*EXP(H130) -> 0.88534443 | N130: =+SUMPRODUCT(I130:M130,$C$113:$G$113) -> 15850.273 | O130: =+N130-$G$117 -> -22.959981 | P130: =+Lambda^B130 -> 0.045330727 | Q130: =+P130/$P$378 -> 0.0028333305 | R130: =+($O130-$C$123)^2 -> 1194.345 | S130: =+($O130-$C$123)^3 -> -41275.722 | T130: =+($O130-$C$123)^4 -> 1426459.9 | V130: -37.200468 | W130: =+_xlfn.XLOOKUP(V130,$O$129:$O$180,$Q$129:$Q$180) -> 0.0055961693 | X130: =+SUM($W$129:W130) -> 0.013221375 | Z130: =+Z131-$Z$141/2.5 -> -72.288813 | AA130: =+AVERAGE(Z129:Z130) -> -76.541096 | AB130: =SUMIFS($W$129:$W$376,$V$129:$V$376,">="&Z129,$V$129:$V$376,"<"&Z130) -> 0 | AU130: =+NORMDIST($Z130,0,SQRT($C$103),TRUE) -> 0.00033692927 | AV130: =+AU130-AU129 -> 0.00026458122 | AW130: =+NORMDIST($Z130,0,SQRT($L$103),TRUE) -> 0.0012801404 | AX130: =+AW130-AW129 -> 0.00090561046
B131: =+B132+1 -> 49 | C131: =+'ZCB rates'!B203 -> 45222 | D131: =+'ZCB rates'!M203 -> -8.85485e-05 | E131: =+'ZCB rates'!N203 -> 7.3673e-05 | F131: =+'ZCB rates'!O203 -> 0.000631296 | G131: =+'ZCB rates'!P203 -> 0.00143662 | H131: =+'ZCB rates'!Q203 -> 0.00157164 | I131: =+C$114*EXP(D131) -> 0.99188108 | J131: =+D$114*EXP(E131) -> 0.98549429 | K131: =+E$114*EXP(F131) -> 0.97552842 | L131: =+F$114*EXP(G131) -> 0.95833503 | M131: =+G$114*EXP(H131) -> 0.89056462 | N131: =+SUMPRODUCT(I131:M131,$C$113:$G$113) -> 15894.034 | O131: =+N131-$G$117 -> 20.80114 | P131: =+Lambda^B131 -> 0.048224177 | Q131: =+P131/$P$378 -> 0.0030141813 | R131: =+($O131-$C$123)^2 -> 84.673581 | S131: =+($O131-$C$123)^3 -> 779.15146 | T131: =+($O131-$C$123)^4 -> 7169.6153 | V131: -25.975963 | W131: =+_xlfn.XLOOKUP(V131,$O$129:$O$180,$Q$129:$Q$180) -> 0.0081119211 | X131: =+SUM($W$129:W131) -> 0.021333296 | Z131: =+Z132-$Z$141/2.5 -> -63.784247 | AA131: =+AVERAGE(Z130:Z131) -> -68.03653 | AB131: =SUMIFS($W$129:$W$376,$V$129:$V$376,">="&Z130,$V$129:$V$376,"<"&Z131) -> 0 | AU131: =+NORMDIST($Z131,0,SQRT($C$103),TRUE) -> 0.001349898 | AV131: =+AU131-AU130 -> 0.0010129688 | AW131: =+NORMDIST($Z131,0,SQRT($L$103),TRUE) -> 0.0038921363 | AX131: =+AW131-AW130 -> 0.0026119958
B132: =+B133+1 -> 48 | C132: =+'ZCB rates'!B204 -> 45229 | D132: =+'ZCB rates'!M204 -> -9.995e-06 | E132: =+'ZCB rates'!N204 -> 0.0002135885 | F132: =+'ZCB rates'!O204 -> 0.000956395 | G132: =+'ZCB rates'!P204 -> 0.002547301 | H132: =+'ZCB rates'!Q204 -> 0.0065319975 | I132: =+C$114*EXP(D132) -> 0.991959 | J132: =+D$114*EXP(E132) -> 0.98563218 | K132: =+E$114*EXP(F132) -> 0.97584561 | L132: =+F$114*EXP(G132) -> 0.95940002 | M132: =+G$114*EXP(H132) -> 0.89499312 | N132: =+SUMPRODUCT(I132:M132,$C$113:$G$113) -> 15912.983 | O132: =+N132-$G$117 -> 39.749837 | P132: =+Lambda^B132 -> 0.051302316 | Q132: =+P132/$P$378 -> 0.0032065759 | R132: =+($O132-$C$123)^2 -> 792.45186 | S132: =+($O132-$C$123)^3 -> 22307.933 | T132: =+($O132-$C$123)^4 -> 627979.95 | V132: -22.959981 | W132: =+_xlfn.XLOOKUP(V132,$O$129:$O$180,$Q$129:$Q$180) -> 0.0028333305 | X132: =+SUM($W$129:W132) -> 0.024166627 | Z132: =+Z133-$Z$141/2.5 -> -55.27968 | AA132: =+AVERAGE(Z131:Z132) -> -59.531963 | AB132: =SUMIFS($W$129:$W$376,$V$129:$V$376,">="&Z131,$V$129:$V$376,"<"&Z132) -> 0 | AU132: =+NORMDIST($Z132,0,SQRT($C$103),TRUE) -> 0.004661188 | AV132: =+AU132-AU131 -> 0.00331129 | AW132: =+NORMDIST($Z132,0,SQRT($L$103),TRUE) -> 0.010542802 | AX132: =+AW132-AW131 -> 0.0066506653
B133: =+B134+1 -> 47 | C133: =+'ZCB rates'!B205 -> 45236 | D133: =+'ZCB rates'!M205 -> 2.5464e-05 | E133: =+'ZCB rates'!N205 -> -1.1305e-06 | F133: =+'ZCB rates'!O205 -> -8.7767e-05 | G133: =+'ZCB rates'!P205 -> 8.771e-06 | H133: =+'ZCB rates'!Q205 -> 0.0027716725 | I133: =+C$114*EXP(D133) -> 0.99199417 | J133: =+D$114*EXP(E133) -> 0.98542057 | K133: =+E$114*EXP(F133) -> 0.9748272 | L133: =+F$114*EXP(G133) -> 0.95696764 | M133: =+G$114*EXP(H133) -> 0.89163397 | N133: =+SUMPRODUCT(I133:M133,$C$113:$G$113) -> 15875.465 | O133: =+N133-$G$117 -> 2.231974 | P133: =+Lambda^B133 -> 0.054576932 | Q133: =+P133/$P$378 -> 0.003411251 | R133: =+($O133-$C$123)^2 -> 87.747088 | S133: =+($O133-$C$123)^3 -> -821.95694 | T133: =+($O133-$C$123)^4 -> 7699.5514 | V133: -22.753387 | W133: =+_xlfn.XLOOKUP(V133,$O$129:$O$180,$Q$129:$Q$180) -> 0.0059533716 | X133: =+SUM($W$129:W133) -> 0.030119998 | Z133: =+Z134-$Z$141/2.5 -> -46.775114 | AA133: =+AVERAGE(Z132:Z133) -> -51.027397 | AB133: =SUMIFS($W$129:$W$376,$V$129:$V$376,">="&Z132,$V$129:$V$376,"<"&Z133) -> 0.0076252059 | AU133: =+NORMDIST($Z133,0,SQRT($C$103),TRUE) -> 0.013903448 | AV133: =+AU133-AU132 -> 0.0092422595 | AW133: =+NORMDIST($Z133,0,SQRT($L$103),TRUE) -> 0.025492263 | AX133: =+AW133-AW132 -> 0.014949462
B134: =+B135+1 -> 46 | C134: =+'ZCB rates'!B206 -> 45243 | D134: =+'ZCB rates'!M206 -> -5.2641e-05 | E134: =+'ZCB rates'!N206 -> 7.7092e-05 | F134: =+'ZCB rates'!O206 -> 0.0003528 | G134: =+'ZCB rates'!P206 -> 0.000679292 | H134: =+'ZCB rates'!Q206 -> 0.00350692 | I134: =+C$114*EXP(D134) -> 0.99191669 | J134: =+D$114*EXP(E134) -> 0.98549766 | K134: =+E$114*EXP(F134) -> 0.97525677 | L134: =+F$114*EXP(G134) -> 0.95760953 | M134: =+G$114*EXP(H134) -> 0.89228978 | N134: =+SUMPRODUCT(I134:M134,$C$113:$G$113) -> 15885.431 | O134: =+N134-$G$117 -> 12.198289 | P134: =+Lambda^B134 -> 0.058060566 | Q134: =+P134/$P$378 -> 0.0036289904 | R134: =+($O134-$C$123)^2 -> 0.35876971 | S134: =+($O134-$C$123)^3 -> 0.21489369 | T134: =+($O134-$C$123)^4 -> 0.1287157 | V134: -21.180452 | W134: =+_xlfn.XLOOKUP(V134,$O$129:$O$180,$Q$129:$Q$180) -> 0.0091805355 | X134: =+SUM($W$129:W134) -> 0.039300534 | Z134: =+Z135-$Z$141/2.5 -> -38.270548 | AA134: =+AVERAGE(Z133:Z134) -> -42.522831 | AB134: =SUMIFS($W$129:$W$376,$V$129:$V$376,">="&Z133,$V$129:$V$376,"<"&Z134) -> 0 | AU134: =+NORMDIST($Z134,0,SQRT($C$103),TRUE) -> 0.035930319 | AV134: =+AU134-AU133 -> 0.022026872 | AW134: =+NORMDIST($Z134,0,SQRT($L$103),TRUE) -> 0.055158291 | AX134: =+AW134-AW133 -> 0.029666028
B135: =+B136+1 -> 45 | C135: =+'ZCB rates'!B207 -> 45250 | D135: =+'ZCB rates'!M207 -> 1.23305e-05 | E135: =+'ZCB rates'!N207 -> 5.9285e-05 | F135: =+'ZCB rates'!O207 -> 0.000163408 | G135: =+'ZCB rates'!P207 -> 0.000354256 | H135: =+'ZCB rates'!Q207 -> 0.0019214 | I135: =+C$114*EXP(D135) -> 0.99198114 | J135: =+D$114*EXP(E135) -> 0.98548011 | K135: =+E$114*EXP(F135) -> 0.97507208 | L135: =+F$114*EXP(G135) -> 0.95729832 | M135: =+G$114*EXP(H135) -> 0.89087616 | N135: =+SUMPRODUCT(I135:M135,$C$113:$G$113) -> 15879.647 | O135: =+N135-$G$117 -> 6.4137147 | P135: =+Lambda^B135 -> 0.06176656 | Q135: =+P135/$P$378 -> 0.0038606281 | R135: =+($O135-$C$123)^2 -> 26.890455 | S135: =+($O135-$C$123)^3 -> -139.44317 | T135: =+($O135-$C$123)^4 -> 723.09659 | V135: -17.830304 | W135: =+_xlfn.XLOOKUP(V135,$O$129:$O$180,$Q$129:$Q$180) -> 0.019290068 | X135: =+SUM($W$129:W135) -> 0.058590602 | Z135: =+Z136-$Z$141/2.5 -> -29.765982 | AA135: =+AVERAGE(Z134:Z135) -> -34.018265 | AB135: =SUMIFS($W$129:$W$376,$V$129:$V$376,">="&Z134,$V$129:$V$376,"<"&Z135) -> 0.0055961693 | AU135: =+NORMDIST($Z135,0,SQRT($C$103),TRUE) -> 0.080756659 | AV135: =+AU135-AU134 -> 0.04482634 | AW135: =+NORMDIST($Z135,0,SQRT($L$103),TRUE) -> 0.10713053 | AX135: =+AW135-AW134 -> 0.051972234
B136: =+B137+1 -> 44 | C136: =+'ZCB rates'!B208 -> 45257 | D136: =+'ZCB rates'!M208 -> 2.73855e-05 | E136: =+'ZCB rates'!N208 -> 0.000203885 | F136: =+'ZCB rates'!O208 -> 0.000861532 | G136: =+'ZCB rates'!P208 -> 0.00272762 | H136: =+'ZCB rates'!Q208 -> 0.00742205 | I136: =+C$114*EXP(D136) -> 0.99199608 | J136: =+D$114*EXP(E136) -> 0.98562262 | K136: =+E$114*EXP(F136) -> 0.97575304 | L136: =+F$114*EXP(G136) -> 0.95957304 | M136: =+G$114*EXP(H136) -> 0.89579006 | N136: =+SUMPRODUCT(I136:M136,$C$113:$G$113) -> 15915.872 | O136: =+N136-$G$117 -> 42.639158 | P136: =+Lambda^B136 -> 0.065709106 | Q136: =+P136/$P$378 -> 0.0041070511 | R136: =+($O136-$C$123)^2 -> 963.47185 | S136: =+($O136-$C$123)^3 -> 29906.015 | T136: =+($O136-$C$123)^4 -> 928278 | V136: -14.327434 | W136: =+_xlfn.XLOOKUP(V136,$O$129:$O$180,$Q$129:$Q$180) -> 0.027961898 | X136: =+SUM($W$129:W136) -> 0.0865525 | Z136: =+Z137-$Z$141/2.5 -> -21.261416 | AA136: =+AVERAGE(Z135:Z136) -> -25.513699 | AB136: =SUMIFS($W$129:$W$376,$V$129:$V$376,">="&Z135,$V$129:$V$376,"<"&Z136) -> 0.016898623 | AU136: =+NORMDIST($Z136,0,SQRT($C$103),TRUE) -> 0.15865525 | AV136: =+AU136-AU135 -> 0.077898595 | AW136: =+NORMDIST($Z136,0,SQRT($L$103),TRUE) -> 0.18751376 | AX136: =+AW136-AW135 -> 0.080383231
B137: =+B138+1 -> 43 | C137: =+'ZCB rates'!B209 -> 45264 | D137: =+'ZCB rates'!M209 -> 0.000159132 | E137: =+'ZCB rates'!N209 -> 0.000468107 | F137: =+'ZCB rates'!O209 -> 0.001407008 | G137: =+'ZCB rates'!P209 -> 0.003953296 | H137: =+'ZCB rates'!Q209 -> 0.0117841 | I137: =+C$114*EXP(D137) -> 0.99212678 | J137: =+D$114*EXP(E137) -> 0.98588308 | K137: =+E$114*EXP(F137) -> 0.97628544 | L137: =+F$114*EXP(G137) -> 0.96074988 | M137: =+G$114*EXP(H137) -> 0.89970608 | N137: =+SUMPRODUCT(I137:M137,$C$113:$G$113) -> 15936.279 | O137: =+N137-$G$117 -> 63.045838 | P137: =+Lambda^B137 -> 0.069903304 | Q137: =+P137/$P$378 -> 0.0043692033 | R137: =+($O137-$C$123)^2 -> 2646.7447 | S137: =+($O137-$C$123)^3 -> 136165.81 | T137: =+($O137-$C$123)^4 -> 7005257.4 | V137: -14.172126 | W137: =+_xlfn.XLOOKUP(V137,$O$129:$O$180,$Q$129:$Q$180) -> 0.015060701 | X137: =+SUM($W$129:W137) -> 0.1016132 | Z137: =+Z138-$Z$141/2.5 -> -12.756849 | AA137: =+AVERAGE(Z136:Z137) -> -17.009132 | AB137: =SUMIFS($W$129:$W$376,$V$129:$V$376,">="&Z136,$V$129:$V$376,"<"&Z137) -> 0.085650262 | AU137: =+NORMDIST($Z137,0,SQRT($C$103),TRUE) -> 0.27425312 | AV137: =+AU137-AU136 -> 0.11559786 | AW137: =+NORMDIST($Z137,0,SQRT($L$103),TRUE) -> 0.29727391 | AX137: =+AW137-AW136 -> 0.10976015
B138: =+B139+1 -> 42 | C138: =+'ZCB rates'!B210 -> 45271 | D138: =+'ZCB rates'!M210 -> -5.3788e-05 | E138: =+'ZCB rates'!N210 -> -6.7276e-05 | F138: =+'ZCB rates'!O210 -> 6.5e-06 | G138: =+'ZCB rates'!P210 -> 0.000451352 | H138: =+'ZCB rates'!Q210 -> 0.00304168 | I138: =+C$114*EXP(D138) -> 0.99191556 | J138: =+D$114*EXP(E138) -> 0.98535539 | K138: =+E$114*EXP(F138) -> 0.9749191 | L138: =+F$114*EXP(G138) -> 0.95739127 | M138: =+G$114*EXP(H138) -> 0.89187475 | N138: =+SUMPRODUCT(I138:M138,$C$113:$G$113) -> 15881.484 | O138: =+N138-$G$117 -> 8.2513112 | P138: =+Lambda^B138 -> 0.074365217 | Q138: =+P138/$P$378 -> 0.0046480886 | R138: =+($O138-$C$123)^2 -> 11.209133 | S138: =+($O138-$C$123)^3 -> -37.528225 | T138: =+($O138-$C$123)^4 -> 125.64466 | V138: -13.782467 | W138: =+_xlfn.XLOOKUP(V138,$O$129:$O$180,$Q$129:$Q$180) -> 0.014157059 | X138: =+SUM($W$129:W138) -> 0.11577026 | Z138: =+Z139-$Z$141/2.5 -> -4.2522831 | AA138: =+AVERAGE(Z137:Z138) -> -8.5045662 | AB138: =SUMIFS($W$129:$W$376,$V$129:$V$376,">="&Z137,$V$129:$V$376,"<"&Z138) -> 0.072354348 | AU138: =+NORMDIST($Z138,0,SQRT($C$103),TRUE) -> 0.42074029 | AV138: =+AU138-AU137 -> 0.14648717 | AW138: =+NORMDIST($Z138,0,SQRT($L$103),TRUE) -> 0.42958961 | AX138: =+AW138-AW137 -> 0.1323157
B139: =+B140+1 -> 41 | C139: =+'ZCB rates'!B211 -> 45278 | D139: =+'ZCB rates'!M211 -> -5.7866e-05 | E139: =+'ZCB rates'!N211 -> 0.00014634 | F139: =+'ZCB rates'!O211 -> 0.001052542 | G139: =+'ZCB rates'!P211 -> 0.003643988 | H139: =+'ZCB rates'!Q211 -> 0.01046422 | I139: =+C$114*EXP(D139) -> 0.99191151 | J139: =+D$114*EXP(E139) -> 0.9855659 | K139: =+E$114*EXP(F139) -> 0.97593944 | L139: =+F$114*EXP(G139) -> 0.96045276 | M139: =+G$114*EXP(H139) -> 0.89851936 | N139: =+SUMPRODUCT(I139:M139,$C$113:$G$113) -> 15930.453 | O139: =+N139-$G$117 -> 57.219627 | P139: =+Lambda^B139 -> 0.079111933 | Q139: =+P139/$P$378 -> 0.0049447752 | R139: =+($O139-$C$123)^2 -> 2081.2128 | S139: =+($O139-$C$123)^3 -> 94945.578 | T139: =+($O139-$C$123)^4 -> 4331446.9 | V139: -11.713132 | W139: =+_xlfn.XLOOKUP(V139,$O$129:$O$180,$Q$129:$Q$180) -> 0.006333374 | X139: =+SUM($W$129:W139) -> 0.12210363 | Z139: =+Z140-$Z$141/2.5 -> 4.2522831 | AA139: =+AVERAGE(Z138:Z139) -> 0 | AB139: =SUMIFS($W$129:$W$376,$V$129:$V$376,">="&Z138,$V$129:$V$376,"<"&Z139) -> 0.24308194 | AU139: =+NORMDIST($Z139,0,SQRT($C$103),TRUE) -> 0.57925971 | AV139: =+AU139-AU138 -> 0.15851942 | AW139: =+NORMDIST($Z139,0,SQRT($L$103),TRUE) -> 0.57041039 | AX139: =+AW139-AW138 -> 0.14082079
B140: =+B141+1 -> 40 | C140: =+'ZCB rates'!B212 -> 45285 | D140: =+'ZCB rates'!M212 -> -7.2848667e-05 | E140: =+'ZCB rates'!N212 -> 5.9396667e-05 | F140: =+'ZCB rates'!O212 -> 0.00065366533 | G140: =+'ZCB rates'!P212 -> 0.00205504 | H140: =+'ZCB rates'!Q212 -> 0.00307507 | I140: =+C$114*EXP(D140) -> 0.99189665 | J140: =+D$114*EXP(E140) -> 0.98548022 | K140: =+E$114*EXP(F140) -> 0.97555024 | L140: =+F$114*EXP(G140) -> 0.95892786 | M140: =+G$114*EXP(H140) -> 0.89190453 | N140: =+SUMPRODUCT(I140:M140,$C$113:$G$113) -> 15903.24 | O140: =+N140-$G$117 -> 30.007231 | P140: =+Lambda^B140 -> 0.084161631 | Q140: =+P140/$P$378 -> 0.0052603991 | R140: =+($O140-$C$123)^2 -> 338.85137 | S140: =+($O140-$C$123)^3 -> 6237.5475 | T140: =+($O140-$C$123)^4 -> 114820.25 | V140: -11.095141 | W140: =+_xlfn.XLOOKUP(V140,$O$129:$O$180,$Q$129:$Q$180) -> 0.0086297033 | X140: =+SUM($W$129:W140) -> 0.13073334 | Z140: =+Z141-$Z$141/2.5 -> 12.756849 | AA140: =+AVERAGE(Z139:Z140) -> 8.5045662 | AB140: =SUMIFS($W$129:$W$376,$V$129:$V$376,">="&Z139,$V$129:$V$376,"<"&Z140) -> 0.13055057 | AU140: =+NORMDIST($Z140,0,SQRT($C$103),TRUE) -> 0.72574688 | AV140: =+AU140-AU139 -> 0.14648717 | AW140: =+NORMDIST($Z140,0,SQRT($L$103),TRUE) -> 0.70272609 | AX140: =+AW140-AW139 -> 0.1323157
B141: =+B142+1 -> 39 | C141: =+'ZCB rates'!B213 -> 45292 | D141: =+'ZCB rates'!M213 -> -5.6108333e-06 | E141: =+'ZCB rates'!N213 -> -0.00013845542 | F141: =+'ZCB rates'!O213 -> -0.00067406083 | G141: =+'ZCB rates'!P213 -> -0.00231395 | H141: =+'ZCB rates'!Q213 -> -0.0078399875 | I141: =+C$114*EXP(D141) -> 0.99196334 | J141: =+D$114*EXP(E141) -> 0.98528526 | K141: =+E$114*EXP(F141) -> 0.97425583 | L141: =+F$114*EXP(G141) -> 0.95474746 | M141: =+G$114*EXP(H141) -> 0.88222228 | N141: =+SUMPRODUCT(I141:M141,$C$113:$G$113) -> 15836.032 | O141: =+N141-$G$117 -> -37.200468 | P141: =+Lambda^B141 -> 0.08953365 | Q141: =+P141/$P$378 -> 0.0055961693 | R141: =+($O141-$C$123)^2 -> 2381.4189 | S141: =+($O141-$C$123)^3 -> -116212.73 | T141: =+($O141-$C$123)^4 -> 5671155.8 | V141: -10.67083 | W141: =+_xlfn.XLOOKUP(V141,$O$129:$O$180,$Q$129:$Q$180) -> 0.020521349 | X141: =+SUM($W$129:W141) -> 0.15125469 | Z141: =+SQRT(C103) -> 21.261416 | AA141: =+AVERAGE(Z140:Z141) -> 17.009132 | AB141: =SUMIFS($W$129:$W$376,$V$129:$V$376,">="&Z140,$V$129:$V$376,"<"&Z141) -> 0.12873924 | AU141: =+NORMDIST($Z141,0,SQRT($C$103),TRUE) -> 0.84134475 | AV141: =+AU141-AU140 -> 0.11559786 | AW141: =+NORMDIST($Z141,0,SQRT($L$103),TRUE) -> 0.81248624 | AX141: =+AW141-AW140 -> 0.10976015
B142: =+B143+1 -> 38 | C142: =+'ZCB rates'!B214 -> 45299 | D142: =+'ZCB rates'!M214 -> -5.2283e-05 | E142: =+'ZCB rates'!N214 -> -0.00018955725 | F142: =+'ZCB rates'!O214 -> -0.0005993705 | G142: =+'ZCB rates'!P214 -> -0.001502658 | H142: =+'ZCB rates'!Q214 -> -0.0029541725 | I142: =+C$114*EXP(D142) -> 0.99191705 | J142: =+D$114*EXP(E142) -> 0.98523491 | K142: =+E$114*EXP(F142) -> 0.9743286 | L142: =+F$114*EXP(G142) -> 0.95552235 | M142: =+G$114*EXP(H142) -> 0.8865432 | N142: =+SUMPRODUCT(I142:M142,$C$113:$G$113) -> 15850.48 | O142: =+N142-$G$117 -> -22.753387 | P142: =+Lambda^B142 -> 0.095248564 | Q142: =+P142/$P$378 -> 0.0059533716 | R142: =+($O142-$C$123)^2 -> 1180.1082 | S142: =+($O142-$C$123)^3 -> -40539.906 | T142: =+($O142-$C$123)^4 -> 1392655.4 | V142: -9.3539587 | W142: =+_xlfn.XLOOKUP(V142,$O$129:$O$180,$Q$129:$Q$180) -> 0.013307635 | X142: =+SUM($W$129:W142) -> 0.16456232 | Z142: =+Z141+$Z$141/2.5 -> 29.765982 | AA142: =+AVERAGE(Z141:Z142) -> 25.513699 | AB142: =SUMIFS($W$129:$W$376,$V$129:$V$376,">="&Z141,$V$129:$V$376,"<"&Z142) -> 0.095865786 | AU142: =+NORMDIST($Z142,0,SQRT($C$103),TRUE) -> 0.91924334 | AV142: =+AU142-AU141 -> 0.077898595 | AW142: =+NORMDIST($Z142,0,SQRT($L$103),TRUE) -> 0.89286947 | AX142: =+AW142-AW141 -> 0.080383231
B143: =+B144+1 -> 37 | C143: =+'ZCB rates'!B215 -> 45306 | D143: =+'ZCB rates'!M215 -> -0.0001351705 | E143: =+'ZCB rates'!N215 -> -0.000201389 | F143: =+'ZCB rates'!O215 -> -0.000272608 | G143: =+'ZCB rates'!P215 -> -0.000635092 | H143: =+'ZCB rates'!Q215 -> -0.00370114 | I143: =+C$114*EXP(D143) -> 0.99183483 | J143: =+D$114*EXP(E143) -> 0.98522325 | K143: =+E$114*EXP(F143) -> 0.97464703 | L143: =+F$114*EXP(G143) -> 0.95635169 | M143: =+G$114*EXP(H143) -> 0.88588123 | N143: =+SUMPRODUCT(I143:M143,$C$113:$G$113) -> 15861.52 | O143: =+N143-$G$117 -> -11.713132 | P143: =+Lambda^B143 -> 0.10132826 | Q143: =+P143/$P$378 -> 0.006333374 | R143: =+($O143-$C$123)^2 -> 543.47019 | S143: =+($O143-$C$123)^3 -> -12669.62 | T143: =+($O143-$C$123)^4 -> 295359.84 | V143: -9.3134971 | W143: =+_xlfn.XLOOKUP(V143,$O$129:$O$180,$Q$129:$Q$180) -> 0.011053109 | X143: =+SUM($W$129:W143) -> 0.17561543 | Z143: =+Z142+$Z$141/2.5 -> 38.270548 | AA143: =+AVERAGE(Z142:Z143) -> 34.018265 | AB143: =SUMIFS($W$129:$W$376,$V$129:$V$376,">="&Z142,$V$129:$V$376,"<"&Z143) -> 0.071181412 | AU143: =+NORMDIST($Z143,0,SQRT($C$103),TRUE) -> 0.96406968 | AV143: =+AU143-AU142 -> 0.04482634 | AW143: =+NORMDIST($Z143,0,SQRT($L$103),TRUE) -> 0.94484171 | AX143: =+AW143-AW142 -> 0.051972234
B144: =+B145+1 -> 36 | C144: =+'ZCB rates'!B216 -> 45313 | D144: =+'ZCB rates'!M216 -> -5.253e-06 | E144: =+'ZCB rates'!N216 -> -2.8039e-05 | F144: =+'ZCB rates'!O216 -> -0.000100826 | G144: =+'ZCB rates'!P216 -> -0.000265792 | H144: =+'ZCB rates'!Q216 -> -0.00065293 | I144: =+C$114*EXP(D144) -> 0.9919637 | J144: =+D$114*EXP(E144) -> 0.98539406 | K144: =+E$114*EXP(F144) -> 0.97481447 | L144: =+F$114*EXP(G144) -> 0.95670493 | M144: =+G$114*EXP(H144) -> 0.8885857 | N144: =+SUMPRODUCT(I144:M144,$C$113:$G$113) -> 15869.111 | O144: =+N144-$G$117 -> -4.1222157 | P144: =+Lambda^B144 -> 0.10779602 | Q144: =+P144/$P$378 -> 0.0067376319 | R144: =+($O144-$C$123)^2 -> 247.16654 | S144: =+($O144-$C$123)^3 -> -3885.8365 | T144: =+($O144-$C$123)^4 -> 61091.3 | V144: -6.9662738 | W144: =+_xlfn.XLOOKUP(V144,$O$129:$O$180,$Q$129:$Q$180) -> 0.012509177 | X144: =+SUM($W$129:W144) -> 0.18812461 | Z144: =+Z143+$Z$141/2.5 -> 46.775114 | AA144: =+AVERAGE(Z143:Z144) -> 42.522831 | AB144: =SUMIFS($W$129:$W$376,$V$129:$V$376,">="&Z143,$V$129:$V$376,"<"&Z144) -> 0.095042258 | AU144: =+NORMDIST($Z144,0,SQRT($C$103),TRUE) -> 0.98609655 | AV144: =+AU144-AU143 -> 0.022026872 | AW144: =+NORMDIST($Z144,0,SQRT($L$103),TRUE) -> 0.97450774 | AX144: =+AW144-AW143 -> 0.029666028
B145: =+B146+1 -> 35 | C145: =+'ZCB rates'!B217 -> 45320 | D145: =+'ZCB rates'!M217 -> 9.25595e-05 | E145: =+'ZCB rates'!N217 -> 0.000247486 | F145: =+'ZCB rates'!O217 -> 0.00070191 | G145: =+'ZCB rates'!P217 -> 0.001939312 | H145: =+'ZCB rates'!Q217 -> 0.00554748 | I145: =+C$114*EXP(D145) -> 0.99206073 | J145: =+D$114*EXP(E145) -> 0.9856656 | K145: =+E$114*EXP(F145) -> 0.9755973 | L145: =+F$114*EXP(G145) -> 0.95881689 | M145: =+G$114*EXP(H145) -> 0.89411241 | N145: =+SUMPRODUCT(I145:M145,$C$113:$G$113) -> 15903.958 | O145: =+N145-$G$117 -> 30.724963 | P145: =+Lambda^B145 -> 0.11467662 | Q145: =+P145/$P$378 -> 0.0071676935 | R145: =+($O145-$C$123)^2 -> 365.79039 | S145: =+($O145-$C$123)^3 -> 6995.978 | T145: =+($O145-$C$123)^4 -> 133802.61 | V145: -4.1222157 | W145: =+_xlfn.XLOOKUP(V145,$O$129:$O$180,$Q$129:$Q$180) -> 0.0067376319 | X145: =+SUM($W$129:W145) -> 0.19486224 | Z145: =+Z144+$Z$141/2.5 -> 55.27968 | AA145: =+AVERAGE(Z144:Z145) -> 51.027397 | AB145: =SUMIFS($W$129:$W$376,$V$129:$V$376,">="&Z144,$V$129:$V$376,"<"&Z145) -> 0.038100211 | AU145: =+NORMDIST($Z145,0,SQRT($C$103),TRUE) -> 0.99533881 | AV145: =+AU145-AU144 -> 0.0092422595 | AW145: =+NORMDIST($Z145,0,SQRT($L$103),TRUE) -> 0.9894572 | AX145: =+AW145-AW144 -> 0.014949462
B146: =+B147+1 -> 34 | C146: =+'ZCB rates'!B218 -> 45327 | D146: =+'ZCB rates'!M218 -> 3.452e-06 | E146: =+'ZCB rates'!N218 -> -0.000207049 | F146: =+'ZCB rates'!O218 -> -0.00101263 | G146: =+'ZCB rates'!P218 -> -0.00311018 | H146: =+'ZCB rates'!Q218 -> -0.00746873 | I146: =+C$114*EXP(D146) -> 0.99197233 | J146: =+D$114*EXP(E146) -> 0.98521768 | K146: =+E$114*EXP(F146) -> 0.97392604 | L146: =+F$114*EXP(G146) -> 0.95398756 | M146: =+G$114*EXP(H146) -> 0.88254987 | N146: =+SUMPRODUCT(I146:M146,$C$113:$G$113) -> 15825.555 | O146: =+N146-$G$117 -> -47.678409 | P146: =+Lambda^B146 -> 0.1219964 | Q146: =+P146/$P$378 -> 0.0076252059 | R146: =+($O146-$C$123)^2 -> 3513.8487 | S146: =+($O146-$C$123)^3 -> -208292.95 | T146: =+($O146-$C$123)^4 -> 12347132 | V146: -3.8261172 | W146: =+_xlfn.XLOOKUP(V146,$O$129:$O$180,$Q$129:$Q$180) -> 0.018132664 | X146: =+SUM($W$129:W146) -> 0.2129949 | Z146: =+Z145+$Z$141/2.5 -> 63.784247 | AA146: =+AVERAGE(Z145:Z146) -> 59.531963 | AB146: =SUMIFS($W$129:$W$376,$V$129:$V$376,">="&Z145,$V$129:$V$376,"<"&Z146) -> 0.0093139785 | AU146: =+NORMDIST($Z146,0,SQRT($C$103),TRUE) -> 0.9986501 | AV146: =+AU146-AU145 -> 0.00331129 | AW146: =+NORMDIST($Z146,0,SQRT($L$103),TRUE) -> 0.99610786 | AX146: =+AW146-AW145 -> 0.0066506653
B147: =+B148+1 -> 33 | C147: =+'ZCB rates'!B219 -> 45334 | D147: =+'ZCB rates'!M219 -> -1.02595e-05 | E147: =+'ZCB rates'!N219 -> -0.000130519 | F147: =+'ZCB rates'!O219 -> -0.000575476 | G147: =+'ZCB rates'!P219 -> -0.001726532 | H147: =+'ZCB rates'!Q219 -> -0.00347857 | I147: =+C$114*EXP(D147) -> 0.99195873 | J147: =+D$114*EXP(E147) -> 0.98529308 | K147: =+E$114*EXP(F147) -> 0.97435189 | L147: =+F$114*EXP(G147) -> 0.95530846 | M147: =+G$114*EXP(H147) -> 0.88607842 | N147: =+SUMPRODUCT(I147:M147,$C$113:$G$113) -> 15847.257 | O147: =+N147-$G$117 -> -25.975963 | P147: =+Lambda^B147 -> 0.12978341 | Q147: =+P147/$P$378 -> 0.0081119211 | R147: =+($O147-$C$123)^2 -> 1411.9016 | S147: =+($O147-$C$123)^3 -> -53052.596 | T147: =+($O147-$C$123)^4 -> 1993466.1 | V147: -3.5659449 | W147: =+_xlfn.XLOOKUP(V147,$O$129:$O$180,$Q$129:$Q$180) -> 0.040532139 | X147: =+SUM($W$129:W147) -> 0.25352704 | Z147: =+Z146+$Z$141/2.5 -> 72.288813 | AA147: =+AVERAGE(Z146:Z147) -> 68.03653 | AB147: =SUMIFS($W$129:$W$376,$V$129:$V$376,">="&Z146,$V$129:$V$376,"<"&Z147) -> 0 | AU147: =+NORMDIST($Z147,0,SQRT($C$103),TRUE) -> 0.99966307 | AV147: =+AU147-AU146 -> 0.0010129688 | AW147: =+NORMDIST($Z147,0,SQRT($L$103),TRUE) -> 0.99871986 | AX147: =+AW147-AW146 -> 0.0026119958
B148: =+B149+1 -> 32 | C148: =+'ZCB rates'!B220 -> 45341 | D148: =+'ZCB rates'!M220 -> 1.6597e-05 | E148: =+'ZCB rates'!N220 -> -3.9282e-05 | F148: =+'ZCB rates'!O220 -> -0.0002652 | G148: =+'ZCB rates'!P220 -> -0.000770884 | H148: =+'ZCB rates'!Q220 -> -0.00092422 | I148: =+C$114*EXP(D148) -> 0.99198537 | J148: =+D$114*EXP(E148) -> 0.98538298 | K148: =+E$114*EXP(F148) -> 0.97465425 | L148: =+F$114*EXP(G148) -> 0.95622183 | M148: =+G$114*EXP(H148) -> 0.88834467 | N148: =+SUMPRODUCT(I148:M148,$C$113:$G$113) -> 15862.138 | O148: =+N148-$G$117 -> -11.095141 | P148: =+Lambda^B148 -> 0.13806745 | Q148: =+P148/$P$378 -> 0.0086297033 | R148: =+($O148-$C$123)^2 -> 515.03836 | S148: =+($O148-$C$123)^3 -> -11688.516 | T148: =+($O148-$C$123)^4 -> 265264.51 | V148: -3.4238806 | W148: =+_xlfn.XLOOKUP(V148,$O$129:$O$180,$Q$129:$Q$180) -> 0.023224705 | X148: =+SUM($W$129:W148) -> 0.27675175 | Z148: =+Z147+$Z$141/2.5 -> 80.793379 | AA148: =+AVERAGE(Z147:Z148) -> 76.541096 | AB148: =SUMIFS($W$129:$W$376,$V$129:$V$376,">="&Z147,$V$129:$V$376,"<"&Z148) -> 0 | AU148: =+NORMDIST($Z148,0,SQRT($C$103),TRUE) -> 0.99992765 | AV148: =+AU148-AU147 -> 0.00026458122 | AW148: =+NORMDIST($Z148,0,SQRT($L$103),TRUE) -> 0.99962547 | AX148: =+AW148-AW147 -> 0.00090561046
B149: =+B150+1 -> 31 | C149: =+'ZCB rates'!B221 -> 45348 | D149: =+'ZCB rates'!M221 -> -1.809e-05 | E149: =+'ZCB rates'!N221 -> -0.000126441 | F149: =+'ZCB rates'!O221 -> -0.000500356 | G149: =+'ZCB rates'!P221 -> -0.001406192 | H149: =+'ZCB rates'!Q221 -> -0.00278094 | I149: =+C$114*EXP(D149) -> 0.99195097 | J149: =+D$114*EXP(E149) -> 0.9852971 | K149: =+E$114*EXP(F149) -> 0.97442508 | L149: =+F$114*EXP(G149) -> 0.95561453 | M149: =+G$114*EXP(H149) -> 0.88669679 | N149: =+SUMPRODUCT(I149:M149,$C$113:$G$113) -> 15852.052 | O149: =+N149-$G$117 -> -21.180452 | P149: =+Lambda^B149 -> 0.14688027 | Q149: =+P149/$P$378 -> 0.0091805355 | R149: =+($O149-$C$123)^2 -> 1074.5132 | S149: =+($O149-$C$123)^3 -> -35222.293 | T149: =+($O149-$C$123)^4 -> 1154578.6 | V149: 0.14924126 | W149: =+_xlfn.XLOOKUP(V149,$O$129:$O$180,$Q$129:$Q$180) -> 0.043119297 | X149: =+SUM($W$129:W149) -> 0.31987105
B150: =+B151+1 -> 30 | C150: =+'ZCB rates'!B222 -> 45355 | D150: =+'ZCB rates'!M222 -> -6.049e-06 | E150: =+'ZCB rates'!N222 -> 7.0021e-05 | F150: =+'ZCB rates'!O222 -> 0.000410218 | G150: =+'ZCB rates'!P222 -> 0.001554184 | H150: =+'ZCB rates'!Q222 -> 0.00602025 | I150: =+C$114*EXP(D150) -> 0.99196291 | J150: =+D$114*EXP(E150) -> 0.98549069 | K150: =+E$114*EXP(F150) -> 0.97531277 | L150: =+F$114*EXP(G150) -> 0.9584477 | M150: =+G$114*EXP(H150) -> 0.89453522 | N150: =+SUMPRODUCT(I150:M150,$C$113:$G$113) -> 15898.823 | O150: =+N150-$G$117 -> 25.589966 | P150: =+Lambda^B150 -> 0.15625561 | Q150: =+P150/$P$378 -> 0.0097665271 | R150: =+($O150-$C$123)^2 -> 195.7383 | S150: =+($O150-$C$123)^3 -> 2738.5061 | T150: =+($O150-$C$123)^4 -> 38313.481 | V150: 1.3603394 | W150: =+_xlfn.XLOOKUP(V150,$O$129:$O$180,$Q$129:$Q$180) -> 0.016022022 | X150: =+SUM($W$129:W150) -> 0.33589307
...

Sheet 31Dec24
B3: Legend
D5: Cashflows to be clumped
D6: Cashflows already at the correct nodes
B9: Date at which cashflows must be computed
B11: VaR comp. date | C11: 45657
B13: Nodes | C13: =+EOMONTH($C$11,'ZCB rates'!C$3) -> 45747 | D13: =+EOMONTH($C$11,'ZCB rates'!D$3) -> 45838 | E13: =+EOMONTH($C$11,'ZCB rates'!E$3) -> 46022 | F13: =+EOMONTH($C$11,'ZCB rates'!F$3) -> 46387 | G13: =+EOMONTH($C$11,'ZCB rates'!G$3) -> 47483
B14: Diff from today | C14: =+C13-$C$11 -> 90 | D14: =+D13-$C$11 -> 181 | E14: =+E13-$C$11 -> 365 | F14: =+F13-$C$11 -> 730 | G14: =+G13-$C$11 -> 1826
B17: Term structure of int rates
C19: =+'ZCB rates'!C3 -> 3 | D19: =+'ZCB rates'!D3 -> 6 | E19: =+'ZCB rates'!E3 -> 12 | F19: =+'ZCB rates'!F3 -> 24 | G19: =+'ZCB rates'!G3 -> 60
B20: =+C11 -> 45657 | C20: ='ZCB rates'!R265 -> 0.027300204 | D20: ='ZCB rates'!S265 -> 0.025143067 | E20: ='ZCB rates'!T265 -> 0.022922954 | F20: ='ZCB rates'!U265 -> 0.0222462 | G20: ='ZCB rates'!V265 -> 0.02569348
B23: Security 7
C26: =+Assumptions!F7 -> 45838 | D26: =+Assumptions!G7 -> 46022 | E26: =+Assumptions!H7 -> 46203 | F26: =+Assumptions!I7 -> 46387
B27: t from today (duration) | C27: =+(C26-$C$11)/365 -> 0.49589041 | D27: =+(D26-$C$11)/365 -> 1 | E27: =+(E26-$C$11)/365 -> 1.4958904 | F27: =+(F26-$C$11)/365 -> 2
B28: Interpolated rate | E28: =+_xlfn.LET(_xlpm.t_rem,E27,_xlpm.r_m1,E20,_xlpm.r_m2,F20,_xlpm.mone,E19,_xlpm.mtwo,F19,_xlpm.r_m1+(_xlpm.r_m2-_xlpm.r_m1)/(_xlpm.mtwo/month_in_a_year-_xlpm.mone/month_in_a_year)*(_xlpm.t_rem-_xlpm.mone/month_in_a_year)) -> 0.022587358
B29: Modified Duration | E29: =+E27/(1+E28) -> 1.4628485
B31: Goal nodes | C31: 6m | D31: 12m | E31: 12m & 24m | F31: 24m
B32: MD 1 | E32: =+(E$19/month_in_a_year)/(1+E$20) -> 0.97759073
B33: MD 2 | E33: =+(F$19/month_in_a_year)/(1+F$20) -> 1.9564758
B35: Market value real cashflow | C35: =Assumptions!F8/(1+D20)^C27 -> 197.55229 | D35: =Assumptions!G8/(1+E20)^D27 -> 195.51815 | E35: =+Assumptions!H8/(1+E28)^E27 -> 193.42795 | F35: =Assumptions!I8/(1+F20)^F27 -> 9760.8842
B37: Mkt value virtual cashflow | E37: =+_xlfn.LET(_xlpm.MDvirt1,E32,_xlpm.MDvirt2,E33,_xlpm.MDreal,E29,_xlpm.Mvreal,E35,(_xlpm.MDvirt2-_xlpm.MDreal)/(_xlpm.MDvirt2-_xlpm.MDvirt1)*_xlpm.Mvreal) -> 97.540886
B38: Mkt value Virtual cashflow | E38: =+E35-E37 -> 95.887065
B40: Face value 1 | C40: =Assumptions!F8 -> 200 | D40: =Assumptions!G8 -> 200 | E40: =+E37*(1+E20)^(E19/month_in_a_year) -> 99.776811 | F40: =Assumptions!I8 -> 10200
B41: Face value 2 | E41: =+E38*(1+F20)^(F19/month_in_a_year) -> 100.20076
B43: Check | E43: =+E29-E32*E37/E35-E33*E38/E35 -> 0
B47: Security 10
C50: =+Assumptions!E10 -> 45747 | D50: =+Assumptions!F10 -> 45838 | E50: =+Assumptions!G10 -> 46022 | F50: =+Assumptions!H10 -> 46203
B51: t from today (duration) | C51: =+(C50-$C$11)/365 -> 0.24657534 | D51: =+(D50-$C$11)/365 -> 0.49589041 | E51: =+(E50-$C$11)/365 -> 1 | F51: =+(F50-$C$11)/365 -> 1.4958904
B52: Interpolated rate | F52: =+_xlfn.LET(_xlpm.t_rem,F51,_xlpm.r_m1,E20,_xlpm.r_m2,F20,_xlpm.mone,E19,_xlpm.mtwo,F19,_xlpm.r_m1+(_xlpm.r_m2-_xlpm.r_m1)/(_xlpm.mtwo/month_in_a_year-_xlpm.mone/month_in_a_year)*(_xlpm.t_rem-_xlpm.mone/month_in_a_year)) -> 0.022587358
B53: Modified Duration | F53: =+F51/(1+F52) -> 1.4628485
B55: Goal nodes | C55: 3m | D55: 6m | E55: 12m | F55: 12m & 24m
B56: MD 1 | F56: =+(E$19/12)/(1+E$20) -> 0.97759073
B57: MD 2 | F57: =+(F$19/12)/(1+F$20) -> 1.9564758
B59: Market value real cashflow | C59: =Assumptions!E11/(1+C20)^C51 -> 149.0071 | D59: =Assumptions!F11/(1+D20)^D51 -> 148.16422 | E59: =Assumptions!G11/(1+E20)^E51 -> 146.63861 | F59: =+Assumptions!H$11/(1+F52)^F51 -> 4980.7697
B61: Mkt value virtual cashflow | F61: =+_xlfn.LET(_xlpm.MDvirt1,F56,_xlpm.MDvirt2,F57,_xlpm.MDreal,F53,_xlpm.Mvreal,F59,(_xlpm.MDvirt2-_xlpm.MDreal)/(_xlpm.MDvirt2-_xlpm.MDvirt1)*_xlpm.Mvreal) -> 2511.6778
B62: Mkt value Virtual cashflow | F62: =+F59-F61 -> 2469.0919
B64: Face value 1 | C64: =Assumptions!E11 -> 150 | D64: =Assumptions!F11 -> 150 | E64: =Assumptions!G11 -> 150 | F64: =+F61*(1+E20)^(E19/month_in_a_year) -> 2569.2529
B65: Face value 2 | F65: =+F62*(1+F20)^(F19/month_in_a_year) -> 2580.1697
B67: Check | F67: =+F53-F56*F61/F59-F57*F62/F59 -> 0
B69: New Portfolio
C71: =+C72-$C$11 -> 90 | D71: =+D72-$C$11 -> 181 | E71: =+E72-$C$11 -> 365 | F71: =+F72-$C$11 -> 730 | G71: =+G72-$C$11 -> 1826
C72: =+C13 -> 45747 | D72: =+D13 -> 45838 | E72: =+E13 -> 46022 | F72: =+F13 -> 46387 | G72: =+G13 -> 47483
B73: Cashflows | C73: =C64 -> 150 | D73: =C40+D64 -> 350 | E73: =E40+D40+E64+F64 -> 3019.0297 | F73: =F40+F65+E41 -> 12880.37 | G73: =F41 -> 0
B74: Disc factor | C74: =+'ZCB rates'!H265 -> 0.99328907 | D74: =+'ZCB rates'!I265 -> 0.98766067 | E74: =+'ZCB rates'!J265 -> 0.97759073 | F74: =+'ZCB rates'!K265 -> 0.95694943 | G74: =+'ZCB rates'!L265 -> 0.88087042
C75: =1/(1+C20)^(C71/365) -> 0.9933807 | D75: =1/(1+D20)^(D71/365) -> 0.98776147 | E75: =1/(1+E20)^(E71/365) -> 0.97759073 | F75: =1/(1+F20)^(F71/365) -> 0.95694943 | G75: =1/(1+G20)^(G71/365) -> 0.8808092
B78: PV of cashflow | C78: =+C73*C74 -> 148.99336 | D78: =+D73*D74 -> 345.68124 | E78: =+E73*E74 -> 2951.3754 | F78: =+F73*F74 -> 12325.863 | G78: =+G73*G74 -> 0
B79: Cash | G79: =Assumptions!E8 -> 200
B80: Sum of PV | G80: =+SUM(C78:G78)+G79 -> 15971.913 | I80: Check | J80: =ROUND(SUM(C59:F59)+SUM(C35:F35)+G79-G80,1) -> 0
B82: Var computation - parametric approach
C84: =+C72 -> 45747 | D84: =+D72 -> 45838 | E84: =+E72 -> 46022 | F84: =+F72 -> 46387 | G84: =+G72 -> 47483
B85: δ' | C85: =C78 -> 148.99336 | D85: =D78 -> 345.68124 | E85: =E78 -> 2951.3754 | F85: =F78 -> 12325.863 | G85: =G78 -> 0
B87: δ | C87: {=+TRANSPOSE(C85:G85)} -> 148.99336
C88: 345.68124
C89: 2951.3754
C90: 12325.863
C91: 0
C94: EWMA | L94: Simple moving average
B96: Σ | C96: {=+EWMACovMatrix('ZCB rates'!M214:Q265,Lambda)} -> 7.9351125e-09 | D96: 1.2468539e-08 | E96: 1.9530884e-08 | F96: 4.1519105e-08 | G96: 1.3095534e-07 | L96: {=CovarianceMatrix('ZCB rates'!M214:Q265)} -> 6.5790948e-09 | M96: 1.2034997e-08 | N96: 2.2454837e-08 | O96: 4.6991908e-08 | P96: 1.2993774e-07
C97: 1.2468539e-08 | D97: 3.084501e-08 | E97: 7.9233746e-08 | F97: 1.9114833e-07 | G97: 4.5067252e-07 | L97: 1.2034997e-08 | M97: 3.1600983e-08 | N97: 8.4027207e-08 | O97: 2.0361857e-07 | P97: 4.689984e-07
C98: 1.9530884e-08 | D98: 7.9233746e-08 | E98: 2.6733517e-07 | F98: 7.1068434e-07 | G98: 1.6136287e-06 | L98: 2.2454837e-08 | M98: 8.4027207e-08 | N98: 2.7408662e-07 | O98: 7.226981e-07 | P98: 1.6192081e-06
C99: 4.1519105e-08 | D99: 1.9114833e-07 | E99: 7.1068434e-07 | F99: 2.074433e-06 | G99: 5.1622772e-06 | L99: 4.6991908e-08 | M99: 2.0361857e-07 | N99: 7.226981e-07 | O99: 2.0355675e-06 | P99: 4.8674614e-06
C100: 1.3095534e-07 | D100: 4.5067252e-07 | E100: 1.6136287e-06 | F100: 5.1622772e-06 | G100: 1.560489e-05 | L100: 1.2993774e-07 | M100: 4.689984e-07 | N100: 1.6192081e-06 | O100: 4.8674614e-06 | P100: 1.3983873e-05
B103: σ2ΔV | C103: {=+MMULT(TRANSPOSE(_xlfn.ANCHORARRAY(C87)),MMULT(_xlfn.ANCHORARRAY(C96),_xlfn.ANCHORARRAY(C87)))} -> 371.16313 | K103: σ2ΔV | L103: {=+MMULT(TRANSPOSE(_xlfn.ANCHORARRAY(C87)),MMULT(_xlfn.ANCHORARRAY(L96),_xlfn.ANCHORARRAY(C87)))} -> 366.33005
B105: CI | C105: 0.95 | D105: 0.99 | K105: CI | L105: 0.95 | M105: 0.99
B106: Var | C106: =+SQRT($C$103)*(-1)*_xlfn.NORM.S.INV(1-C105) -> 31.689083 | D106: =+SQRT($C$103)*(-1)*_xlfn.NORM.S.INV(1-D105) -> 44.818475 | K106: Var | L106: =+SQRT($L$103)*(-1)*_xlfn.NORM.S.INV(1-L105) -> 31.482088 | M106: =+SQRT($L$103)*(-1)*_xlfn.NORM.S.INV(1-M105) -> 44.525718
B110: Var computation - hybrid approach
C112: =+C72 -> 45747 | D112: =+D72 -> 45838 | E112: =+E72 -> 46022 | F112: =+F72 -> 46387 | G112: =+G72 -> 47483
B113: =+B73 -> Cashflows | C113: =+C73 -> 150 | D113: =+D73 -> 350 | E113: =+E73 -> 3019.0297 | F113: =+F73 -> 12880.37 | G113: =+G73 -> 0
B114: Discount factor | C114: =+C74 -> 0.99328907 | D114: =+D74 -> 0.98766067 | E114: =+E74 -> 0.97759073 | F114: =+F74 -> 0.95694943 | G114: =+G74 -> 0.88087042
B116: PV of Cashflows | C116: =+C114*C113 -> 148.99336 | D116: =+D114*D113 -> 345.68124 | E116: =+E114*E113 -> 2951.3754 | F116: =+F114*F113 -> 12325.863 | G116: =+G114*G113 -> 0
B117: Cash | G117: =G79 -> 200
B118: Sum of PV | G118: =+SUM(C116:G116)+G117 -> 15971.913
B120: CI | C120: 0.95 | D120: 0.99 | N120: Check | Q120: =+SUM(Q130:Q338)-1 -> 0 | W120: =+SUM(W130:W390)-1 -> 0 | AB120: =+SUM(AB130:AB390)-1 -> 0
B121: Plain vanilla VaR | C121: {=-(INDEX(_xlfn.ANCHORARRAY(V130),MATCH(TRUE,X130:X350>=1-C120,0))-$C$124)} -> 27.190894 | D121: {=-(INDEX(_xlfn.ANCHORARRAY(V130),MATCH(TRUE,X130:X350>=1-D120,0))-$C$124)} -> 47.085678
B122: Interpolated Var | C122: =+_xlfn.LET(_xlpm.x_1,V132,_xlpm.x_2,V133,_xlpm.alfa_1,X132,_xlpm.alfa_2,X133,_xlpm.p,(1-C120),_xlpm.mu,C124,(-1)*(_xlpm.x_1*(_xlpm.alfa_2-_xlpm.p)/(_xlpm.alfa_2-_xlpm.alfa_1)+_xlpm.x_2*(_xlpm.p-_xlpm.alfa_1)/(_xlpm.alfa_2-_xlpm.alfa_1)-_xlpm.mu)) -> 27.704112 | D122: n.m.
B124: Mean | C124: =+SUMPRODUCT(O130:O181,Q130:Q181) -> 4.9969116
B125: Variance | C125: =+SUMPRODUCT(Q130:Q181,R130:R181) -> 366.8463
B126: Skewness | C126: =+(SUMPRODUCT(Q130:Q181,S130:S181)/(C125^(3/2))-3) -> -3.0983559
B127: Excess Kurtosis | C127: =+(SUMPRODUCT(Q130:Q181,T130:T181)/(C125^2))-3 -> -0.27553207 | AU127: Parametric
Z128: Hybrid | AU128: EWMA | AW128: SMA
B129: Ordering factor | C129: Date | D129: r 3m | E129: r 6m | F129: r 12m | G129: r 24m | H129: r 60m | I129: PZCB3M | J129: PZCB6M | K129: PZCB12M | L129: PZCB24M | M129: PZCB60M | N129: V | O129: ΔV | P129: λi | Q129: frequency | R129: (ΔV-μ)2 | S129: (ΔV-μ)3 | T129: (ΔV-μ)4 | V129: Sorted ΔV | W129: Frequency | X129: Cum Frequency | Z129: Bands | AA129: Band average | AB129: Frequency | AE129: Changes in the portfolio's value: frequency distribution | AU129: Cum. Freq. | AV129: PseudoN | AW129: Cum. Freq. | AX129: PseudoN
B130: =+B131+1 -> 52 | C130: =+'ZCB rates'!B214 -> 45299 | D130: =+'ZCB rates'!M214 -> -5.2283e-05 | E130: =+'ZCB rates'!N214 -> -0.00018955725 | F130: =+'ZCB rates'!O214 -> -0.0005993705 | G130: =+'ZCB rates'!P214 -> -0.001502658 | H130: =+'ZCB rates'!Q214 -> -0.0029541725 | I130: =+C$114*EXP(D130) -> 0.99323714 | J130: =+D$114*EXP(E130) -> 0.98747347 | K130: =+E$114*EXP(F130) -> 0.97700497 | L130: =+F$114*EXP(G130) -> 0.95551255 | M130: =+G$114*EXP(H130) -> 0.87827201 | N130: =+SUMPRODUCT(I130:M130,$C$113:$G$113)+$G$117 -> 15951.564 | O130: =+N130-$G$118 -> -20.349395 | P130: =+Lambda^B130 -> 0.04005423 | Q130: =+P130/$P$183 -> 0.0026633306 | R130: =+($O130-$C$124)^2 -> 642.43527 | S130: =+($O130-$C$124)^3 -> -16283.362 | T130: =+($O130-$C$124)^4 -> 412723.08 | V130: {=+_xlfn._xlws.SORT(O130:O181)} -> -42.088767 | W130: =+_xlfn.XLOOKUP(V130,$O$130:$O$181,$Q$130:$Q$181) -> 0.0297467 | X130: =+SUM($W$130:W130) -> 0.0297467 | Z130: =+Z131-$Z$142/2.5 -> -73.209259 | AU130: =+NORMDIST($Z130,0,SQRT($C$103),TRUE) -> 7.2348044e-05 | AW130: =+NORMDIST($Z130,0,SQRT($L$103),TRUE) -> 6.5390008e-05
B131: =+B132+1 -> 51 | C131: =+'ZCB rates'!B215 -> 45306 | D131: =+'ZCB rates'!M215 -> -0.0001351705 | E131: =+'ZCB rates'!N215 -> -0.000201389 | F131: =+'ZCB rates'!O215 -> -0.000272608 | G131: =+'ZCB rates'!P215 -> -0.000635092 | H131: =+'ZCB rates'!Q215 -> -0.00370114 | I131: =+C$114*EXP(D131) -> 0.99315482 | J131: =+D$114*EXP(E131) -> 0.98746179 | K131: =+E$114*EXP(F131) -> 0.97732427 | L131: =+F$114*EXP(G131) -> 0.95634188 | M131: =+G$114*EXP(H131) -> 0.87761622 | N131: =+SUMPRODUCT(I131:M131,$C$113:$G$113)+$G$117 -> 15963.193 | O131: =+N131-$G$118 -> -8.7197783 | P131: =+Lambda^B131 -> 0.042610883 | Q131: =+P131/$P$183 -> 0.0028333305 | R131: =+($O131-$C$124)^2 -> 188.14758 | S131: =+($O131-$C$124)^3 -> -2580.762 | T131: =+($O131-$C$124)^4 -> 35399.513 | V131: -41.33429 | W131: =+_xlfn.XLOOKUP(V131,$O$130:$O$181,$Q$130:$Q$181) -> 0.003411251 | X131: =+SUM($W$130:W131) -> 0.033157951 | Z131: =+Z132-$Z$142/2.5 -> -65.503022 | AA131: =+AVERAGE(Z130:Z131) -> -69.35614 | AB131: =SUMIFS($W$130:$W$181,_xlfn.ANCHORARRAY($V$130),">="&Z130,$V$130:$V$181,"<"&Z131) -> 0 | AU131: =+NORMDIST($Z131,0,SQRT($C$103),TRUE) -> 0.00033692927 | AV131: =+AU131-AU130 -> 0.00026458122 | AW131: =+NORMDIST($Z131,0,SQRT($L$103),TRUE) -> 0.00031040594 | AX131: =+AW131-AW130 -> 0.00024501593
B132: =+B133+1 -> 50 | C132: =+'ZCB rates'!B216 -> 45313 | D132: =+'ZCB rates'!M216 -> -5.253e-06 | E132: =+'ZCB rates'!N216 -> -2.8039e-05 | F132: =+'ZCB rates'!O216 -> -0.000100826 | G132: =+'ZCB rates'!P216 -> -0.000265792 | H132: =+'ZCB rates'!Q216 -> -0.00065293 | I132: =+C$114*EXP(D132) -> 0.99328385 | J132: =+D$114*EXP(E132) -> 0.98763298 | K132: =+E$114*EXP(F132) -> 0.97749217 | L132: =+F$114*EXP(G132) -> 0.95669512 | M132: =+G$114*EXP(H132) -> 0.88029546 | N132: =+SUMPRODUCT(I132:M132,$C$113:$G$113)+$G$117 -> 15968.33 | O132: =+N132-$G$118 -> -3.583716 | P132: =+Lambda^B132 -> 0.045330727 | Q132: =+P132/$P$183 -> 0.0030141813 | R132: =+($O132-$C$124)^2 -> 73.627169 | S132: =+($O132-$C$124)^3 -> -631.76731 | T132: =+($O132-$C$124)^4 -> 5420.96 | V132: -23.007237 | W132: =+_xlfn.XLOOKUP(V132,$O$130:$O$181,$Q$130:$Q$181) -> 0.0036289904 | X132: =+SUM($W$130:W132) -> 0.036786941 | Z132: =+Z133-$Z$142/2.5 -> -57.796784 | AA132: =+AVERAGE(Z131:Z132) -> -61.649903 | AB132: =SUMIFS($W$130:$W$181,_xlfn.ANCHORARRAY($V$130),">="&Z131,$V$130:$V$181,"<"&Z132) -> 0 | AU132: =+NORMDIST($Z132,0,SQRT($C$103),TRUE) -> 0.001349898 | AV132: =+AU132-AU131 -> 0.0010129688 | AW132: =+NORMDIST($Z132,0,SQRT($L$103),TRUE) -> 0.0012650213 | AX132: =+AW132-AW131 -> 0.00095461532
B133: =+B134+1 -> 49 | C133: =+'ZCB rates'!B217 -> 45320 | D133: =+'ZCB rates'!M217 -> 9.25595e-05 | E133: =+'ZCB rates'!N217 -> 0.000247486 | F133: =+'ZCB rates'!O217 -> 0.00070191 | G133: =+'ZCB rates'!P217 -> 0.001939312 | H133: =+'ZCB rates'!Q217 -> 0.00554748 | I133: =+C$114*EXP(D133) -> 0.99338101 | J133: =+D$114*EXP(E133) -> 0.98790513 | K133: =+E$114*EXP(F133) -> 0.97827715 | L133: =+F$114*EXP(G133) -> 0.95880706 | M133: =+G$114*EXP(H133) -> 0.88577061 | N133: =+SUMPRODUCT(I133:M133,$C$113:$G$113)+$G$117 -> 15998.012 | O133: =+N133-$G$118 -> 26.098568 | P133: =+Lambda^B133 -> 0.048224177 | Q133: =+P133/$P$183 -> 0.0032065759 | R133: =+($O133-$C$124)^2 -> 445.27991 | S133: =+($O133-$C$124)^3 -> 9396.1438 | T133: =+($O133-$C$124)^4 -> 198274.2 | V133: -22.193982 | W133: =+_xlfn.XLOOKUP(V133,$O$130:$O$181,$Q$130:$Q$181) -> 0.035814198 | X133: =+SUM($W$130:W133) -> 0.07260114 | Z133: =+Z134-$Z$142/2.5 -> -50.090546 | AA133: =+AVERAGE(Z132:Z133) -> -53.943665 | AB133: =SUMIFS($W$130:$W$181,_xlfn.ANCHORARRAY($V$130),">="&Z132,$V$130:$V$181,"<"&Z133) -> 0 | AU133: =+NORMDIST($Z133,0,SQRT($C$103),TRUE) -> 0.004661188 | AV133: =+AU133-AU132 -> 0.00331129 | AW133: =+NORMDIST($Z133,0,SQRT($L$103),TRUE) -> 0.0044340823 | AX133: =+AW133-AW132 -> 0.003169061
B134: =+B135+1 -> 48 | C134: =+'ZCB rates'!B218 -> 45327 | D134: =+'ZCB rates'!M218 -> 3.452e-06 | E134: =+'ZCB rates'!N218 -> -0.000207049 | F134: =+'ZCB rates'!O218 -> -0.00101263 | G134: =+'ZCB rates'!P218 -> -0.00311018 | H134: =+'ZCB rates'!Q218 -> -0.00746873 | I134: =+C$114*EXP(D134) -> 0.9932925 | J134: =+D$114*EXP(E134) -> 0.9874562 | K134: =+E$114*EXP(F134) -> 0.9766013 | L134: =+F$114*EXP(G134) -> 0.95397777 | M134: =+G$114*EXP(H134) -> 0.87431594 | N134: =+SUMPRODUCT(I134:M134,$C$113:$G$113)+$G$117 -> 15930.579 | O134: =+N134-$G$118 -> -41.33429 | P134: =+Lambda^B134 -> 0.051302316 | Q134: =+P134/$P$183 -> 0.003411251 | R134: =+($O134-$C$124)^2 -> 2146.5802 | S134: =+($O134-$C$124)^3 -> -99453.639 | T134: =+($O134-$C$124)^4 -> 4607806.5 | V134: -20.349395 | W134: =+_xlfn.XLOOKUP(V134,$O$130:$O$181,$Q$130:$Q$181) -> 0.0026633306 | X134: =+SUM($W$130:W134) -> 0.07526447 | Z134: =+Z135-$Z$142/2.5 -> -42.384308 | AA134: =+AVERAGE(Z133:Z134) -> -46.237427 | AB134: =SUMIFS($W$130:$W$181,_xlfn.ANCHORARRAY($V$130),">="&Z133,$V$130:$V$181,"<"&Z134) -> 0 | AU134: =+NORMDIST($Z134,0,SQRT($C$103),TRUE) -> 0.013903448 | AV134: =+AU134-AU133 -> 0.0092422595 | AW134: =+NORMDIST($Z134,0,SQRT($L$103),TRUE) -> 0.013398403 | AX134: =+AW134-AW133 -> 0.0089643204
B135: =+B136+1 -> 47 | C135: =+'ZCB rates'!B219 -> 45334 | D135: =+'ZCB rates'!M219 -> -1.02595e-05 | E135: =+'ZCB rates'!N219 -> -0.000130519 | F135: =+'ZCB rates'!O219 -> -0.000575476 | G135: =+'ZCB rates'!P219 -> -0.001726532 | H135: =+'ZCB rates'!Q219 -> -0.00347857 | I135: =+C$114*EXP(D135) -> 0.99327888 | J135: =+D$114*EXP(E135) -> 0.98753177 | K135: =+E$114*EXP(F135) -> 0.97702831 | L135: =+F$114*EXP(G135) -> 0.95529866 | M135: =+G$114*EXP(H135) -> 0.87781157 | N135: =+SUMPRODUCT(I135:M135,$C$113:$G$113)+$G$117 -> 15948.906 | O135: =+N135-$G$118 -> -23.007237 | P135: =+Lambda^B135 -> 0.054576932 | Q135: =+P135/$P$183 -> 0.0036289904 | R135: =+($O135-$C$124)^2 -> 784.23236 | S135: =+($O135-$C$124)^3 -> -21961.76 | T135: =+($O135-$C$124)^4 -> 615020.4 | V135: -18.843119 | W135: =+_xlfn.XLOOKUP(V135,$O$130:$O$181,$Q$130:$Q$181) -> 0.0041070511 | X135: =+SUM($W$130:W135) -> 0.079371521 | Z135: =+Z136-$Z$142/2.5 -> -34.67807 | AA135: =+AVERAGE(Z134:Z135) -> -38.531189 | AB135: =SUMIFS($W$130:$W$181,_xlfn.ANCHORARRAY($V$130),">="&Z134,$V$130:$V$181,"<"&Z135) -> 0.033157951 | AU135: =+NORMDIST($Z135,0,SQRT($C$103),TRUE) -> 0.035930319 | AV135: =+AU135-AU134 -> 0.022026872 | AW135: =+NORMDIST($Z135,0,SQRT($L$103),TRUE) -> 0.035005845 | AX135: =+AW135-AW134 -> 0.021607443
B136: =+B137+1 -> 46 | C136: =+'ZCB rates'!B220 -> 45341 | D136: =+'ZCB rates'!M220 -> 1.6597e-05 | E136: =+'ZCB rates'!N220 -> -3.9282e-05 | F136: =+'ZCB rates'!O220 -> -0.0002652 | G136: =+'ZCB rates'!P220 -> -0.000770884 | H136: =+'ZCB rates'!Q220 -> -0.00092422 | I136: =+C$114*EXP(D136) -> 0.99330556 | J136: =+D$114*EXP(E136) -> 0.98762188 | K136: =+E$114*EXP(F136) -> 0.97733151 | L136: =+F$114*EXP(G136) -> 0.95621202 | M136: =+G$114*EXP(H136) -> 0.88005668 | N136: =+SUMPRODUCT(I136:M136,$C$113:$G$113)+$G$117 -> 15961.621 | O136: =+N136-$G$118 -> -10.291856 | P136: =+Lambda^B136 -> 0.058060566 | Q136: =+P136/$P$183 -> 0.0038606281 | R136: =+($O136-$C$124)^2 -> 233.74642 | S136: =+($O136-$C$124)^3 -> -3573.6947 | T136: =+($O136-$C$124)^4 -> 54637.389 | V136: -18.249377 | W136: =+_xlfn.XLOOKUP(V136,$O$130:$O$181,$Q$130:$Q$181) -> 0.05522812 | X136: =+SUM($W$130:W136) -> 0.13459964 | Z136: =+Z137-$Z$142/2.5 -> -26.971832 | AA136: =+AVERAGE(Z135:Z136) -> -30.824951 | AB136: =SUMIFS($W$130:$W$181,_xlfn.ANCHORARRAY($V$130),">="&Z135,$V$130:$V$181,"<"&Z136) -> 0 | AU136: =+NORMDIST($Z136,0,SQRT($C$103),TRUE) -> 0.080756659 | AV136: =+AU136-AU135 -> 0.04482634 | AW136: =+NORMDIST($Z136,0,SQRT($L$103),TRUE) -> 0.079387277 | AX136: =+AW136-AW135 -> 0.044381431
B137: =+B138+1 -> 45 | C137: =+'ZCB rates'!B221 -> 45348 | D137: =+'ZCB rates'!M221 -> -1.809e-05 | E137: =+'ZCB rates'!N221 -> -0.000126441 | F137: =+'ZCB rates'!O221 -> -0.000500356 | G137: =+'ZCB rates'!P221 -> -0.001406192 | H137: =+'ZCB rates'!Q221 -> -0.00278094 | I137: =+C$114*EXP(D137) -> 0.9932711 | J137: =+D$114*EXP(E137) -> 0.9875358 | K137: =+E$114*EXP(F137) -> 0.97710171 | L137: =+F$114*EXP(G137) -> 0.95560473 | M137: =+G$114*EXP(H137) -> 0.87842417 | N137: =+SUMPRODUCT(I137:M137,$C$113:$G$113)+$G$117 -> 15953.07 | O137: =+N137-$G$118 -> -18.843119 | P137: =+Lambda^B137 -> 0.06176656 | Q137: =+P137/$P$183 -> 0.0041070511 | R137: =+($O137-$C$124)^2 -> 568.34708 | S137: =+($O137-$C$124)^3 -> -13549.412 | T137: =+($O137-$C$124)^4 -> 323018.4 | V137: -15.105522 | W137: =+_xlfn.XLOOKUP(V137,$O$130:$O$181,$Q$130:$Q$181) -> 0.0086297033 | X137: =+SUM($W$130:W137) -> 0.14322934 | Z137: =+Z138-$Z$142/2.5 -> -19.265595 | AA137: =+AVERAGE(Z136:Z137) -> -23.118713 | AB137: =SUMIFS($W$130:$W$181,_xlfn.ANCHORARRAY($V$130),">="&Z136,$V$130:$V$181,"<"&Z137) -> 0.042106519 | AU137: =+NORMDIST($Z137,0,SQRT($C$103),TRUE) -> 0.15865525 | AV137: =+AU137-AU136 -> 0.077898595 | AW137: =+NORMDIST($Z137,0,SQRT($L$103),TRUE) -> 0.15706952 | AX137: =+AW137-AW136 -> 0.077682246
B138: =+B139+1 -> 44 | C138: =+'ZCB rates'!B222 -> 45355 | D138: =+'ZCB rates'!M222 -> -6.049e-06 | E138: =+'ZCB rates'!N222 -> 7.0021e-05 | F138: =+'ZCB rates'!O222 -> 0.000410218 | G138: =+'ZCB rates'!P222 -> 0.001554184 | H138: =+'ZCB rates'!Q222 -> 0.00602025 | I138: =+C$114*EXP(D138) -> 0.99328306 | J138: =+D$114*EXP(E138) -> 0.98772983 | K138: =+E$114*EXP(F138) -> 0.97799184 | L138: =+F$114*EXP(G138) -> 0.95843787 | M138: =+G$114*EXP(H138) -> 0.88618947 | N138: =+SUMPRODUCT(I138:M138,$C$113:$G$113)+$G$117 -> 15992.319 | O138: =+N138-$G$118 -> 20.405814 | P138: =+Lambda^B138 -> 0.065709106 | Q138: =+P138/$P$183 -> 0.0043692033 | R138: =+($O138-$C$124)^2 -> 237.43427 | S138: =+($O138-$C$124)^3 -> 3658.6014 | T138: =+($O138-$C$124)^4 -> 56375.032 | V138: -13.001408 | W138: =+_xlfn.XLOOKUP(V138,$O$130:$O$181,$Q$130:$Q$181) -> 0.038100211 | X138: =+SUM($W$130:W138) -> 0.18132956 | Z138: =+Z139-$Z$142/2.5 -> -11.559357 | AA138: =+AVERAGE(Z137:Z138) -> -15.412476 | AB138: =SUMIFS($W$130:$W$181,_xlfn.ANCHORARRAY($V$130),">="&Z137,$V$130:$V$181,"<"&Z138) -> 0.11280272 | AU138: =+NORMDIST($Z138,0,SQRT($C$103),TRUE) -> 0.27425312 | AV138: =+AU138-AU137 -> 0.11559786 | AW138: =+NORMDIST($Z138,0,SQRT($L$103),TRUE) -> 0.2729401 | AX138: =+AW138-AW137 -> 0.11587058
B139: =+B140+1 -> 43 | C139: =+'ZCB rates'!B223 -> 45362 | D139: =+'ZCB rates'!M223 -> -5.8932e-05 | E139: =+'ZCB rates'!N223 -> -5.0985e-05 | F139: =+'ZCB rates'!O223 -> 6.262e-05 | G139: =+'ZCB rates'!P223 -> 0.00028914 | H139: =+'ZCB rates'!Q223 -> -0.00050232 | I139: =+C$114*EXP(D139) -> 0.99323053 | J139: =+D$114*EXP(E139) -> 0.98761032 | K139: =+E$114*EXP(F139) -> 0.97765195 | L139: =+F$114*EXP(G139) -> 0.95722617 | M139: =+G$114*EXP(H139) -> 0.88042805 | N139: =+SUMPRODUCT(I139:M139,$C$113:$G$113)+$G$117 -> 15975.636 | O139: =+N139-$G$118 -> 3.722832 | P139: =+Lambda^B139 -> 0.069903304 | Q139: =+P139/$P$183 -> 0.0046480886 | R139: =+($O139-$C$124)^2 -> 1.6232789 | S139: =+($O139-$C$124)^3 -> -2.0681865 | T139: =+($O139-$C$124)^4 -> 2.6350343 | V139: -11.619255 | W139: =+_xlfn.XLOOKUP(V139,$O$130:$O$181,$Q$130:$Q$181) -> 0.0067376319 | X139: =+SUM($W$130:W139) -> 0.18806719 | Z139: =+Z140-$Z$142/2.5 -> -3.8531189 | AA139: =+AVERAGE(Z138:Z139) -> -7.7062378 | AB139: =SUMIFS($W$130:$W$181,_xlfn.ANCHORARRAY($V$130),">="&Z138,$V$130:$V$181,"<"&Z139) -> 0.13184756 | AU139: =+NORMDIST($Z139,0,SQRT($C$103),TRUE) -> 0.42074029 | AV139: =+AU139-AU138 -> 0.14648717 | AW139: =+NORMDIST($Z139,0,SQRT($L$103),TRUE) -> 0.42022614 | AX139: =+AW139-AW138 -> 0.14728603
B140: =+B141+1 -> 42 | C140: =+'ZCB rates'!B224 -> 45369 | D140: =+'ZCB rates'!M224 -> 7.26785e-05 | E140: =+'ZCB rates'!N224 -> 6.8632e-05 | F140: =+'ZCB rates'!O224 -> -8.2632e-05 | G140: =+'ZCB rates'!P224 -> -0.000600196 | H140: =+'ZCB rates'!Q224 -> -0.00186176 | I140: =+C$114*EXP(D140) -> 0.99336126 | J140: =+D$114*EXP(E140) -> 0.98772846 | K140: =+E$114*EXP(F140) -> 0.97750996 | L140: =+F$114*EXP(G140) -> 0.95637525 | M140: =+G$114*EXP(H140) -> 0.87923197 | N140: =+SUMPRODUCT(I140:M140,$C$113:$G$113)+$G$117 -> 15964.308 | O140: =+N140-$G$118 -> -7.6050275 | P140: =+Lambda^B140 -> 0.074365217 | Q140: =+P140/$P$183 -> 0.0049447752 | R140: =+($O140-$C$124)^2 -> 158.80887 | S140: =+($O140-$C$124)^3 -> -2001.2997 | T140: =+($O140-$C$124)^4 -> 25220.257 | V140: -11.41973 | W140: =+_xlfn.XLOOKUP(V140,$O$130:$O$181,$Q$130:$Q$181) -> 0.012509177 | X140: =+SUM($W$130:W140) -> 0.20057636 | Z140: =+Z141-$Z$142/2.5 -> 3.8531189 | AA140: =+AVERAGE(Z139:Z140) -> 0 | AB140: =SUMIFS($W$130:$W$181,_xlfn.ANCHORARRAY($V$130),">="&Z139,$V$130:$V$181,"<"&Z140) -> 0.18799676 | AU140: =+NORMDIST($Z140,0,SQRT($C$103),TRUE) -> 0.57925971 | AV140: =+AU140-AU139 -> 0.15851942 | AW140: =+NORMDIST($Z140,0,SQRT($L$103),TRUE) -> 0.57977386 | AX140: =+AW140-AW139 -> 0.15954773
B141: =+B142+1 -> 41 | C141: =+'ZCB rates'!B225 -> 45376 | D141: =+'ZCB rates'!M225 -> 0.00011035063 | E141: =+'ZCB rates'!N225 -> 0.00021406475 | F141: =+'ZCB rates'!O225 -> 0.0004157255 | G141: =+'ZCB rates'!P225 -> 0.00084628 | H141: =+'ZCB rates'!Q225 -> 0.002457615 | I141: =+C$114*EXP(D141) -> 0.99339869 | J141: =+D$114*EXP(E141) -> 0.98787212 | K141: =+E$114*EXP(F141) -> 0.97799723 | L141: =+F$114*EXP(G141) -> 0.95775962 | M141: =+G$114*EXP(H141) -> 0.88303792 | N141: =+SUMPRODUCT(I141:M141,$C$113:$G$113)+$G$117 -> 15983.666 | O141: =+N141-$G$118 -> 11.753212 | P141: =+Lambda^B141 -> 0.079111933 | Q141: =+P141/$P$183 -> 0.0052603991 | R141: =+($O141-$C$124)^2 -> 45.647598 | S141: =+($O141-$C$124)^3 -> 308.4089 | T141: =+($O141-$C$124)^4 -> 2083.7032 | V141: -10.291856 | W141: =+_xlfn.XLOOKUP(V141,$O$130:$O$181,$Q$130:$Q$181) -> 0.0038606281 | X141: =+SUM($W$130:W141) -> 0.20443699 | Z141: =+Z142-$Z$142/2.5 -> 11.559357 | AA141: =+AVERAGE(Z140:Z141) -> 7.7062378 | AB141: =SUMIFS($W$130:$W$181,_xlfn.ANCHORARRAY($V$130),">="&Z140,$V$130:$V$181,"<"&Z141) -> 0.10785171 | AU141: =+NORMDIST($Z141,0,SQRT($C$103),TRUE) -> 0.72574688 | AV141: =+AU141-AU140 -> 0.14648717 | AW141: =+NORMDIST($Z141,0,SQRT($L$103),TRUE) -> 0.7270599 | AX141: =+AW141-AW140 -> 0.14728603
B142: =+B143+1 -> 40 | C142: =+'ZCB rates'!B226 -> 45383 | D142: =+'ZCB rates'!M226 -> 1.2981875e-05 | E142: =+'ZCB rates'!N226 -> 1.2695e-05 | F142: =+'ZCB rates'!O226 -> -3.94025e-05 | G142: =+'ZCB rates'!P226 -> -0.000369965 | H142: =+'ZCB rates'!Q226 -> -0.0026551875 | I142: =+C$114*EXP(D142) -> 0.99330196 | J142: =+D$114*EXP(E142) -> 0.98767321 | K142: =+E$114*EXP(F142) -> 0.97755221 | L142: =+F$114*EXP(G142) -> 0.95659546 | M142: =+G$114*EXP(H142) -> 0.87853464 | N142: =+SUMPRODUCT(I142:M142,$C$113:$G$113)+$G$117 -> 15967.244 | O142: =+N142-$G$118 -> -4.6692612 | P142: =+Lambda^B142 -> 0.084161631 | Q142: =+P142/$P$183 -> 0.0055961693 | R142: =+($O142-$C$124)^2 -> 93.434895 | S142: =+($O142-$C$124)^3 -> -903.15784 | T142: =+($O142-$C$124)^4 -> 8730.0797 | V142: -10.157079 | W142: =+_xlfn.XLOOKUP(V142,$O$130:$O$181,$Q$130:$Q$181) -> 0.006333374 | X142: =+SUM($W$130:W142) -> 0.21077037 | Z142: =+SQRT(C103) -> 19.265595 | AA142: =+AVERAGE(Z141:Z142) -> 15.412476 | AB142: =SUMIFS($W$130:$W$181,_xlfn.ANCHORARRAY($V$130),">="&Z141,$V$130:$V$181,"<"&Z142) -> 0.1034555 | AU142: =+NORMDIST($Z142,0,SQRT($C$103),TRUE) -> 0.84134475 | AV142: =+AU142-AU141 -> 0.11559786 | AW142: =+NORMDIST($Z142,0,SQRT($L$103),TRUE) -> 0.84293048 | AX142: =+AW142-AW141 -> 0.11587058
B143: =+B144+1 -> 39 | C143: =+'ZCB rates'!B227 -> 45390 | D143: =+'ZCB rates'!M227 -> 1.8121e-05 | E143: =+'ZCB rates'!N227 -> -2.525375e-05 | F143: =+'ZCB rates'!O227 -> -0.000213719 | G143: =+'ZCB rates'!P227 -> -0.000657671 | H143: =+'ZCB rates'!Q227 -> -0.0006815575 | I143: =+C$114*EXP(D143) -> 0.99330707 | J143: =+D$114*EXP(E143) -> 0.98763573 | K143: =+E$114*EXP(F143) -> 0.97738183 | L143: =+F$114*EXP(G143) -> 0.95632028 | M143: =+G$114*EXP(H143) -> 0.88027026 | N143: =+SUMPRODUCT(I143:M143,$C$113:$G$113)+$G$117 -> 15963.173 | O143: =+N143-$G$118 -> -8.740425 | P143: =+Lambda^B143 -> 0.08953365 | Q143: =+P143/$P$183 -> 0.0059533716 | R143: =+($O143-$C$124)^2 -> 188.71442 | S143: =+($O143-$C$124)^3 -> -2592.4335 | T143: =+($O143-$C$124)^4 -> 35613.131 | V143: -8.740425 | W143: =+_xlfn.XLOOKUP(V143,$O$130:$O$181,$Q$130:$Q$181) -> 0.0059533716 | X143: =+SUM($W$130:W143) -> 0.21672374 | Z143: =+Z142+$Z$142/2.5 -> 26.971832 | AA143: =+AVERAGE(Z142:Z143) -> 23.118713 | AB143: =SUMIFS($W$130:$W$181,_xlfn.ANCHORARRAY($V$130),">="&Z142,$V$130:$V$181,"<"&Z143) -> 0.11180194 | AU143: =+NORMDIST($Z143,0,SQRT($C$103),TRUE) -> 0.91924334 | AV143: =+AU143-AU142 -> 0.077898595 | AW143: =+NORMDIST($Z143,0,SQRT($L$103),TRUE) -> 0.92061272 | AX143: =+AW143-AW142 -> 0.077682246
B144: =+B145+1 -> 38 | C144: =+'ZCB rates'!B228 -> 45397 | D144: =+'ZCB rates'!M228 -> 3.1923e-05 | E144: =+'ZCB rates'!N228 -> 2.366e-05 | F144: =+'ZCB rates'!O228 -> -0.000113744 | G144: =+'ZCB rates'!P228 -> -0.00079818 | H144: =+'ZCB rates'!Q228 -> -0.00414373 | I144: =+C$114*EXP(D144) -> 0.99332078 | J144: =+D$114*EXP(E144) -> 0.98768404 | K144: =+E$114*EXP(F144) -> 0.97747954 | L144: =+F$114*EXP(G144) -> 0.95618592 | M144: =+G$114*EXP(H144) -> 0.87722788 | N144: =+SUMPRODUCT(I144:M144,$C$113:$G$113)+$G$117 -> 15961.756 | O144: =+N144-$G$118 -> -10.157079 | P144: =+Lambda^B144 -> 0.095248564 | Q144: =+P144/$P$183 -> 0.006333374 | R144: =+($O144-$C$124)^2 -> 229.64343 | S144: =+($O144-$C$124)^3 -> -3480.0144 | T144: =+($O144-$C$124)^4 -> 52736.106 | V144: -8.7197783 | W144: =+_xlfn.XLOOKUP(V144,$O$130:$O$181,$Q$130:$Q$181) -> 0.0028333305 | X144: =+SUM($W$130:W144) -> 0.21955707 | Z144: =+Z143+$Z$142/2.5 -> 34.67807 | AA144: =+AVERAGE(Z143:Z144) -> 30.824951 | AB144: =SUMIFS($W$130:$W$181,_xlfn.ANCHORARRAY($V$130),">="&Z143,$V$130:$V$181,"<"&Z144) -> 0.11268792 | AU144: =+NORMDIST($Z144,0,SQRT($C$103),TRUE) -> 0.96406968 | AV144: =+AU144-AU143 -> 0.04482634 | AW144: =+NORMDIST($Z144,0,SQRT($L$103),TRUE) -> 0.96499415 | AX144: =+AW144-AW143 -> 0.044381431
B145: =+B146+1 -> 37 | C145: =+'ZCB rates'!B229 -> 45404 | D145: =+'ZCB rates'!M229 -> 6.5844e-05 | E145: =+'ZCB rates'!N229 -> 4.3974e-05 | F145: =+'ZCB rates'!O229 -> -0.000172556 | G145: =+'ZCB rates'!P229 -> -0.000903796 | H145: =+'ZCB rates'!Q229 -> -0.00285235 | I145: =+C$114*EXP(D145) -> 0.99335447 | J145: =+D$114*EXP(E145) -> 0.9877041 | K145: =+E$114*EXP(F145) -> 0.97742206 | L145: =+F$114*EXP(G145) -> 0.95608494 | M145: =+G$114*EXP(H145) -> 0.87836145 | N145: =+SUMPRODUCT(I145:M145,$C$113:$G$113)+$G$117 -> 15960.294 | O145: =+N145-$G$118 -> -11.619255 | P145: =+Lambda^B145 -> 0.10132826 | Q145: =+P145/$P$183 -> 0.0067376319 | R145: =+($O145-$C$124)^2 -> 276.09699 | S145: =+($O145-$C$124)^3 -> -4587.6735 | T145: =+($O145-$C$124)^4 -> 76229.547 | V145: -8.6987364 | W145: =+_xlfn.XLOOKUP(V145,$O$130:$O$181,$Q$130:$Q$181) -> 0.062503531 | X145: =+SUM($W$130:W145) -> 0.2820606 | Z145: =+Z144+$Z$142/2.5 -> 42.384308 | AA145: =+AVERAGE(Z144:Z145) -> 38.531189 | AB145: =SUMIFS($W$130:$W$181,_xlfn.ANCHORARRAY($V$130),">="&Z144,$V$130:$V$181,"<"&Z145) -> 0.039246727 | AU145: =+NORMDIST($Z145,0,SQRT($C$103),TRUE) -> 0.98609655 | AV145: =+AU145-AU144 -> 0.022026872 | AW145: =+NORMDIST($Z145,0,SQRT($L$103),TRUE) -> 0.9866016 | AX145: =+AW145-AW144 -> 0.021607443
B146: =+B147+1 -> 36 | C146: =+'ZCB rates'!B230 -> 45411 | D146: =+'ZCB rates'!M230 -> 3.0500125e-05 | E146: =+'ZCB rates'!N230 -> 4.010225e-05 | F146: =+'ZCB rates'!O230 -> 3.2234e-05 | G146: =+'ZCB rates'!P230 -> 4.5702e-05 | H146: =+'ZCB rates'!Q230 -> 0.0008572625 | I146: =+C$114*EXP(D146) -> 0.99331937 | J146: =+D$114*EXP(E146) -> 0.98770028 | K146: =+E$114*EXP(F146) -> 0.97762225 | L146: =+F$114*EXP(G146) -> 0.95699317 | M146: =+G$114*EXP(H146) -> 0.88162588 | N146: =+SUMPRODUCT(I146:M146,$C$113:$G$113)+$G$117 -> 15972.59 | O146: =+N146-$G$118 -> 0.6768729 | P146: =+Lambda^B146 -> 0.10779602 | Q146: =+P146/$P$183 -> 0.0071676935 | R146: =+($O146-$C$124)^2 -> 18.662734 | S146: =+($O146-$C$124)^3 -> -80.623734 | T146: =+($O146-$C$124)^4 -> 348.29765 | V146: -7.9036773 | W146: =+_xlfn.XLOOKUP(V146,$O$130:$O$181,$Q$130:$Q$181) -> 0.0091805355 | X146: =+SUM($W$130:W146) -> 0.29124113 | Z146: =+Z145+$Z$142/2.5 -> 50.090546 | AA146: =+AVERAGE(Z145:Z146) -> 46.237427 | AB146: =SUMIFS($W$130:$W$181,_xlfn.ANCHORARRAY($V$130),">="&Z145,$V$130:$V$181,"<"&Z146) -> 0.017044705 | AU146: =+NORMDIST($Z146,0,SQRT($C$103),TRUE) -> 0.99533881 | AV146: =+AU146-AU145 -> 0.0092422595 | AW146: =+NORMDIST($Z146,0,SQRT($L$103),TRUE) -> 0.99556592 | AX146: =+AW146-AW145 -> 0.0089643204
B147: =+B148+1 -> 35 | C147: =+'ZCB rates'!B231 -> 45418 | D147: =+'ZCB rates'!M231 -> 5.6890375e-05 | E147: =+'ZCB rates'!N231 -> 0.00011938075 | F147: =+'ZCB rates'!O231 -> 0.000271978 | G147: =+'ZCB rates'!P231 -> 0.000705078 | H147: =+'ZCB rates'!Q231 -> 0.0025345575 | I147: =+C$114*EXP(D147) -> 0.99334558 | J147: =+D$114*EXP(E147) -> 0.98777859 | K147: =+E$114*EXP(F147) -> 0.97785665 | L147: =+F$114*EXP(G147) -> 0.9576244 | M147: =+G$114*EXP(H147) -> 0.88310587 | N147: =+SUMPRODUCT(I147:M147,$C$113:$G$113)+$G$117 -> 15981.46 | O147: =+N147-$G$118 -> 9.5463246 | P147: =+Lambda^B147 -> 0.11467662 | Q147: =+P147/$P$183 -> 0.0076252059 | R147: =+($O147-$C$124)^2 -> 20.697158 | S147: =+($O147-$C$124)^3 -> 94.159921 | T147: =+($O147-$C$124)^4 -> 428.37237 | V147: -7.6050275 | W147: =+_xlfn.XLOOKUP(V147,$O$130:$O$181,$Q$130:$Q$181) -> 0.0049447752 | X147: =+SUM($W$130:W147) -> 0.29618591 | Z147: =+Z146+$Z$142/2.5 -> 57.796784 | AA147: =+AVERAGE(Z146:Z147) -> 53.943665 | AB147: =SUMIFS($W$130:$W$181,_xlfn.ANCHORARRAY($V$130),">="&Z146,$V$130:$V$181,"<"&Z147) -> 0 | AU147: =+NORMDIST($Z147,0,SQRT($C$103),TRUE) -> 0.9986501 | AV147: =+AU147-AU146 -> 0.00331129 | AW147: =+NORMDIST($Z147,0,SQRT($L$103),TRUE) -> 0.99873498 | AX147: =+AW147-AW146 -> 0.003169061
B148: =+B149+1 -> 34 | C148: =+'ZCB rates'!B232 -> 45425 | D148: =+'ZCB rates'!M232 -> 6.5198e-05 | E148: =+'ZCB rates'!N232 -> 7.1894e-05 | F148: =+'ZCB rates'!O232 -> -1.3506e-05 | G148: =+'ZCB rates'!P232 -> -0.000274432 | H148: =+'ZCB rates'!Q232 -> -0.00039521 | I148: =+C$114*EXP(D148) -> 0.99335383 | J148: =+D$114*EXP(E148) -> 0.98773168 | K148: =+E$114*EXP(F148) -> 0.97757753 | L148: =+F$114*EXP(G148) -> 0.95668685 | M148: =+G$114*EXP(H148) -> 0.88052236 | N148: =+SUMPRODUCT(I148:M148,$C$113:$G$113)+$G$117 -> 15968.526 | O148: =+N148-$G$118 -> -3.3874405 | P148: =+Lambda^B148 -> 0.1219964 | Q148: =+P148/$P$183 -> 0.0081119211 | R148: =+($O148-$C$124)^2 -> 70.29736 | S148: =+($O148-$C$124)^3 -> -589.39782 | T148: =+($O148-$C$124)^4 -> 4941.7188 | V148: -4.6692612 | W148: =+_xlfn.XLOOKUP(V148,$O$130:$O$181,$Q$130:$Q$181) -> 0.0055961693 | X148: =+SUM($W$130:W148) -> 0.30178208 | Z148: =+Z147+$Z$142/2.5 -> 65.503022 | AA148: =+AVERAGE(Z147:Z148) -> 61.649903 | AB148: =SUMIFS($W$130:$W$181,_xlfn.ANCHORARRAY($V$130),">="&Z147,$V$130:$V$181,"<"&Z148) -> 0 | AU148: =+NORMDIST($Z148,0,SQRT($C$103),TRUE) -> 0.99966307 | AV148: =+AU148-AU147 -> 0.0010129688 | AW148: =+NORMDIST($Z148,0,SQRT($L$103),TRUE) -> 0.99968959 | AX148: =+AW148-AW147 -> 0.00095461532
B149: =+B150+1 -> 33 | C149: =+'ZCB rates'!B233 -> 45432 | D149: =+'ZCB rates'!M233 -> -2.2696e-05 | E149: =+'ZCB rates'!N233 -> -0.00010135 | F149: =+'ZCB rates'!O233 -> -0.000373716 | G149: =+'ZCB rates'!P233 -> -0.001133572 | H149: =+'ZCB rates'!Q233 -> -0.0032283 | I149: =+C$114*EXP(D149) -> 0.99326653 | J149: =+D$114*EXP(E149) -> 0.98756058 | K149: =+E$114*EXP(F149) -> 0.97722546 | L149: =+F$114*EXP(G149) -> 0.95586528 | M149: =+G$114*EXP(H149) -> 0.87803129 | N149: =+SUMPRODUCT(I149:M149,$C$113:$G$113)+$G$117 -> 15956.808 | O149: =+N149-$G$118 -> -15.105522 | P149: =+Lambda^B149 -> 0.12978341 | Q149: =+P149/$P$183 -> 0.0086297033 | R149: =+($O149-$C$124)^2 -> 404.10783 | S149: =+($O149-$C$124)^3 -> -8123.5507 | T149: =+($O149-$C$124)^4 -> 163303.14 | V149: -3.9146413 | W149: =+_xlfn.XLOOKUP(V149,$O$130:$O$181,$Q$130:$Q$181) -> 0.018132664 | X149: =+SUM($W$130:W149) -> 0.31991474 | Z149: =+Z148+$Z$142/2.5 -> 73.209259 | AA149: =+AVERAGE(Z148:Z149) -> 69.35614 | AB149: =SUMIFS($W$130:$W$181,_xlfn.ANCHORARRAY($V$130),">="&Z148,$V$130:$V$181,"<"&Z149) -> 0 | AU149: =+NORMDIST($Z149,0,SQRT($C$103),TRUE) -> 0.99992765 | AV149: =+AU149-AU148 -> 0.00026458122 | AW149: =+NORMDIST($Z149,0,SQRT($L$103),TRUE) -> 0.99993461 | AX149: =+AW149-AW148 -> 0.00024501593
...
